Workbook
Name status: buildReport!$I$3:$I$1000
Name fixVersion: JIRA!$R$2:$R$1000
Name Issue_Type: JIRA!$A$2:$A$1000
Name impact_of_failure: buildReport!$E$3:$E$1000
Name linked_ID: buildReport!$K$3:$K$1000
Name Likelihood_of_failure: buildReport!$F$3:$F$1000
Name jira_priority: JIRA!$D$2:$D$1000
Name issue_ID: JIRA!$B$2:$B$1000
Name release: buildReport!$J$3:$J$1000
Name jira_status: JIRA!$E$2:$E$1000
Name Automation_status: buildReport!$H$3:$H$1000
Name can_be_automated: buildReport!$G$3:$G$1000

Sheet JIRA
A1: Issue Type | B1: Key | C1: Summary | D1: Priority | E1: Status | F1: Created | G1: Linked Issues | H1: Project | I1: Sport | J1: Squad | K1: Components | L1: Test event date | M1: customfield_10436 | N1: customfield_10416 | O1: customfield_10494 | P1: Links | Q1: Status Category Changed | R1: Fix versions | S1: Labels | T1: Software Release | U1: Release date
A2: Bug | B2: =HYPERLINK("https://hawk-eye.atlassian.net/browse/BAS-1354?atlOrigin=eyJpIjoiYzgwYTQ0ZjEyNzQzNGJhN2JmNjEyZTM0NmRhZWZhNjIiLCJwIjoic2hlZXRzLWppcmEifQ","BAS-1354") -> BAS-1354 | C2: NBA are reporting that the last record of `processed.pose.clean` files are truncated. | D2: P3 - Medium | E2: In Progress | F2: 45939.382 | G2: =HYPERLINK("https://hawk-eye.atlassian.net/browse/BAS-1226?atlOrigin=eyJpIjoiYzgwYTQ0ZjEyNzQzNGJhN2JmNjEyZTM0NmRhZWZhNjIiLCJwIjoic2hlZXRzLWppcmEifQ","BAS-1226") -> BAS-1226 | H2: Basketball & Baseball Data Platform | M2: [no field found] | N2: [no field found] | O2: [no field found] | Q2: 45940.467 | S2: Basketball | U2: 45692
A3: Story | B3: =HYPERLINK("https://hawk-eye.atlassian.net/browse/BAS-1353?atlOrigin=eyJpIjoiYzgwYTQ0ZjEyNzQzNGJhN2JmNjEyZTM0NmRhZWZhNjIiLCJwIjoic2hlZXRzLWppcmEifQ","BAS-1353") -> BAS-1353 | C3: Interpret new 'heave' event from NGSS | D3: P3 - Medium | E3: Backlog | F3: 45938.565 | G3: =HYPERLINK("https://hawk-eye.atlassian.net/browse/?atlOrigin=eyJpIjoiYzgwYTQ0ZjEyNzQzNGJhN2JmNjEyZTM0NmRhZWZhNjIiLCJwIjoic2hlZXRzLWppcmEifQ","") | H3: Basketball & Baseball Data Platform | M3: [no field found] | N3: [no field found] | O3: [no field found] | Q3: 45938.565 | S3: Basketball;Feature | U3: 45691
A4: Bug | B4: =HYPERLINK("https://hawk-eye.atlassian.net/browse/BAS-1352?atlOrigin=eyJpIjoiYzgwYTQ0ZjEyNzQzNGJhN2JmNjEyZTM0NmRhZWZhNjIiLCJwIjoic2hlZXRzLWppcmEifQ","BAS-1352") -> BAS-1352 | C4: Live Event feed numbering | D4: P2 - High | E4: Done | F4: 45937.518 | G4: =HYPERLINK("https://hawk-eye.atlassian.net/browse/BAS-1274?atlOrigin=eyJpIjoiYzgwYTQ0ZjEyNzQzNGJhN2JmNjEyZTM0NmRhZWZhNjIiLCJwIjoic2hlZXRzLWppcmEifQ","BAS-1274") -> BAS-1274 | H4: Basketball & Baseball Data Platform | M4: [no field found] | N4: [no field found] | O4: [no field found] | Q4: 45944.6 | R4: 2.42 | S4: Basketball;Feature | T4: 1 | U4: 45658
A5: Story | B5: =HYPERLINK("https://hawk-eye.atlassian.net/browse/BAS-1351?atlOrigin=eyJpIjoiYzgwYTQ0ZjEyNzQzNGJhN2JmNjEyZTM0NmRhZWZhNjIiLCJwIjoic2hlZXRzLWppcmEifQ","BAS-1351") -> BAS-1351 | C5: NBA to Access Status Update API via a Key | D5: P2 - High | E5: Backlog | F5: 45937.457 | G5: =HYPERLINK("https://hawk-eye.atlassian.net/browse/?atlOrigin=eyJpIjoiYzgwYTQ0ZjEyNzQzNGJhN2JmNjEyZTM0NmRhZWZhNjIiLCJwIjoic2hlZXRzLWppcmEifQ","") | H5: Basketball & Baseball Data Platform | M5: [no field found] | N5: [no field found] | O5: [no field found] | Q5: 45937.457 | S5: Basketball;DevOps;Feature | U5: 45667
A6: Bug | B6: =HYPERLINK("https://hawk-eye.atlassian.net/browse/BAS-1344?atlOrigin=eyJpIjoiYzgwYTQ0ZjEyNzQzNGJhN2JmNjEyZTM0NmRhZWZhNjIiLCJwIjoic2hlZXRzLWppcmEifQ","BAS-1344") -> BAS-1344 | C6: SFG cannot authenticate with Dynamo DB in AWS | D6: P1 - Highest | E6: Closed | F6: 45919.617 | G6: =HYPERLINK("https://hawk-eye.atlassian.net/browse/BAS-1226?atlOrigin=eyJpIjoiYzgwYTQ0ZjEyNzQzNGJhN2JmNjEyZTM0NmRhZWZhNjIiLCJwIjoic2hlZXRzLWppcmEifQ","BAS-1226") -> BAS-1226 | H6: Basketball & Baseball Data Platform | M6: [no field found] | N6: [no field found] | O6: [no field found] | Q6: 45924.406 | S6: Basketball;Feature | U6: 45667
A7: Bug | B7: =HYPERLINK("https://hawk-eye.atlassian.net/browse/BAS-1342?atlOrigin=eyJpIjoiYzgwYTQ0ZjEyNzQzNGJhN2JmNjEyZTM0NmRhZWZhNjIiLCJwIjoic2hlZXRzLWppcmEifQ","BAS-1342") -> BAS-1342 | C7: Status Update API updates not showing in DynamoDB | D7: P2 - High | E7: Closed | F7: 45916.744 | G7: =HYPERLINK("https://hawk-eye.atlassian.net/browse/?atlOrigin=eyJpIjoiYzgwYTQ0ZjEyNzQzNGJhN2JmNjEyZTM0NmRhZWZhNjIiLCJwIjoic2hlZXRzLWppcmEifQ","") | H7: Basketball & Baseball Data Platform | M7: [no field found] | N7: [no field found] | O7: [no field found] | Q7: 45924.406 | R7: 2.41 | S7: Basketball;Feature | T7: 1 | U7: 45658
A8: Story | B8: =HYPERLINK("https://hawk-eye.atlassian.net/browse/BAS-1338?atlOrigin=eyJpIjoiYzgwYTQ0ZjEyNzQzNGJhN2JmNjEyZTM0NmRhZWZhNjIiLCJwIjoic2hlZXRzLWppcmEifQ","BAS-1338") -> BAS-1338 | C8: Add Clock Events To Combine Events Feed & Join With NGSS Events | D8: P2 - High | E8: To Test | F8: 45912.153 | G8: =HYPERLINK("https://hawk-eye.atlassian.net/browse/BAS-1337?atlOrigin=eyJpIjoiYzgwYTQ0ZjEyNzQzNGJhN2JmNjEyZTM0NmRhZWZhNjIiLCJwIjoic2hlZXRzLWppcmEifQ","BAS-1337") -> BAS-1337 | H8: Basketball & Baseball Data Platform | M8: [no field found] | N8: [no field found] | O8: [no field found] | Q8: 45923.498 | R8: 2.42 | S8: Basketball;Feature | T8: 1 | U8: 45658
A9: Story | B9: =HYPERLINK("https://hawk-eye.atlassian.net/browse/BAS-1337?atlOrigin=eyJpIjoiYzgwYTQ0ZjEyNzQzNGJhN2JmNjEyZTM0NmRhZWZhNjIiLCJwIjoic2hlZXRzLWppcmEifQ","BAS-1337") -> BAS-1337 | C9: Add Clock Stop/Start Events to Live Events Feed | D9: P2 - High | E9: Closed | F9: 45911.763 | G9: =HYPERLINK("https://hawk-eye.atlassian.net/browse/BAS-1338?atlOrigin=eyJpIjoiYzgwYTQ0ZjEyNzQzNGJhN2JmNjEyZTM0NmRhZWZhNjIiLCJwIjoic2hlZXRzLWppcmEifQ","BAS-1338") -> BAS-1338 | H9: Basketball & Baseball Data Platform | M9: [no field found] | N9: [no field found] | O9: [no field found] | Q9: 45932.588 | R9: 2.41 | S9: Basketball;Feature | T9: 1 | U9: 45662
A10: Story | B10: =HYPERLINK("https://hawk-eye.atlassian.net/browse/BAS-1328?atlOrigin=eyJpIjoiYzgwYTQ0ZjEyNzQzNGJhN2JmNjEyZTM0NmRhZWZhNjIiLCJwIjoic2hlZXRzLWppcmEifQ","BAS-1328") -> BAS-1328 | C10: Starter project for Eden | D10: P5 - Lowest | E10: Backlog | F10: 45909.689 | G10: =HYPERLINK("https://hawk-eye.atlassian.net/browse/?atlOrigin=eyJpIjoiYzgwYTQ0ZjEyNzQzNGJhN2JmNjEyZTM0NmRhZWZhNjIiLCJwIjoic2hlZXRzLWppcmEifQ","") | H10: Basketball & Baseball Data Platform | M10: [no field found] | N10: [no field found] | O10: [no field found] | Q10: 45909.689 | S10: Basketball | U10: 45699
A11: Story | B11: =HYPERLINK("https://hawk-eye.atlassian.net/browse/BAS-1326?atlOrigin=eyJpIjoiYzgwYTQ0ZjEyNzQzNGJhN2JmNjEyZTM0NmRhZWZhNjIiLCJwIjoic2hlZXRzLWppcmEifQ","BAS-1326") -> BAS-1326 | C11: Add Chance To Score data to Officiating Events Feed | D11: P2 - High | E11: To Test | F11: 45901.727 | G11: =HYPERLINK("https://hawk-eye.atlassian.net/browse/?atlOrigin=eyJpIjoiYzgwYTQ0ZjEyNzQzNGJhN2JmNjEyZTM0NmRhZWZhNjIiLCJwIjoic2hlZXRzLWppcmEifQ","") | H11: Basketball & Baseball Data Platform | M11: [no field found] | N11: [no field found] | O11: [no field found] | Q11: 45943.405 | R11: 2.42 | S11: Basketball;Feature | U11: 45735
A12: Story | B12: =HYPERLINK("https://hawk-eye.atlassian.net/browse/BAS-1322?atlOrigin=eyJpIjoiYzgwYTQ0ZjEyNzQzNGJhN2JmNjEyZTM0NmRhZWZhNjIiLCJwIjoic2hlZXRzLWppcmEifQ","BAS-1322") -> BAS-1322 | C12: Allow scopes in the JWT to grant authorisation | D12: P5 - Lowest | E12: Closed | F12: 45897.48 | G12: =HYPERLINK("https://hawk-eye.atlassian.net/browse/?atlOrigin=eyJpIjoiYzgwYTQ0ZjEyNzQzNGJhN2JmNjEyZTM0NmRhZWZhNjIiLCJwIjoic2hlZXRzLWppcmEifQ","") | H12: Basketball & Baseball Data Platform | M12: [no field found] | N12: [no field found] | O12: [no field found] | Q12: 45924.404 | R12: 2.41 | S12: Basketball;Feature | U12: 45667
A13: Bug | B13: =HYPERLINK("https://hawk-eye.atlassian.net/browse/BAS-1321?atlOrigin=eyJpIjoiYzgwYTQ0ZjEyNzQzNGJhN2JmNjEyZTM0NmRhZWZhNjIiLCJwIjoic2hlZXRzLWppcmEifQ","BAS-1321") -> BAS-1321 | C13: Basket centre is not being reporting in processed feeds | D13: P2 - High | E13: Backlog | F13: 45894.707 | G13: =HYPERLINK("https://hawk-eye.atlassian.net/browse/?atlOrigin=eyJpIjoiYzgwYTQ0ZjEyNzQzNGJhN2JmNjEyZTM0NmRhZWZhNjIiLCJwIjoic2hlZXRzLWppcmEifQ","") | H13: Basketball & Baseball Data Platform | M13: [no field found] | N13: [no field found] | O13: [no field found] | Q13: 45894.707 | S13: Basketball;TechDebt | U13: 45667
A14: Story | B14: =HYPERLINK("https://hawk-eye.atlassian.net/browse/BAS-1320?atlOrigin=eyJpIjoiYzgwYTQ0ZjEyNzQzNGJhN2JmNjEyZTM0NmRhZWZhNjIiLCJwIjoic2hlZXRzLWppcmEifQ","BAS-1320") -> BAS-1320 | C14: Add arenaId to OpenAPI Spec | D14: P3 - Medium | E14: Closed | F14: 45889.758 | G14: =HYPERLINK("https://hawk-eye.atlassian.net/browse/BAS-1140?atlOrigin=eyJpIjoiYzgwYTQ0ZjEyNzQzNGJhN2JmNjEyZTM0NmRhZWZhNjIiLCJwIjoic2hlZXRzLWppcmEifQ","BAS-1140") -> BAS-1140 | H14: Basketball & Baseball Data Platform | M14: [no field found] | N14: [no field found] | O14: [no field found] | Q14: 45924.405 | R14: 2.41 | S14: Basketball;Feature | T14: 1 | U14: 45662
A15: Bug | B15: =HYPERLINK("https://hawk-eye.atlassian.net/browse/BAS-1318?atlOrigin=eyJpIjoiYzgwYTQ0ZjEyNzQzNGJhN2JmNjEyZTM0NmRhZWZhNjIiLCJwIjoic2hlZXRzLWppcmEifQ","BAS-1318") -> BAS-1318 | C15: Test Stream 2nd Game taking a long time to start publishing | D15: P3 - Medium | E15: Closed | F15: 45889.466 | G15: =HYPERLINK("https://hawk-eye.atlassian.net/browse/?atlOrigin=eyJpIjoiYzgwYTQ0ZjEyNzQzNGJhN2JmNjEyZTM0NmRhZWZhNjIiLCJwIjoic2hlZXRzLWppcmEifQ","") | H15: Basketball & Baseball Data Platform | M15: [no field found] | N15: [no field found] | O15: [no field found] | Q15: 45897.427 | S15: Basketball | T15: 1 | U15: 45662
A16: Story | B16: =HYPERLINK("https://hawk-eye.atlassian.net/browse/BAS-1316?atlOrigin=eyJpIjoiYzgwYTQ0ZjEyNzQzNGJhN2JmNjEyZTM0NmRhZWZhNjIiLCJwIjoic2hlZXRzLWppcmEifQ","BAS-1316") -> BAS-1316 | C16: Convert radians to degrees | D16: P1 - Highest | E16: Closed | F16: 45888.875 | G16: =HYPERLINK("https://hawk-eye.atlassian.net/browse/BAS-1317?atlOrigin=eyJpIjoiYzgwYTQ0ZjEyNzQzNGJhN2JmNjEyZTM0NmRhZWZhNjIiLCJwIjoic2hlZXRzLWppcmEifQ","BAS-1317") -> BAS-1317 | H16: Basketball & Baseball Data Platform | M16: [no field found] | N16: [no field found] | O16: [no field found] | Q16: 45932.697 | R16: 2.41 | S16: Basketball;Feature;Improvement | U16: 45667
A17: Story | B17: =HYPERLINK("https://hawk-eye.atlassian.net/browse/BAS-1303?atlOrigin=eyJpIjoiYzgwYTQ0ZjEyNzQzNGJhN2JmNjEyZTM0NmRhZWZhNjIiLCJwIjoic2hlZXRzLWppcmEifQ","BAS-1303") -> BAS-1303 | C17: Resend Updated List of 23/24 Games | D17: P3 - Medium | E17: Backlog | F17: 45874.512 | G17: =HYPERLINK("https://hawk-eye.atlassian.net/browse/BAS-1202?atlOrigin=eyJpIjoiYzgwYTQ0ZjEyNzQzNGJhN2JmNjEyZTM0NmRhZWZhNjIiLCJwIjoic2hlZXRzLWppcmEifQ","BAS-1202") -> BAS-1202 | H17: Basketball & Baseball Data Platform | M17: [no field found] | N17: [no field found] | O17: [no field found] | Q17: 45874.512 | S17: Basketball;CustomerRaised;Feature | U17: 45667
A18: Story | B18: =HYPERLINK("https://hawk-eye.atlassian.net/browse/BAS-1301?atlOrigin=eyJpIjoiYzgwYTQ0ZjEyNzQzNGJhN2JmNjEyZTM0NmRhZWZhNjIiLCJwIjoic2hlZXRzLWppcmEifQ","BAS-1301") -> BAS-1301 | C18: Cater for ReboundDeflection Event | D18: P2 - High | E18: Closed | F18: 45874.504 | G18: =HYPERLINK("https://hawk-eye.atlassian.net/browse/RTT-11010?atlOrigin=eyJpIjoiYzgwYTQ0ZjEyNzQzNGJhN2JmNjEyZTM0NmRhZWZhNjIiLCJwIjoic2hlZXRzLWppcmEifQ","RTT-11010") -> RTT-11010 | H18: Basketball & Baseball Data Platform | M18: [no field found] | N18: [no field found] | O18: [no field found] | Q18: 45937.416 | R18: 2.41 | S18: Basketball;Feature | U18: 45667
A19: Bug | B19: =HYPERLINK("https://hawk-eye.atlassian.net/browse/BAS-1299?atlOrigin=eyJpIjoiYzgwYTQ0ZjEyNzQzNGJhN2JmNjEyZTM0NmRhZWZhNjIiLCJwIjoic2hlZXRzLWppcmEifQ","BAS-1299") -> BAS-1299 | C19: Repush required radio button cannot be deselected | D19: P5 - Lowest | E19: Backlog | F19: 45873.336 | G19: =HYPERLINK("https://hawk-eye.atlassian.net/browse/BAS-1054?atlOrigin=eyJpIjoiYzgwYTQ0ZjEyNzQzNGJhN2JmNjEyZTM0NmRhZWZhNjIiLCJwIjoic2hlZXRzLWppcmEifQ","BAS-1054") -> BAS-1054 | H19: Basketball & Baseball Data Platform | M19: [no field found] | N19: [no field found] | O19: [no field found] | Q19: 45873.336 | S19: Basketball;Feature;Frontend | U19: 45667
A20: Story | B20: =HYPERLINK("https://hawk-eye.atlassian.net/browse/BAS-1297?atlOrigin=eyJpIjoiYzgwYTQ0ZjEyNzQzNGJhN2JmNjEyZTM0NmRhZWZhNjIiLCJwIjoic2hlZXRzLWppcmEifQ","BAS-1297") -> BAS-1297 | C20: update cors configuration in status update api | D20: P5 - Lowest | E20: Closed | F20: 45868.622 | G20: =HYPERLINK("https://hawk-eye.atlassian.net/browse/?atlOrigin=eyJpIjoiYzgwYTQ0ZjEyNzQzNGJhN2JmNjEyZTM0NmRhZWZhNjIiLCJwIjoic2hlZXRzLWppcmEifQ","") | H20: Basketball & Baseball Data Platform | M20: [no field found] | N20: [no field found] | O20: [no field found] | Q20: 45912.496 | R20: 2.41 | S20: Basketball | U20: 45667
A21: Story | B21: =HYPERLINK("https://hawk-eye.atlassian.net/browse/BAS-1294?atlOrigin=eyJpIjoiYzgwYTQ0ZjEyNzQzNGJhN2JmNjEyZTM0NmRhZWZhNjIiLCJwIjoic2hlZXRzLWppcmEifQ","BAS-1294") -> BAS-1294 | C21: Add Team Logos | D21: P3 - Medium | E21: Closed | F21: 45868.545 | G21: =HYPERLINK("https://hawk-eye.atlassian.net/browse/?atlOrigin=eyJpIjoiYzgwYTQ0ZjEyNzQzNGJhN2JmNjEyZTM0NmRhZWZhNjIiLCJwIjoic2hlZXRzLWppcmEifQ","") | H21: Basketball & Baseball Data Platform | M21: [no field found] | N21: [no field found] | O21: [no field found] | Q21: 45884.446 | R21: 2.41 FE | S21: Basketball;Feature;Frontend | U21: 45667
A22: Story | B22: =HYPERLINK("https://hawk-eye.atlassian.net/browse/BAS-1285?atlOrigin=eyJpIjoiYzgwYTQ0ZjEyNzQzNGJhN2JmNjEyZTM0NmRhZWZhNjIiLCJwIjoic2hlZXRzLWppcmEifQ","BAS-1285") -> BAS-1285 | C22: Upgrade BskDP Spring Boot Version | D22: P5 - Lowest | E22: In Review | F22: 45866.485 | G22: =HYPERLINK("https://hawk-eye.atlassian.net/browse/?atlOrigin=eyJpIjoiYzgwYTQ0ZjEyNzQzNGJhN2JmNjEyZTM0NmRhZWZhNjIiLCJwIjoic2hlZXRzLWppcmEifQ","") | H22: Basketball & Baseball Data Platform | M22: [no field found] | N22: [no field found] | O22: [no field found] | Q22: 45903.618 | S22: Basketball | U22: 45667
A23: Bug | B23: =HYPERLINK("https://hawk-eye.atlassian.net/browse/BAS-1277?atlOrigin=eyJpIjoiYzgwYTQ0ZjEyNzQzNGJhN2JmNjEyZTM0NmRhZWZhNjIiLCJwIjoic2hlZXRzLWppcmEifQ","BAS-1277") -> BAS-1277 | C23: AWS Region not set correctly for SFG & LFG | D23: P2 - High | E23: Closed | F23: 45862.617 | G23: =HYPERLINK("https://hawk-eye.atlassian.net/browse/?atlOrigin=eyJpIjoiYzgwYTQ0ZjEyNzQzNGJhN2JmNjEyZTM0NmRhZWZhNjIiLCJwIjoic2hlZXRzLWppcmEifQ","") | H23: Basketball & Baseball Data Platform | M23: [no field found] | N23: [no field found] | O23: [no field found] | Q23: 45937.697 | S23: Basketball;DevOps | U23: 45691
A24: Story | B24: =HYPERLINK("https://hawk-eye.atlassian.net/browse/BAS-1276?atlOrigin=eyJpIjoiYzgwYTQ0ZjEyNzQzNGJhN2JmNjEyZTM0NmRhZWZhNjIiLCJwIjoic2hlZXRzLWppcmEifQ","BAS-1276") -> BAS-1276 | C24: PMEG rebound logic not behaving the same as LFG | D24: P5 - Lowest | E24: To Test | F24: 45862.453 | G24: =HYPERLINK("https://hawk-eye.atlassian.net/browse/BAS-1174?atlOrigin=eyJpIjoiYzgwYTQ0ZjEyNzQzNGJhN2JmNjEyZTM0NmRhZWZhNjIiLCJwIjoic2hlZXRzLWppcmEifQ","BAS-1174") -> BAS-1174 | H24: Basketball & Baseball Data Platform | M24: [no field found] | N24: [no field found] | O24: [no field found] | Q24: 45937.426 | R24: 2.41 | S24: Basketball;Improvement | U24: 45691
A25: Story | B25: =HYPERLINK("https://hawk-eye.atlassian.net/browse/BAS-1275?atlOrigin=eyJpIjoiYzgwYTQ0ZjEyNzQzNGJhN2JmNjEyZTM0NmRhZWZhNjIiLCJwIjoic2hlZXRzLWppcmEifQ","BAS-1275") -> BAS-1275 | C25: Output backboard touches to the Officiating Events feed | D25: P1 - Highest | E25: Closed | F25: 45861.88 | G25: =HYPERLINK("https://hawk-eye.atlassian.net/browse/?atlOrigin=eyJpIjoiYzgwYTQ0ZjEyNzQzNGJhN2JmNjEyZTM0NmRhZWZhNjIiLCJwIjoic2hlZXRzLWppcmEifQ","") | H25: Basketball & Baseball Data Platform | M25: [no field found] | N25: [no field found] | O25: [no field found] | Q25: 45932.7 | R25: 2.41 | S25: Basketball;Feature | U25: 45672
A26: Story | B26: =HYPERLINK("https://hawk-eye.atlassian.net/browse/BAS-1274?atlOrigin=eyJpIjoiYzgwYTQ0ZjEyNzQzNGJhN2JmNjEyZTM0NmRhZWZhNjIiLCJwIjoic2hlZXRzLWppcmEifQ","BAS-1274") -> BAS-1274 | C26: Ignore new events for the Live Events feed | D26: P2 - High | E26: Closed | F26: 45861.87 | G26: =HYPERLINK("https://hawk-eye.atlassian.net/browse/BAS-1352?atlOrigin=eyJpIjoiYzgwYTQ0ZjEyNzQzNGJhN2JmNjEyZTM0NmRhZWZhNjIiLCJwIjoic2hlZXRzLWppcmEifQ","BAS-1352") -> BAS-1352 | H26: Basketball & Baseball Data Platform | M26: [no field found] | N26: [no field found] | O26: [no field found] | Q26: 45931.732 | R26: 2.41 | S26: Basketball;Feature | U26: 45691
A27: Story | B27: =HYPERLINK("https://hawk-eye.atlassian.net/browse/BAS-1272?atlOrigin=eyJpIjoiYzgwYTQ0ZjEyNzQzNGJhN2JmNjEyZTM0NmRhZWZhNjIiLCJwIjoic2hlZXRzLWppcmEifQ","BAS-1272") -> BAS-1272 | C27: Change test stream games | D27: P3 - Medium | E27: Closed | F27: 45861.839 | G27: =HYPERLINK("https://hawk-eye.atlassian.net/issues/?atlOrigin=eyJpIjoiYzgwYTQ0ZjEyNzQzNGJhN2JmNjEyZTM0NmRhZWZhNjIiLCJwIjoic2hlZXRzLWppcmEifQ&jql=key+in+%28BAS-1189%2CDEVOPS-1004%2CBAS-1314%29","BAS-1189;DEVOPS-1004;BAS-1314") -> BAS-1189;DEVOPS-1004;BAS-1314 | H27: Basketball & Baseball Data Platform | M27: [no field found] | N27: [no field found] | O27: [no field found] | Q27: 45897.426 | S27: Basketball;CustomerRaised | U27: 45672
A28: Story | B28: =HYPERLINK("https://hawk-eye.atlassian.net/browse/BAS-1249?atlOrigin=eyJpIjoiYzgwYTQ0ZjEyNzQzNGJhN2JmNjEyZTM0NmRhZWZhNjIiLCJwIjoic2hlZXRzLWppcmEifQ","BAS-1249") -> BAS-1249 | C28: Add ball spin to Officiating and Live feeds | D28: P2 - High | E28: Closed | F28: 45855.667 | G28: =HYPERLINK("https://hawk-eye.atlassian.net/issues/?atlOrigin=eyJpIjoiYzgwYTQ0ZjEyNzQzNGJhN2JmNjEyZTM0NmRhZWZhNjIiLCJwIjoic2hlZXRzLWppcmEifQ&jql=key+in+%28BAS-742%2CBAS-1345%29","BAS-742;BAS-1345") -> BAS-742;BAS-1345 | H28: Basketball & Baseball Data Platform | M28: [no field found] | N28: [no field found] | O28: [no field found] | Q28: 45860.463 | S28: Basketball | U28: 45672
A29: Story | B29: =HYPERLINK("https://hawk-eye.atlassian.net/browse/BAS-1227?atlOrigin=eyJpIjoiYzgwYTQ0ZjEyNzQzNGJhN2JmNjEyZTM0NmRhZWZhNjIiLCJwIjoic2hlZXRzLWppcmEifQ","BAS-1227") -> BAS-1227 | C29: Lambda for PMEG data to NBA S3 | D29: P3 - Medium | E29: Closed | F29: 45831.007 | G29: =HYPERLINK("https://hawk-eye.atlassian.net/browse/?atlOrigin=eyJpIjoiYzgwYTQ0ZjEyNzQzNGJhN2JmNjEyZTM0NmRhZWZhNjIiLCJwIjoic2hlZXRzLWppcmEifQ","") | H29: Basketball & Baseball Data Platform | M29: [no field found] | N29: [no field found] | O29: [no field found] | Q29: 45860.76 | S29: Basketball;Feature | U29: 45672
A30: Story | B30: =HYPERLINK("https://hawk-eye.atlassian.net/browse/BAS-1226?atlOrigin=eyJpIjoiYzgwYTQ0ZjEyNzQzNGJhN2JmNjEyZTM0NmRhZWZhNjIiLCJwIjoic2hlZXRzLWppcmEifQ","BAS-1226") -> BAS-1226 | C30: Write lambdas to copy over processed data to NBA S3 | D30: P1 - Highest | E30: Closed | F30: 45831.002 | G30: =HYPERLINK("https://hawk-eye.atlassian.net/issues/?atlOrigin=eyJpIjoiYzgwYTQ0ZjEyNzQzNGJhN2JmNjEyZTM0NmRhZWZhNjIiLCJwIjoic2hlZXRzLWppcmEifQ&jql=key+in+%28BAS-1034%2CBAS-1228%2CBAS-1327%2CBAS-1344%2CBAS-1346%2CBAS-1354%29","BAS-1034;BAS-1228;BAS-1327;BAS-1344;BAS-1346;BAS-1354") -> BAS-1034;BAS-1228;BAS-1327;BAS-1344;BAS-1346;BAS-1354 | H30: Basketball & Baseball Data Platform | M30: [no field found] | N30: [no field found] | O30: [no field found] | Q30: 45922.494 | R30: 2.41 | S30: Basketball;Feature | U30: 45672
A31: Story | B31: =HYPERLINK("https://hawk-eye.atlassian.net/browse/BAS-1224?atlOrigin=eyJpIjoiYzgwYTQ0ZjEyNzQzNGJhN2JmNjEyZTM0NmRhZWZhNjIiLCJwIjoic2hlZXRzLWppcmEifQ","BAS-1224") -> BAS-1224 | C31: Use 404 not found responses for status update api | D31: P5 - Lowest | E31: Closed | F31: 45827.469 | G31: =HYPERLINK("https://hawk-eye.atlassian.net/browse/?atlOrigin=eyJpIjoiYzgwYTQ0ZjEyNzQzNGJhN2JmNjEyZTM0NmRhZWZhNjIiLCJwIjoic2hlZXRzLWppcmEifQ","") | H31: Basketball & Baseball Data Platform | M31: [no field found] | N31: [no field found] | O31: [no field found] | Q31: 45860.582 | R31: 2.41 | S31: Basketball;Feature | T31: 1 | U31: 45665
A32: Bug | B32: =HYPERLINK("https://hawk-eye.atlassian.net/browse/BAS-1219?atlOrigin=eyJpIjoiYzgwYTQ0ZjEyNzQzNGJhN2JmNjEyZTM0NmRhZWZhNjIiLCJwIjoic2hlZXRzLWppcmEifQ","BAS-1219") -> BAS-1219 | C32: Error group not removed when user selects clear all. | D32: P5 - Lowest | E32: Closed | F32: 45825.35 | G32: =HYPERLINK("https://hawk-eye.atlassian.net/browse/BAS-1054?atlOrigin=eyJpIjoiYzgwYTQ0ZjEyNzQzNGJhN2JmNjEyZTM0NmRhZWZhNjIiLCJwIjoic2hlZXRzLWppcmEifQ","BAS-1054") -> BAS-1054 | H32: Basketball & Baseball Data Platform | M32: [no field found] | N32: [no field found] | O32: [no field found] | Q32: 45869.327 | R32: 2.41 FE | S32: Basketball;Feature | T32: 2.37 | U32: 45741
A33: Story | B33: =HYPERLINK("https://hawk-eye.atlassian.net/browse/BAS-1204?atlOrigin=eyJpIjoiYzgwYTQ0ZjEyNzQzNGJhN2JmNjEyZTM0NmRhZWZhNjIiLCJwIjoic2hlZXRzLWppcmEifQ","BAS-1204") -> BAS-1204 | C33: Extricate Test Stream from Release Process | D33: P3 - Medium | E33: Backlog | F33: 45819.465 | G33: =HYPERLINK("https://hawk-eye.atlassian.net/browse/BAS-1189?atlOrigin=eyJpIjoiYzgwYTQ0ZjEyNzQzNGJhN2JmNjEyZTM0NmRhZWZhNjIiLCJwIjoic2hlZXRzLWppcmEifQ","BAS-1189") -> BAS-1189 | H33: Basketball & Baseball Data Platform | M33: [no field found] | N33: [no field found] | O33: [no field found] | Q33: 45819.465 | S33: Basketball;TechDebt | U33: 45672
A34: Bug | B34: =HYPERLINK("https://hawk-eye.atlassian.net/browse/BAS-1186?atlOrigin=eyJpIjoiYzgwYTQ0ZjEyNzQzNGJhN2JmNjEyZTM0NmRhZWZhNjIiLCJwIjoic2hlZXRzLWppcmEifQ","BAS-1186") -> BAS-1186 | C34: NGSS data is not saving to S3 in prod | D34: P4 - Low | E34: Backlog | F34: 45814.614 | G34: =HYPERLINK("https://hawk-eye.atlassian.net/browse/BAS-1070?atlOrigin=eyJpIjoiYzgwYTQ0ZjEyNzQzNGJhN2JmNjEyZTM0NmRhZWZhNjIiLCJwIjoic2hlZXRzLWppcmEifQ","BAS-1070") -> BAS-1070 | H34: Basketball & Baseball Data Platform | M34: [no field found] | N34: [no field found] | O34: [no field found] | Q34: 45814.614 | S34: Basketball;Improvement | U34: 45672
A35: Story | B35: =HYPERLINK("https://hawk-eye.atlassian.net/browse/BAS-1178?atlOrigin=eyJpIjoiYzgwYTQ0ZjEyNzQzNGJhN2JmNjEyZTM0NmRhZWZhNjIiLCJwIjoic2hlZXRzLWppcmEifQ","BAS-1178") -> BAS-1178 | C35: Nearest frame time for post process events | D35: P4 - Low | E35: Backlog | F35: 45810.139 | G35: =HYPERLINK("https://hawk-eye.atlassian.net/browse/BAS-561?atlOrigin=eyJpIjoiYzgwYTQ0ZjEyNzQzNGJhN2JmNjEyZTM0NmRhZWZhNjIiLCJwIjoic2hlZXRzLWppcmEifQ","BAS-561") -> BAS-561 | H35: Basketball & Baseball Data Platform | M35: [no field found] | N35: [no field found] | O35: [no field found] | Q35: 45810.139 | S35: Basketball | U35: 45672
A36: Bug | B36: =HYPERLINK("https://hawk-eye.atlassian.net/browse/BAS-1177?atlOrigin=eyJpIjoiYzgwYTQ0ZjEyNzQzNGJhN2JmNjEyZTM0NmRhZWZhNjIiLCJwIjoic2hlZXRzLWppcmEifQ","BAS-1177") -> BAS-1177 | C36: Rebounds from NGSS are being removed from PGCE | D36: P2 - High | E36: Closed | F36: 45810.13 | G36: =HYPERLINK("https://hawk-eye.atlassian.net/issues/?atlOrigin=eyJpIjoiYzgwYTQ0ZjEyNzQzNGJhN2JmNjEyZTM0NmRhZWZhNjIiLCJwIjoic2hlZXRzLWppcmEifQ&jql=key+in+%28BAS-1174%2CBAS-1176%29","BAS-1174;BAS-1176") -> BAS-1174;BAS-1176 | H36: Basketball & Baseball Data Platform | M36: [no field found] | N36: [no field found] | O36: [no field found] | Q36: 45853.59 | S36: Basketball | U36: 45672
A37: Story | B37: =HYPERLINK("https://hawk-eye.atlassian.net/browse/BAS-1175?atlOrigin=eyJpIjoiYzgwYTQ0ZjEyNzQzNGJhN2JmNjEyZTM0NmRhZWZhNjIiLCJwIjoic2hlZXRzLWppcmEifQ","BAS-1175") -> BAS-1175 | C37: Use gameClockRunning field in index file to better filter for pose backfilling | D37: P3 - Medium | E37: Closed | F37: 45810.091 | G37: =HYPERLINK("https://hawk-eye.atlassian.net/browse/BAS-1173?atlOrigin=eyJpIjoiYzgwYTQ0ZjEyNzQzNGJhN2JmNjEyZTM0NmRhZWZhNjIiLCJwIjoic2hlZXRzLWppcmEifQ","BAS-1173") -> BAS-1173 | H37: Basketball & Baseball Data Platform | M37: [no field found] | N37: [no field found] | O37: [no field found] | Q37: 45931.67 | R37: 2.41 | S37: Basketball;Improvement | U37: 45672
A38: Bug | B38: =HYPERLINK("https://hawk-eye.atlassian.net/browse/BAS-1172?atlOrigin=eyJpIjoiYzgwYTQ0ZjEyNzQzNGJhN2JmNjEyZTM0NmRhZWZhNjIiLCJwIjoic2hlZXRzLWppcmEifQ","BAS-1172") -> BAS-1172 | C38: Rework using dribbles to match shots | D38: P3 - Medium | E38: Backlog | F38: 45807.671 | G38: =HYPERLINK("https://hawk-eye.atlassian.net/issues/?atlOrigin=eyJpIjoiYzgwYTQ0ZjEyNzQzNGJhN2JmNjEyZTM0NmRhZWZhNjIiLCJwIjoic2hlZXRzLWppcmEifQ&jql=key+in+%28BAS-714%2CBAS-627%2CBAS-1136%2CBAS-1074%2CBAS-1176%29","BAS-714;BAS-627;BAS-1136;BAS-1074;BAS-1176") -> BAS-714;BAS-627;BAS-1136;BAS-1074;BAS-1176 | H38: Basketball & Baseball Data Platform | M38: [no field found] | N38: [no field found] | O38: [no field found] | Q38: 45807.671 | S38: Basketball;Improvement | U38: 45672
A39: Story | B39: =HYPERLINK("https://hawk-eye.atlassian.net/browse/BAS-1166?atlOrigin=eyJpIjoiYzgwYTQ0ZjEyNzQzNGJhN2JmNjEyZTM0NmRhZWZhNjIiLCJwIjoic2hlZXRzLWppcmEifQ","BAS-1166") -> BAS-1166 | C39: Build TimeInput Component | D39: P3 - Medium | E39: Closed | F39: 45804.534 | G39: =HYPERLINK("https://hawk-eye.atlassian.net/browse/?atlOrigin=eyJpIjoiYzgwYTQ0ZjEyNzQzNGJhN2JmNjEyZTM0NmRhZWZhNjIiLCJwIjoic2hlZXRzLWppcmEifQ","") | H39: Basketball & Baseball Data Platform | M39: [no field found] | N39: [no field found] | O39: [no field found] | Q39: 45926.426 | R39: 2.41 FE | S39: Basketball;Feature;Frontend | U39: 45672
A40: Story | B40: =HYPERLINK("https://hawk-eye.atlassian.net/browse/BAS-1165?atlOrigin=eyJpIjoiYzgwYTQ0ZjEyNzQzNGJhN2JmNjEyZTM0NmRhZWZhNjIiLCJwIjoic2hlZXRzLWppcmEifQ","BAS-1165") -> BAS-1165 | C40: Build SelectPill Component | D40: P3 - Medium | E40: Closed | F40: 45804.514 | G40: =HYPERLINK("https://hawk-eye.atlassian.net/browse/?atlOrigin=eyJpIjoiYzgwYTQ0ZjEyNzQzNGJhN2JmNjEyZTM0NmRhZWZhNjIiLCJwIjoic2hlZXRzLWppcmEifQ","") | H40: Basketball & Baseball Data Platform | M40: [no field found] | N40: [no field found] | O40: [no field found] | Q40: 45876.712 | R40: 2.41 FE | S40: Basketball;Feature;Frontend | U40: 45672
A41: Story | B41: =HYPERLINK("https://hawk-eye.atlassian.net/browse/BAS-1157?atlOrigin=eyJpIjoiYzgwYTQ0ZjEyNzQzNGJhN2JmNjEyZTM0NmRhZWZhNjIiLCJwIjoic2hlZXRzLWppcmEifQ","BAS-1157") -> BAS-1157 | C41: gameActive to true if null for SFG from-feeds | D41: P1 - Highest | E41: Closed | F41: 45798.689 | G41: =HYPERLINK("https://hawk-eye.atlassian.net/browse/?atlOrigin=eyJpIjoiYzgwYTQ0ZjEyNzQzNGJhN2JmNjEyZTM0NmRhZWZhNjIiLCJwIjoic2hlZXRzLWppcmEifQ","") | H41: Basketball & Baseball Data Platform | M41: [no field found] | N41: [no field found] | O41: [no field found] | Q41: 45800.589 | S41: Basketball;Feature | U41: 45672
A42: Story | B42: =HYPERLINK("https://hawk-eye.atlassian.net/browse/BAS-1144?atlOrigin=eyJpIjoiYzgwYTQ0ZjEyNzQzNGJhN2JmNjEyZTM0NmRhZWZhNjIiLCJwIjoic2hlZXRzLWppcmEifQ","BAS-1144") -> BAS-1144 | C42: Link Post Process Officiating Events to Live Officiating Events | D42: P2 - High | E42: Closed | F42: 45776.944 | G42: =HYPERLINK("https://hawk-eye.atlassian.net/browse/?atlOrigin=eyJpIjoiYzgwYTQ0ZjEyNzQzNGJhN2JmNjEyZTM0NmRhZWZhNjIiLCJwIjoic2hlZXRzLWppcmEifQ","") | H42: Basketball & Baseball Data Platform | M42: [no field found] | N42: [no field found] | O42: [no field found] | Q42: 45852.446 | R42: 2.41 | S42: Basketball;CustomerRaised | U42: 45672
A43: Story | B43: =HYPERLINK("https://hawk-eye.atlassian.net/browse/BAS-1143?atlOrigin=eyJpIjoiYzgwYTQ0ZjEyNzQzNGJhN2JmNjEyZTM0NmRhZWZhNjIiLCJwIjoic2hlZXRzLWppcmEifQ","BAS-1143") -> BAS-1143 | C43: Integrate Status Update Frontend to API | D43: P2 - High | E43: Closed | F43: 45772.891 | G43: =HYPERLINK("https://hawk-eye.atlassian.net/browse/?atlOrigin=eyJpIjoiYzgwYTQ0ZjEyNzQzNGJhN2JmNjEyZTM0NmRhZWZhNjIiLCJwIjoic2hlZXRzLWppcmEifQ","") | H43: Basketball & Baseball Data Platform | M43: [no field found] | N43: [no field found] | O43: [no field found] | Q43: 45856.468 | R43: 2.41 FE | S43: Basketball;Feature;Frontend | U43: 45672
A44: Story | B44: =HYPERLINK("https://hawk-eye.atlassian.net/browse/BAS-1136?atlOrigin=eyJpIjoiYzgwYTQ0ZjEyNzQzNGJhN2JmNjEyZTM0NmRhZWZhNjIiLCJwIjoic2hlZXRzLWppcmEifQ","BAS-1136") -> BAS-1136 | C44: Handle events with no classification in PMEG event store | D44: P3 - Medium | E44: Backlog | F44: 45770.445 | G44: =HYPERLINK("https://hawk-eye.atlassian.net/issues/?atlOrigin=eyJpIjoiYzgwYTQ0ZjEyNzQzNGJhN2JmNjEyZTM0NmRhZWZhNjIiLCJwIjoic2hlZXRzLWppcmEifQ&jql=key+in+%28BAS-1074%2CBAS-1172%29","BAS-1074;BAS-1172") -> BAS-1074;BAS-1172 | H44: Basketball & Baseball Data Platform | M44: [no field found] | N44: [no field found] | O44: [no field found] | Q44: 45770.445 | S44: Basketball;Improvement | U44: 45672
A45: Story | B45: =HYPERLINK("https://hawk-eye.atlassian.net/browse/BAS-1135?atlOrigin=eyJpIjoiYzgwYTQ0ZjEyNzQzNGJhN2JmNjEyZTM0NmRhZWZhNjIiLCJwIjoic2hlZXRzLWppcmEifQ","BAS-1135") -> BAS-1135 | C45: Data platform end to end testing environment | D45: P5 - Lowest | E45: Backlog | F45: 45769.415 | G45: =HYPERLINK("https://hawk-eye.atlassian.net/browse/?atlOrigin=eyJpIjoiYzgwYTQ0ZjEyNzQzNGJhN2JmNjEyZTM0NmRhZWZhNjIiLCJwIjoic2hlZXRzLWppcmEifQ","") | H45: Basketball & Baseball Data Platform | M45: [no field found] | N45: [no field found] | O45: [no field found] | Q45: 45769.415 | S45: Basketball | U45: 45672
A46: Story | B46: =HYPERLINK("https://hawk-eye.atlassian.net/browse/BAS-1125?atlOrigin=eyJpIjoiYzgwYTQ0ZjEyNzQzNGJhN2JmNjEyZTM0NmRhZWZhNjIiLCJwIjoic2hlZXRzLWppcmEifQ","BAS-1125") -> BAS-1125 | C46: Complete SFG Adaptation | D46: P2 - High | E46: Closed | F46: 45758.608 | G46: =HYPERLINK("https://hawk-eye.atlassian.net/issues/?atlOrigin=eyJpIjoiYzgwYTQ0ZjEyNzQzNGJhN2JmNjEyZTM0NmRhZWZhNjIiLCJwIjoic2hlZXRzLWppcmEifQ&jql=key+in+%28BAS-1119%2CBAS-1121%29","BAS-1119;BAS-1121") -> BAS-1119;BAS-1121 | H46: Basketball & Baseball Data Platform | M46: [no field found] | N46: [no field found] | O46: [no field found] | Q46: 45786.662 | R46: 2.40 | S46: Basketball | U46: 45672
A47: Story | B47: =HYPERLINK("https://hawk-eye.atlassian.net/browse/BAS-1122?atlOrigin=eyJpIjoiYzgwYTQ0ZjEyNzQzNGJhN2JmNjEyZTM0NmRhZWZhNjIiLCJwIjoic2hlZXRzLWppcmEifQ","BAS-1122") -> BAS-1122 | C47: Add Capability to Feed Messages into SFG from an SQS Queue | D47: P3 - Medium | E47: Closed | F47: 45757.412 | G47: =HYPERLINK("https://hawk-eye.atlassian.net/browse/?atlOrigin=eyJpIjoiYzgwYTQ0ZjEyNzQzNGJhN2JmNjEyZTM0NmRhZWZhNjIiLCJwIjoic2hlZXRzLWppcmEifQ","") | H47: Basketball & Baseball Data Platform | M47: [no field found] | N47: [no field found] | O47: [no field found] | Q47: 45786.661 | R47: 2.40 | S47: Basketball | U47: 45672
A48: Story | B48: =HYPERLINK("https://hawk-eye.atlassian.net/browse/BAS-1121?atlOrigin=eyJpIjoiYzgwYTQ0ZjEyNzQzNGJhN2JmNjEyZTM0NmRhZWZhNjIiLCJwIjoic2hlZXRzLWppcmEifQ","BAS-1121") -> BAS-1121 | C48: Write Message Producers | D48: P2 - High | E48: Closed | F48: 45757.408 | G48: =HYPERLINK("https://hawk-eye.atlassian.net/browse/BAS-1125?atlOrigin=eyJpIjoiYzgwYTQ0ZjEyNzQzNGJhN2JmNjEyZTM0NmRhZWZhNjIiLCJwIjoic2hlZXRzLWppcmEifQ","BAS-1125") -> BAS-1125 | H48: Basketball & Baseball Data Platform | M48: [no field found] | N48: [no field found] | O48: [no field found] | Q48: 45786.661 | R48: 2.40 | S48: Basketball | U48: 45672
A49: Story | B49: =HYPERLINK("https://hawk-eye.atlassian.net/browse/BAS-1120?atlOrigin=eyJpIjoiYzgwYTQ0ZjEyNzQzNGJhN2JmNjEyZTM0NmRhZWZhNjIiLCJwIjoic2hlZXRzLWppcmEifQ","BAS-1120") -> BAS-1120 | C49: Write a Message Location Service | D49: P2 - High | E49: Closed | F49: 45757.401 | G49: =HYPERLINK("https://hawk-eye.atlassian.net/browse/?atlOrigin=eyJpIjoiYzgwYTQ0ZjEyNzQzNGJhN2JmNjEyZTM0NmRhZWZhNjIiLCJwIjoic2hlZXRzLWppcmEifQ","") | H49: Basketball & Baseball Data Platform | M49: [no field found] | N49: [no field found] | O49: [no field found] | Q49: 45786.662 | R49: 2.40 | S49: Basketball | U49: 45672
A50: Story | B50: =HYPERLINK("https://hawk-eye.atlassian.net/browse/BAS-1119?atlOrigin=eyJpIjoiYzgwYTQ0ZjEyNzQzNGJhN2JmNjEyZTM0NmRhZWZhNjIiLCJwIjoic2hlZXRzLWppcmEifQ","BAS-1119") -> BAS-1119 | C50: Write Alternate Deduplication Logic | D50: P2 - High | E50: Closed | F50: 45757.385 | G50: =HYPERLINK("https://hawk-eye.atlassian.net/browse/BAS-1125?atlOrigin=eyJpIjoiYzgwYTQ0ZjEyNzQzNGJhN2JmNjEyZTM0NmRhZWZhNjIiLCJwIjoic2hlZXRzLWppcmEifQ","BAS-1125") -> BAS-1125 | H50: Basketball & Baseball Data Platform | M50: [no field found] | N50: [no field found] | O50: [no field found] | Q50: 45786.662 | R50: 2.40 | S50: Basketball | T50: 1 | U50: 45665
A51: Story | B51: =HYPERLINK("https://hawk-eye.atlassian.net/browse/BAS-1105?atlOrigin=eyJpIjoiYzgwYTQ0ZjEyNzQzNGJhN2JmNjEyZTM0NmRhZWZhNjIiLCJwIjoic2hlZXRzLWppcmEifQ","BAS-1105") -> BAS-1105 | C51: Add warning message when LFG current game id doesn't correspond to current day | D51: P3 - Medium | E51: Backlog | F51: 45747.767 | G51: =HYPERLINK("https://hawk-eye.atlassian.net/browse/?atlOrigin=eyJpIjoiYzgwYTQ0ZjEyNzQzNGJhN2JmNjEyZTM0NmRhZWZhNjIiLCJwIjoic2hlZXRzLWppcmEifQ","") | H51: Basketball & Baseball Data Platform | M51: [no field found] | N51: [no field found] | O51: [no field found] | Q51: 45747.767 | S51: Basketball;InternalCustomer | T51: 1 | U51: 45665
A52: Story | B52: =HYPERLINK("https://hawk-eye.atlassian.net/browse/BAS-1097?atlOrigin=eyJpIjoiYzgwYTQ0ZjEyNzQzNGJhN2JmNjEyZTM0NmRhZWZhNjIiLCJwIjoic2hlZXRzLWppcmEifQ","BAS-1097") -> BAS-1097 | C52: Pair data from multiple NGSS events to single HEI event on fouls | D52: P3 - Medium | E52: Backlog | F52: 45743.93 | G52: =HYPERLINK("https://hawk-eye.atlassian.net/issues/?atlOrigin=eyJpIjoiYzgwYTQ0ZjEyNzQzNGJhN2JmNjEyZTM0NmRhZWZhNjIiLCJwIjoic2hlZXRzLWppcmEifQ&jql=key+in+%28BAS-663%2CBAS-1001%29","BAS-663;BAS-1001") -> BAS-663;BAS-1001 | H52: Basketball & Baseball Data Platform | M52: [no field found] | N52: [no field found] | O52: [no field found] | Q52: 45743.93 | S52: Basketball | T52: 1 | U52: 45665
A53: Story | B53: =HYPERLINK("https://hawk-eye.atlassian.net/browse/BAS-1095?atlOrigin=eyJpIjoiYzgwYTQ0ZjEyNzQzNGJhN2JmNjEyZTM0NmRhZWZhNjIiLCJwIjoic2hlZXRzLWppcmEifQ","BAS-1095") -> BAS-1095 | C53: Handle slow internet connection on SFG uploads in GL | D53: P4 - Low | E53: Backlog | F53: 45742.879 | G53: =HYPERLINK("https://hawk-eye.atlassian.net/browse/?atlOrigin=eyJpIjoiYzgwYTQ0ZjEyNzQzNGJhN2JmNjEyZTM0NmRhZWZhNjIiLCJwIjoic2hlZXRzLWppcmEifQ","") | H53: Basketball & Baseball Data Platform | M53: [no field found] | N53: [no field found] | O53: [no field found] | Q53: 45742.879 | S53: Basketball;InternalCustomer | U53: 45674
A54: Story | B54: =HYPERLINK("https://hawk-eye.atlassian.net/browse/BAS-1092?atlOrigin=eyJpIjoiYzgwYTQ0ZjEyNzQzNGJhN2JmNjEyZTM0NmRhZWZhNjIiLCJwIjoic2hlZXRzLWppcmEifQ","BAS-1092") -> BAS-1092 | C54: Update Dashboard Filter Component | D54: P3 - Medium | E54: Closed | F54: 45742.81 | G54: =HYPERLINK("https://hawk-eye.atlassian.net/browse/BAS-1050?atlOrigin=eyJpIjoiYzgwYTQ0ZjEyNzQzNGJhN2JmNjEyZTM0NmRhZWZhNjIiLCJwIjoic2hlZXRzLWppcmEifQ","BAS-1050") -> BAS-1050 | H54: Basketball & Baseball Data Platform | M54: [no field found] | N54: [no field found] | O54: [no field found] | Q54: 45824.451 | R54: 2.41 FE | S54: Basketball;Feature;Frontend | U54: 45674
A55: Story | B55: =HYPERLINK("https://hawk-eye.atlassian.net/browse/BAS-1089?atlOrigin=eyJpIjoiYzgwYTQ0ZjEyNzQzNGJhN2JmNjEyZTM0NmRhZWZhNjIiLCJwIjoic2hlZXRzLWppcmEifQ","BAS-1089") -> BAS-1089 | C55: NGSS Client is populating home and away team lists with same players | D55: P1 - Highest | E55: Closed | F55: 45741.397 | G55: =HYPERLINK("https://hawk-eye.atlassian.net/browse/BAS-1088?atlOrigin=eyJpIjoiYzgwYTQ0ZjEyNzQzNGJhN2JmNjEyZTM0NmRhZWZhNjIiLCJwIjoic2hlZXRzLWppcmEifQ","BAS-1088") -> BAS-1088 | H55: Basketball & Baseball Data Platform | M55: [no field found] | N55: [no field found] | O55: [no field found] | Q55: 45741.696 | R55: 2.38.2 | S55: Basketball | U55: 45674
A56: Bug | B56: =HYPERLINK("https://hawk-eye.atlassian.net/browse/BAS-1088?atlOrigin=eyJpIjoiYzgwYTQ0ZjEyNzQzNGJhN2JmNjEyZTM0NmRhZWZhNjIiLCJwIjoic2hlZXRzLWppcmEifQ","BAS-1088") -> BAS-1088 | C56: NGSS Client is populating home and away team lists with same players | D56: P1 - Highest | E56: Closed | F56: 45741.382 | G56: =HYPERLINK("https://hawk-eye.atlassian.net/browse/BAS-1089?atlOrigin=eyJpIjoiYzgwYTQ0ZjEyNzQzNGJhN2JmNjEyZTM0NmRhZWZhNjIiLCJwIjoic2hlZXRzLWppcmEifQ","BAS-1089") -> BAS-1089 | H56: Basketball & Baseball Data Platform | M56: [no field found] | N56: [no field found] | O56: [no field found] | Q56: 45742.555 | S56: Basketball | U56: 45674
A57: Story | B57: =HYPERLINK("https://hawk-eye.atlassian.net/browse/BAS-1084?atlOrigin=eyJpIjoiYzgwYTQ0ZjEyNzQzNGJhN2JmNjEyZTM0NmRhZWZhNjIiLCJwIjoic2hlZXRzLWppcmEifQ","BAS-1084") -> BAS-1084 | C57: Run 23/24 Games Through PMEG | D57: P2 - High | E57: Closed | F57: 45734.679 | G57: =HYPERLINK("https://hawk-eye.atlassian.net/browse/BAS-1083?atlOrigin=eyJpIjoiYzgwYTQ0ZjEyNzQzNGJhN2JmNjEyZTM0NmRhZWZhNjIiLCJwIjoic2hlZXRzLWppcmEifQ","BAS-1083") -> BAS-1083 | H57: Basketball & Baseball Data Platform | M57: [no field found] | N57: [no field found] | O57: [no field found] | Q57: 45757.645 | S57: Basketball | U57: 45674
A58: Story | B58: =HYPERLINK("https://hawk-eye.atlassian.net/browse/BAS-1083?atlOrigin=eyJpIjoiYzgwYTQ0ZjEyNzQzNGJhN2JmNjEyZTM0NmRhZWZhNjIiLCJwIjoic2hlZXRzLWppcmEifQ","BAS-1083") -> BAS-1083 | C58: Generate Index Files | D58: P2 - High | E58: Closed | F58: 45734.674 | G58: =HYPERLINK("https://hawk-eye.atlassian.net/issues/?atlOrigin=eyJpIjoiYzgwYTQ0ZjEyNzQzNGJhN2JmNjEyZTM0NmRhZWZhNjIiLCJwIjoic2hlZXRzLWppcmEifQ&jql=key+in+%28BAS-1082%2CBAS-1084%29","BAS-1082;BAS-1084") -> BAS-1082;BAS-1084 | H58: Basketball & Baseball Data Platform | M58: [no field found] | N58: [no field found] | O58: [no field found] | Q58: 45757.645 | S58: Basketball | U58: 45674
A59: Story | B59: =HYPERLINK("https://hawk-eye.atlassian.net/browse/BAS-1082?atlOrigin=eyJpIjoiYzgwYTQ0ZjEyNzQzNGJhN2JmNjEyZTM0NmRhZWZhNjIiLCJwIjoic2hlZXRzLWppcmEifQ","BAS-1082") -> BAS-1082 | C59: Move Data and Add Timestamp | D59: P2 - High | E59: Closed | F59: 45734.666 | G59: =HYPERLINK("https://hawk-eye.atlassian.net/browse/BAS-1083?atlOrigin=eyJpIjoiYzgwYTQ0ZjEyNzQzNGJhN2JmNjEyZTM0NmRhZWZhNjIiLCJwIjoic2hlZXRzLWppcmEifQ","BAS-1083") -> BAS-1083 | H59: Basketball & Baseball Data Platform | M59: [no field found] | N59: [no field found] | O59: [no field found] | Q59: 45757.645 | S59: Basketball | U59: 45674
A60: Story | B60: =HYPERLINK("https://hawk-eye.atlassian.net/browse/BAS-1076?atlOrigin=eyJpIjoiYzgwYTQ0ZjEyNzQzNGJhN2JmNjEyZTM0NmRhZWZhNjIiLCJwIjoic2hlZXRzLWppcmEifQ","BAS-1076") -> BAS-1076 | C60: Post game combined events feed skipping event numbers | D60: P4 - Low | E60: Backlog | F60: 45729.877 | G60: =HYPERLINK("https://hawk-eye.atlassian.net/browse/?atlOrigin=eyJpIjoiYzgwYTQ0ZjEyNzQzNGJhN2JmNjEyZTM0NmRhZWZhNjIiLCJwIjoic2hlZXRzLWppcmEifQ","") | H60: Basketball & Baseball Data Platform | M60: [no field found] | N60: [no field found] | O60: [no field found] | Q60: 45729.877 | S60: Basketball;Improvement | U60: 45674
A61: Story | B61: =HYPERLINK("https://hawk-eye.atlassian.net/browse/BAS-1075?atlOrigin=eyJpIjoiYzgwYTQ0ZjEyNzQzNGJhN2JmNjEyZTM0NmRhZWZhNjIiLCJwIjoic2hlZXRzLWppcmEifQ","BAS-1075") -> BAS-1075 | C61: Don't allow shot and subsequent rebound to match same event | D61: P3 - Medium | E61: Closed | F61: 45727.968 | G61: =HYPERLINK("https://hawk-eye.atlassian.net/browse/BAS-1074?atlOrigin=eyJpIjoiYzgwYTQ0ZjEyNzQzNGJhN2JmNjEyZTM0NmRhZWZhNjIiLCJwIjoic2hlZXRzLWppcmEifQ","BAS-1074") -> BAS-1074 | H61: Basketball & Baseball Data Platform | M61: [no field found] | N61: [no field found] | O61: [no field found] | Q61: 45763.559 | R61: 2.39 | S61: Basketball | U61: 45674
A62: Story | B62: =HYPERLINK("https://hawk-eye.atlassian.net/browse/BAS-1074?atlOrigin=eyJpIjoiYzgwYTQ0ZjEyNzQzNGJhN2JmNjEyZTM0NmRhZWZhNjIiLCJwIjoic2hlZXRzLWppcmEifQ","BAS-1074") -> BAS-1074 | C62: PMEG event backfill not responding the same as LFG | D62: P2 - High | E62: Closed | F62: 45727.923 | G62: =HYPERLINK("https://hawk-eye.atlassian.net/issues/?atlOrigin=eyJpIjoiYzgwYTQ0ZjEyNzQzNGJhN2JmNjEyZTM0NmRhZWZhNjIiLCJwIjoic2hlZXRzLWppcmEifQ&jql=key+in+%28BAS-1075%2CBAS-1136%2CBAS-1172%29","BAS-1075;BAS-1136;BAS-1172") -> BAS-1075;BAS-1136;BAS-1172 | H62: Basketball & Baseball Data Platform | M62: [no field found] | N62: [no field found] | O62: [no field found] | Q62: 45770.447 | S62: Basketball | U62: 45674
A63: Story | B63: =HYPERLINK("https://hawk-eye.atlassian.net/browse/BAS-1073?atlOrigin=eyJpIjoiYzgwYTQ0ZjEyNzQzNGJhN2JmNjEyZTM0NmRhZWZhNjIiLCJwIjoic2hlZXRzLWppcmEifQ","BAS-1073") -> BAS-1073 | C63: PMEG not finding pose backfill when event is recorded during long break in play | D63: P2 - High | E63: Closed | F63: 45727.897 | G63: =HYPERLINK("https://hawk-eye.atlassian.net/issues/?atlOrigin=eyJpIjoiYzgwYTQ0ZjEyNzQzNGJhN2JmNjEyZTM0NmRhZWZhNjIiLCJwIjoic2hlZXRzLWppcmEifQ&jql=key+in+%28BAS-841%2CBAS-1173%29","BAS-841;BAS-1173") -> BAS-841;BAS-1173 | H63: Basketball & Baseball Data Platform | M63: [no field found] | N63: [no field found] | O63: [no field found] | Q63: 45770.588 | R63: 2.39 | S63: Basketball | U63: 45674
A64: Story | B64: =HYPERLINK("https://hawk-eye.atlassian.net/browse/BAS-1070?atlOrigin=eyJpIjoiYzgwYTQ0ZjEyNzQzNGJhN2JmNjEyZTM0NmRhZWZhNjIiLCJwIjoic2hlZXRzLWppcmEifQ","BAS-1070") -> BAS-1070 | C64: Fix saving live ngss websocket messages | D64: P5 - Lowest | E64: Closed | F64: 45727.474 | G64: =HYPERLINK("https://hawk-eye.atlassian.net/issues/?atlOrigin=eyJpIjoiYzgwYTQ0ZjEyNzQzNGJhN2JmNjEyZTM0NmRhZWZhNjIiLCJwIjoic2hlZXRzLWppcmEifQ&jql=key+in+%28BAS-836%2CBAS-1186%29","BAS-836;BAS-1186") -> BAS-836;BAS-1186 | H64: Basketball & Baseball Data Platform | M64: [no field found] | N64: [no field found] | O64: [no field found] | Q64: 45763.466 | R64: 2.39 | S64: Basketball | U64: 45674
A65: Story | B65: =HYPERLINK("https://hawk-eye.atlassian.net/browse/BAS-1066?atlOrigin=eyJpIjoiYzgwYTQ0ZjEyNzQzNGJhN2JmNjEyZTM0NmRhZWZhNjIiLCJwIjoic2hlZXRzLWppcmEifQ","BAS-1066") -> BAS-1066 | C65: Format Old Files Into 1000 Line Format | D65: P2 - High | E65: Closed | F65: 45726.663 | G65: =HYPERLINK("https://hawk-eye.atlassian.net/browse/?atlOrigin=eyJpIjoiYzgwYTQ0ZjEyNzQzNGJhN2JmNjEyZTM0NmRhZWZhNjIiLCJwIjoic2hlZXRzLWppcmEifQ","") | H65: Basketball & Baseball Data Platform | M65: [no field found] | N65: [no field found] | O65: [no field found] | Q65: 45757.645 | S65: Basketball | U65: 45674
A66: Story | B66: =HYPERLINK("https://hawk-eye.atlassian.net/browse/BAS-1062?atlOrigin=eyJpIjoiYzgwYTQ0ZjEyNzQzNGJhN2JmNjEyZTM0NmRhZWZhNjIiLCJwIjoic2hlZXRzLWppcmEifQ","BAS-1062") -> BAS-1062 | C66: Create API Spec Document | D66: P2 - High | E66: Closed | F66: 45722.474 | G66: =HYPERLINK("https://hawk-eye.atlassian.net/browse/?atlOrigin=eyJpIjoiYzgwYTQ0ZjEyNzQzNGJhN2JmNjEyZTM0NmRhZWZhNjIiLCJwIjoic2hlZXRzLWppcmEifQ","") | H66: Basketball & Baseball Data Platform | M66: [no field found] | N66: [no field found] | O66: [no field found] | Q66: 45805.586 | R66: 2.41 | S66: Basketball;Feature | U66: 45674
A67: Story | B67: =HYPERLINK("https://hawk-eye.atlassian.net/browse/BAS-1060?atlOrigin=eyJpIjoiYzgwYTQ0ZjEyNzQzNGJhN2JmNjEyZTM0NmRhZWZhNjIiLCJwIjoic2hlZXRzLWppcmEifQ","BAS-1060") -> BAS-1060 | C67: Identify Games that need Reformatting | D67: P2 - High | E67: Closed | F67: 45715.533 | G67: =HYPERLINK("https://hawk-eye.atlassian.net/browse/BAS-1087?atlOrigin=eyJpIjoiYzgwYTQ0ZjEyNzQzNGJhN2JmNjEyZTM0NmRhZWZhNjIiLCJwIjoic2hlZXRzLWppcmEifQ","BAS-1087") -> BAS-1087 | H67: Basketball & Baseball Data Platform | M67: [no field found] | N67: [no field found] | O67: [no field found] | Q67: 45756.451 | S67: Basketball | U67: 45674
A68: Story | B68: =HYPERLINK("https://hawk-eye.atlassian.net/browse/BAS-1054?atlOrigin=eyJpIjoiYzgwYTQ0ZjEyNzQzNGJhN2JmNjEyZTM0NmRhZWZhNjIiLCJwIjoic2hlZXRzLWppcmEifQ","BAS-1054") -> BAS-1054 | C68: Populate Game Status Update Modal | D68: P3 - Medium | E68: Closed | F68: 45712.911 | G68: =HYPERLINK("https://hawk-eye.atlassian.net/issues/?atlOrigin=eyJpIjoiYzgwYTQ0ZjEyNzQzNGJhN2JmNjEyZTM0NmRhZWZhNjIiLCJwIjoic2hlZXRzLWppcmEifQ&jql=key+in+%28BAS-1053%2CBAS-1219%2CBAS-1299%29","BAS-1053;BAS-1219;BAS-1299") -> BAS-1053;BAS-1219;BAS-1299 | H68: Basketball & Baseball Data Platform | M68: [no field found] | N68: [no field found] | O68: [no field found] | Q68: 45876.709 | R68: 2.41 FE | S68: Basketball;Feature;Frontend | U68: 45674
A69: Story | B69: =HYPERLINK("https://hawk-eye.atlassian.net/browse/BAS-1053?atlOrigin=eyJpIjoiYzgwYTQ0ZjEyNzQzNGJhN2JmNjEyZTM0NmRhZWZhNjIiLCJwIjoic2hlZXRzLWppcmEifQ","BAS-1053") -> BAS-1053 | C69: Create Game Status Update Modal | D69: P3 - Medium | E69: Closed | F69: 45712.901 | G69: =HYPERLINK("https://hawk-eye.atlassian.net/issues/?atlOrigin=eyJpIjoiYzgwYTQ0ZjEyNzQzNGJhN2JmNjEyZTM0NmRhZWZhNjIiLCJwIjoic2hlZXRzLWppcmEifQ&jql=key+in+%28BAS-1050%2CBAS-1054%29","BAS-1050;BAS-1054") -> BAS-1050;BAS-1054 | H69: Basketball & Baseball Data Platform | M69: [no field found] | N69: [no field found] | O69: [no field found] | Q69: 45824.413 | R69: 2.41 FE | S69: Basketball;Feature;Frontend | U69: 45674
A70: Story | B70: =HYPERLINK("https://hawk-eye.atlassian.net/browse/BAS-1050?atlOrigin=eyJpIjoiYzgwYTQ0ZjEyNzQzNGJhN2JmNjEyZTM0NmRhZWZhNjIiLCJwIjoic2hlZXRzLWppcmEifQ","BAS-1050") -> BAS-1050 | C70: Create Game Status Update Page | D70: P3 - Medium | E70: Closed | F70: 45712.883 | G70: =HYPERLINK("https://hawk-eye.atlassian.net/issues/?atlOrigin=eyJpIjoiYzgwYTQ0ZjEyNzQzNGJhN2JmNjEyZTM0NmRhZWZhNjIiLCJwIjoic2hlZXRzLWppcmEifQ&jql=key+in+%28BAS-1044%2CBAS-1053%2CBAS-1092%29","BAS-1044;BAS-1053;BAS-1092") -> BAS-1044;BAS-1053;BAS-1092 | H70: Basketball & Baseball Data Platform | M70: [no field found] | N70: [no field found] | O70: [no field found] | Q70: 45824.495 | R70: 2.41 FE | S70: Basketball;Feature;Frontend | T70: 1 | U70: 45667
A71: Story | B71: =HYPERLINK("https://hawk-eye.atlassian.net/browse/BAS-1044?atlOrigin=eyJpIjoiYzgwYTQ0ZjEyNzQzNGJhN2JmNjEyZTM0NmRhZWZhNjIiLCJwIjoic2hlZXRzLWppcmEifQ","BAS-1044") -> BAS-1044 | C71: Create Game Card Component | D71: P3 - Medium | E71: Closed | F71: 45712.571 | G71: =HYPERLINK("https://hawk-eye.atlassian.net/browse/BAS-1050?atlOrigin=eyJpIjoiYzgwYTQ0ZjEyNzQzNGJhN2JmNjEyZTM0NmRhZWZhNjIiLCJwIjoic2hlZXRzLWppcmEifQ","BAS-1050") -> BAS-1050 | H71: Basketball & Baseball Data Platform | M71: [no field found] | N71: [no field found] | O71: [no field found] | Q71: 45824.558 | R71: 2.41 FE | S71: Basketball;Feature;Frontend | U71: 45674
A72: Bug | B72: =HYPERLINK("https://hawk-eye.atlassian.net/browse/BAS-1038?atlOrigin=eyJpIjoiYzgwYTQ0ZjEyNzQzNGJhN2JmNjEyZTM0NmRhZWZhNjIiLCJwIjoic2hlZXRzLWppcmEifQ","BAS-1038") -> BAS-1038 | C72: CLONE - Last touch details in bson moved | D72: P2 - High | E72: Closed | F72: 45709.406 | G72: =HYPERLINK("https://hawk-eye.atlassian.net/issues/?atlOrigin=eyJpIjoiYzgwYTQ0ZjEyNzQzNGJhN2JmNjEyZTM0NmRhZWZhNjIiLCJwIjoic2hlZXRzLWppcmEifQ&jql=key+in+%28BAS-824%2CBAS-580%29","BAS-824;BAS-580") -> BAS-824;BAS-580 | H72: Basketball & Baseball Data Platform | M72: [no field found] | N72: [no field found] | O72: [no field found] | Q72: 45720.567 | S72: Basketball | U72: 45674
A73: Bug | B73: =HYPERLINK("https://hawk-eye.atlassian.net/browse/BAS-1036?atlOrigin=eyJpIjoiYzgwYTQ0ZjEyNzQzNGJhN2JmNjEyZTM0NmRhZWZhNjIiLCJwIjoic2hlZXRzLWppcmEifQ","BAS-1036") -> BAS-1036 | C73: BasketballFramerateAnalyser error when data is uploaded via cyberduck | D73: P5 - Lowest | E73: Closed | F73: 45708.645 | G73: =HYPERLINK("https://hawk-eye.atlassian.net/browse/BAS-835?atlOrigin=eyJpIjoiYzgwYTQ0ZjEyNzQzNGJhN2JmNjEyZTM0NmRhZWZhNjIiLCJwIjoic2hlZXRzLWppcmEifQ","BAS-835") -> BAS-835 | H73: Basketball & Baseball Data Platform | M73: [no field found] | N73: [no field found] | O73: [no field found] | Q73: 45715.614 | S73: Basketball | T73: 1 | U73: 45667
A74: Story | B74: =HYPERLINK("https://hawk-eye.atlassian.net/browse/BAS-1034?atlOrigin=eyJpIjoiYzgwYTQ0ZjEyNzQzNGJhN2JmNjEyZTM0NmRhZWZhNjIiLCJwIjoic2hlZXRzLWppcmEifQ","BAS-1034") -> BAS-1034 | C74: Automate Copying of G League games from S3 to Azure | D74: P5 - Lowest | E74: Closed | F74: 45707.454 | G74: =HYPERLINK("https://hawk-eye.atlassian.net/issues/?atlOrigin=eyJpIjoiYzgwYTQ0ZjEyNzQzNGJhN2JmNjEyZTM0NmRhZWZhNjIiLCJwIjoic2hlZXRzLWppcmEifQ&jql=key+in+%28BAS-1022%2CDEVOPS-944%2CBAS-1226%29","BAS-1022;DEVOPS-944;BAS-1226") -> BAS-1022;DEVOPS-944;BAS-1226 | H74: Basketball & Baseball Data Platform | M74: [no field found] | N74: [no field found] | O74: [no field found] | Q74: 45762.589 | S74: Basketball | U74: 45674
A75: Story | B75: =HYPERLINK("https://hawk-eye.atlassian.net/browse/BAS-1023?atlOrigin=eyJpIjoiYzgwYTQ0ZjEyNzQzNGJhN2JmNjEyZTM0NmRhZWZhNjIiLCJwIjoic2hlZXRzLWppcmEifQ","BAS-1023") -> BAS-1023 | C75: Improve logging for live ngss events s3 output | D75: P5 - Lowest | E75: Closed | F75: 45701.43 | G75: =HYPERLINK("https://hawk-eye.atlassian.net/browse/?atlOrigin=eyJpIjoiYzgwYTQ0ZjEyNzQzNGJhN2JmNjEyZTM0NmRhZWZhNjIiLCJwIjoic2hlZXRzLWppcmEifQ","") | H75: Basketball & Baseball Data Platform | M75: [no field found] | N75: [no field found] | O75: [no field found] | Q75: 45742.598 | S75: Basketball | U75: 45674
A76: Story | B76: =HYPERLINK("https://hawk-eye.atlassian.net/browse/BAS-1018?atlOrigin=eyJpIjoiYzgwYTQ0ZjEyNzQzNGJhN2JmNjEyZTM0NmRhZWZhNjIiLCJwIjoic2hlZXRzLWppcmEifQ","BAS-1018") -> BAS-1018 | C76: Don't allow inactive players to be paired with jersey numbers from tracking | D76: P3 - Medium | E76: Closed | F76: 45698.774 | G76: =HYPERLINK("https://hawk-eye.atlassian.net/browse/?atlOrigin=eyJpIjoiYzgwYTQ0ZjEyNzQzNGJhN2JmNjEyZTM0NmRhZWZhNjIiLCJwIjoic2hlZXRzLWppcmEifQ","") | H76: Basketball & Baseball Data Platform | M76: [no field found] | N76: [no field found] | O76: [no field found] | Q76: 45735.634 | R76: 2.38.1 | S76: Basketball | U76: 45692
A77: Story | B77: =HYPERLINK("https://hawk-eye.atlassian.net/browse/BAS-1017?atlOrigin=eyJpIjoiYzgwYTQ0ZjEyNzQzNGJhN2JmNjEyZTM0NmRhZWZhNjIiLCJwIjoic2hlZXRzLWppcmEifQ","BAS-1017") -> BAS-1017 | C77: Remove push branches from CI pipeline | D77: P5 - Lowest | E77: Closed | F77: 45698.638 | G77: =HYPERLINK("https://hawk-eye.atlassian.net/browse/?atlOrigin=eyJpIjoiYzgwYTQ0ZjEyNzQzNGJhN2JmNjEyZTM0NmRhZWZhNjIiLCJwIjoic2hlZXRzLWppcmEifQ","") | H77: Basketball & Baseball Data Platform | M77: [no field found] | N77: [no field found] | O77: [no field found] | Q77: 45699.428 | R77: 2.38 | S77: Basketball | U77: 45658
A78: Bug | B78: =HYPERLINK("https://hawk-eye.atlassian.net/browse/BAS-1010?atlOrigin=eyJpIjoiYzgwYTQ0ZjEyNzQzNGJhN2JmNjEyZTM0NmRhZWZhNjIiLCJwIjoic2hlZXRzLWppcmEifQ","BAS-1010") -> BAS-1010 | C78: SFG: Teams data missing from output json for non NGSS games | D78: P3 - Medium | E78: Closed | F78: 45694.353 | G78: =HYPERLINK("https://hawk-eye.atlassian.net/browse/BAS-733?atlOrigin=eyJpIjoiYzgwYTQ0ZjEyNzQzNGJhN2JmNjEyZTM0NmRhZWZhNjIiLCJwIjoic2hlZXRzLWppcmEifQ","BAS-733") -> BAS-733 | H78: Basketball & Baseball Data Platform | M78: [no field found] | N78: [no field found] | O78: [no field found] | Q78: 45695.593 | R78: 2.37 | S78: Basketball | U78: 45658
A79: Bug | B79: =HYPERLINK("https://hawk-eye.atlassian.net/browse/BAS-1002?atlOrigin=eyJpIjoiYzgwYTQ0ZjEyNzQzNGJhN2JmNjEyZTM0NmRhZWZhNjIiLCJwIjoic2hlZXRzLWppcmEifQ","BAS-1002") -> BAS-1002 | C79: Should not default AWS Endpoint for production in LFG config | D79: P1 - Highest | E79: Closed | F79: 45688.377 | G79: =HYPERLINK("https://hawk-eye.atlassian.net/browse/?atlOrigin=eyJpIjoiYzgwYTQ0ZjEyNzQzNGJhN2JmNjEyZTM0NmRhZWZhNjIiLCJwIjoic2hlZXRzLWppcmEifQ","") | H79: Basketball & Baseball Data Platform | M79: [no field found] | N79: [no field found] | O79: [no field found] | Q79: 45693.437 | R79: 2.37 | S79: Basketball | T79: 1 | U79: 45667
A80: Bug | B80: =HYPERLINK("https://hawk-eye.atlassian.net/browse/BAS-1001?atlOrigin=eyJpIjoiYzgwYTQ0ZjEyNzQzNGJhN2JmNjEyZTM0NmRhZWZhNjIiLCJwIjoic2hlZXRzLWppcmEifQ","BAS-1001") -> BAS-1001 | C80: Foul drawn message from NGSS on missed shots being backfilled into Hawkeye event but also creating new event | D80: P5 - Lowest | E80: Backlog | F80: 45687.968 | G80: =HYPERLINK("https://hawk-eye.atlassian.net/issues/?atlOrigin=eyJpIjoiYzgwYTQ0ZjEyNzQzNGJhN2JmNjEyZTM0NmRhZWZhNjIiLCJwIjoic2hlZXRzLWppcmEifQ&jql=key+in+%28BAS-663%2CBAS-1097%29","BAS-663;BAS-1097") -> BAS-663;BAS-1097 | H80: Basketball & Baseball Data Platform | M80: [no field found] | N80: [no field found] | O80: [no field found] | Q80: 45838.463 | S80: Basketball;Improvement | T80: 2.1 | U80: 45672
A81: Story | B81: =HYPERLINK("https://hawk-eye.atlassian.net/browse/BAS-972?atlOrigin=eyJpIjoiYzgwYTQ0ZjEyNzQzNGJhN2JmNjEyZTM0NmRhZWZhNjIiLCJwIjoic2hlZXRzLWppcmEifQ","BAS-972") -> BAS-972 | C81: SFG log message to print how long upload process took | D81: P4 - Low | E81: Backlog | F81: 45674.848 | G81: =HYPERLINK("https://hawk-eye.atlassian.net/browse/?atlOrigin=eyJpIjoiYzgwYTQ0ZjEyNzQzNGJhN2JmNjEyZTM0NmRhZWZhNjIiLCJwIjoic2hlZXRzLWppcmEifQ","") | H81: Basketball & Baseball Data Platform | M81: [no field found] | N81: [no field found] | O81: [no field found] | Q81: 45674.848 | S81: Basketball | U81: 45658
A82: Story | B82: =HYPERLINK("https://hawk-eye.atlassian.net/browse/BAS-967?atlOrigin=eyJpIjoiYzgwYTQ0ZjEyNzQzNGJhN2JmNjEyZTM0NmRhZWZhNjIiLCJwIjoic2hlZXRzLWppcmEifQ","BAS-967") -> BAS-967 | C82: Component test environment setup | D82: P5 - Lowest | E82: In Progress | F82: 45674.344 | G82: =HYPERLINK("https://hawk-eye.atlassian.net/issues/?atlOrigin=eyJpIjoiYzgwYTQ0ZjEyNzQzNGJhN2JmNjEyZTM0NmRhZWZhNjIiLCJwIjoic2hlZXRzLWppcmEifQ&jql=key+in+%28BAS-968%2CBAS-969%2CBAS-667%29","BAS-968;BAS-969;BAS-667") -> BAS-968;BAS-969;BAS-667 | H82: Basketball & Baseball Data Platform | M82: [no field found] | N82: [no field found] | O82: [no field found] | Q82: 45714.39 | S82: Basketball | T82: 2.1 | U82: 45672
A83: Bug | B83: =HYPERLINK("https://hawk-eye.atlassian.net/browse/BAS-964?atlOrigin=eyJpIjoiYzgwYTQ0ZjEyNzQzNGJhN2JmNjEyZTM0NmRhZWZhNjIiLCJwIjoic2hlZXRzLWppcmEifQ","BAS-964") -> BAS-964 | C83: Pose backfill not working for event 660 in game 0022400007 | D83: P1 - Highest | E83: Closed | F83: 45672.583 | G83: =HYPERLINK("https://hawk-eye.atlassian.net/issues/?atlOrigin=eyJpIjoiYzgwYTQ0ZjEyNzQzNGJhN2JmNjEyZTM0NmRhZWZhNjIiLCJwIjoic2hlZXRzLWppcmEifQ&jql=key+in+%28BAS-838%2CBAS-971%29","BAS-838;BAS-971") -> BAS-838;BAS-971 | H83: Basketball & Baseball Data Platform | M83: [no field found] | N83: [no field found] | O83: [no field found] | Q83: 45691.449 | R83: 2.37 | S83: Basketball | U83: 45699
A84: Story | B84: =HYPERLINK("https://hawk-eye.atlassian.net/browse/BAS-959?atlOrigin=eyJpIjoiYzgwYTQ0ZjEyNzQzNGJhN2JmNjEyZTM0NmRhZWZhNjIiLCJwIjoic2hlZXRzLWppcmEifQ","BAS-959") -> BAS-959 | C84: Create DD alert for missing post game combined events | D84: P3 - Medium | E84: To Test | F84: 45670.886 | G84: =HYPERLINK("https://hawk-eye.atlassian.net/browse/?atlOrigin=eyJpIjoiYzgwYTQ0ZjEyNzQzNGJhN2JmNjEyZTM0NmRhZWZhNjIiLCJwIjoic2hlZXRzLWppcmEifQ","") | H84: Basketball & Baseball Data Platform | M84: [no field found] | N84: [no field found] | O84: [no field found] | Q84: 45691.509 | R84: 2.38;2.39 | S84: Basketball;InternalCustomer | U84: 45699
A85: Story | B85: =HYPERLINK("https://hawk-eye.atlassian.net/browse/BAS-957?atlOrigin=eyJpIjoiYzgwYTQ0ZjEyNzQzNGJhN2JmNjEyZTM0NmRhZWZhNjIiLCJwIjoic2hlZXRzLWppcmEifQ","BAS-957") -> BAS-957 | C85: SFG & LFG need to write a process file on startup for Configurator | D85: P3 - Medium | E85: Closed | F85: 45670.522 | G85: =HYPERLINK("https://hawk-eye.atlassian.net/browse/?atlOrigin=eyJpIjoiYzgwYTQ0ZjEyNzQzNGJhN2JmNjEyZTM0NmRhZWZhNjIiLCJwIjoic2hlZXRzLWppcmEifQ","") | H85: Basketball & Baseball Data Platform | M85: [no field found] | N85: [no field found] | O85: [no field found] | Q85: 45692.656 | R85: 2.37 | S85: Basketball | U85: 45662
A86: Bug | B86: =HYPERLINK("https://hawk-eye.atlassian.net/browse/BAS-956?atlOrigin=eyJpIjoiYzgwYTQ0ZjEyNzQzNGJhN2JmNjEyZTM0NmRhZWZhNjIiLCJwIjoic2hlZXRzLWppcmEifQ","BAS-956") -> BAS-956 | C86: SFG & LFG require the AWS region to be available when launching. | D86: P4 - Low | E86: Backlog | F86: 45670.394 | G86: =HYPERLINK("https://hawk-eye.atlassian.net/browse/?atlOrigin=eyJpIjoiYzgwYTQ0ZjEyNzQzNGJhN2JmNjEyZTM0NmRhZWZhNjIiLCJwIjoic2hlZXRzLWppcmEifQ","") | H86: Basketball & Baseball Data Platform | M86: [no field found] | N86: [no field found] | O86: [no field found] | Q86: 45670.394 | S86: Basketball | T86: 2.1 | U86: 45672
A87: Story | B87: =HYPERLINK("https://hawk-eye.atlassian.net/browse/BAS-845?atlOrigin=eyJpIjoiYzgwYTQ0ZjEyNzQzNGJhN2JmNjEyZTM0NmRhZWZhNjIiLCJwIjoic2hlZXRzLWppcmEifQ","BAS-845") -> BAS-845 | C87: Remove inactive players from dashboard | D87: P2 - High | E87: Closed | F87: 45649.696 | G87: =HYPERLINK("https://hawk-eye.atlassian.net/browse/?atlOrigin=eyJpIjoiYzgwYTQ0ZjEyNzQzNGJhN2JmNjEyZTM0NmRhZWZhNjIiLCJwIjoic2hlZXRzLWppcmEifQ","") | H87: Basketball & Baseball Data Platform | M87: [no field found] | N87: [no field found] | O87: [no field found] | Q87: 45667.97 | S87: Basketball | T87: 2.1 | U87: 45672
A88: Bug | B88: =HYPERLINK("https://hawk-eye.atlassian.net/browse/BAS-844?atlOrigin=eyJpIjoiYzgwYTQ0ZjEyNzQzNGJhN2JmNjEyZTM0NmRhZWZhNjIiLCJwIjoic2hlZXRzLWppcmEifQ","BAS-844") -> BAS-844 | C88: Reprocessing Manager fails when selecting season | D88: P5 - Lowest | E88: Closed | F88: 45645.445 | G88: =HYPERLINK("https://hawk-eye.atlassian.net/browse/?atlOrigin=eyJpIjoiYzgwYTQ0ZjEyNzQzNGJhN2JmNjEyZTM0NmRhZWZhNjIiLCJwIjoic2hlZXRzLWppcmEifQ","") | H88: Basketball & Baseball Data Platform | M88: [no field found] | N88: [no field found] | O88: [no field found] | Q88: 45684.525 | R88: 2.37 | S88: Basketball | T88: 2.1 | U88: 45674
A89: Bug | B89: =HYPERLINK("https://hawk-eye.atlassian.net/browse/BAS-843?atlOrigin=eyJpIjoiYzgwYTQ0ZjEyNzQzNGJhN2JmNjEyZTM0NmRhZWZhNjIiLCJwIjoic2hlZXRzLWppcmEifQ","BAS-843") -> BAS-843 | C89: SFG not reading all the events from all_events folder | D89: P1 - Highest | E89: Closed | F89: 45645.102 | G89: =HYPERLINK("https://hawk-eye.atlassian.net/browse/?atlOrigin=eyJpIjoiYzgwYTQ0ZjEyNzQzNGJhN2JmNjEyZTM0NmRhZWZhNjIiLCJwIjoic2hlZXRzLWppcmEifQ","") | H89: Basketball & Baseball Data Platform | M89: [no field found] | N89: [no field found] | O89: [no field found] | Q89: 45660.552 | R89: 2.35.2 | S89: Basketball | U89: 45699
A90: Bug | B90: =HYPERLINK("https://hawk-eye.atlassian.net/browse/BAS-842?atlOrigin=eyJpIjoiYzgwYTQ0ZjEyNzQzNGJhN2JmNjEyZTM0NmRhZWZhNjIiLCJwIjoic2hlZXRzLWppcmEifQ","BAS-842") -> BAS-842 | C90: Period = 9 in post game combined events feed | D90: P2 - High | E90: Closed | F90: 45645.017 | G90: =HYPERLINK("https://hawk-eye.atlassian.net/browse/?atlOrigin=eyJpIjoiYzgwYTQ0ZjEyNzQzNGJhN2JmNjEyZTM0NmRhZWZhNjIiLCJwIjoic2hlZXRzLWppcmEifQ","") | H90: Basketball & Baseball Data Platform | M90: [no field found] | N90: [no field found] | O90: [no field found] | Q90: 45646.659 | R90: 2.35.2 | S90: Basketball | T90: 2.2 | U90: 45674
A91: Bug | B91: =HYPERLINK("https://hawk-eye.atlassian.net/browse/BAS-841?atlOrigin=eyJpIjoiYzgwYTQ0ZjEyNzQzNGJhN2JmNjEyZTM0NmRhZWZhNjIiLCJwIjoic2hlZXRzLWppcmEifQ","BAS-841") -> BAS-841 | C91: Pose backfilling has issues working when the clock is not running | D91: P2 - High | E91: Closed | F91: 45644.978 | G91: =HYPERLINK("https://hawk-eye.atlassian.net/browse/BAS-1073?atlOrigin=eyJpIjoiYzgwYTQ0ZjEyNzQzNGJhN2JmNjEyZTM0NmRhZWZhNjIiLCJwIjoic2hlZXRzLWppcmEifQ","BAS-1073") -> BAS-1073 | H91: Basketball & Baseball Data Platform | M91: [no field found] | N91: [no field found] | O91: [no field found] | Q91: 45770.295 | S91: Basketball | T91: 2.35.2 | U91: 45646
A92: Bug | B92: =HYPERLINK("https://hawk-eye.atlassian.net/browse/BAS-840?atlOrigin=eyJpIjoiYzgwYTQ0ZjEyNzQzNGJhN2JmNjEyZTM0NmRhZWZhNjIiLCJwIjoic2hlZXRzLWppcmEifQ","BAS-840") -> BAS-840 | C92: Normal event matching/backfilling not working all the time when events exists | D92: P2 - High | E92: Closed | F92: 45644.958 | G92: =HYPERLINK("https://hawk-eye.atlassian.net/browse/?atlOrigin=eyJpIjoiYzgwYTQ0ZjEyNzQzNGJhN2JmNjEyZTM0NmRhZWZhNjIiLCJwIjoic2hlZXRzLWppcmEifQ","") | H92: Basketball & Baseball Data Platform | M92: [no field found] | N92: [no field found] | O92: [no field found] | Q92: 45854.594 | S92: Basketball | U92: 45699
A93: Bug | B93: =HYPERLINK("https://hawk-eye.atlassian.net/browse/BAS-838?atlOrigin=eyJpIjoiYzgwYTQ0ZjEyNzQzNGJhN2JmNjEyZTM0NmRhZWZhNjIiLCJwIjoic2hlZXRzLWppcmEifQ","BAS-838") -> BAS-838 | C93: Pose backfill selectively not applied | D93: P1 - Highest | E93: Closed | F93: 45644.938 | G93: =HYPERLINK("https://hawk-eye.atlassian.net/browse/BAS-964?atlOrigin=eyJpIjoiYzgwYTQ0ZjEyNzQzNGJhN2JmNjEyZTM0NmRhZWZhNjIiLCJwIjoic2hlZXRzLWppcmEifQ","BAS-964") -> BAS-964 | H93: Basketball & Baseball Data Platform | M93: [no field found] | N93: [no field found] | O93: [no field found] | Q93: 45691.448 | R93: 2.37 | S93: Basketball | U93: 45691
A94: Story | B94: =HYPERLINK("https://hawk-eye.atlassian.net/browse/BAS-836?atlOrigin=eyJpIjoiYzgwYTQ0ZjEyNzQzNGJhN2JmNjEyZTM0NmRhZWZhNjIiLCJwIjoic2hlZXRzLWppcmEifQ","BAS-836") -> BAS-836 | C94: Change reconnect policy on Websocket when game not active | D94: P3 - Medium | E94: Closed | F94: 45642.949 | G94: =HYPERLINK("https://hawk-eye.atlassian.net/browse/BAS-1070?atlOrigin=eyJpIjoiYzgwYTQ0ZjEyNzQzNGJhN2JmNjEyZTM0NmRhZWZhNjIiLCJwIjoic2hlZXRzLWppcmEifQ","BAS-1070") -> BAS-1070 | H94: Basketball & Baseball Data Platform | M94: [no field found] | N94: [no field found] | O94: [no field found] | Q94: 45770.588 | R94: 2.39 | S94: Basketball | T94: 2.35.2 | U94: 45646
A95: Story | B95: =HYPERLINK("https://hawk-eye.atlassian.net/browse/BAS-835?atlOrigin=eyJpIjoiYzgwYTQ0ZjEyNzQzNGJhN2JmNjEyZTM0NmRhZWZhNjIiLCJwIjoic2hlZXRzLWppcmEifQ","BAS-835") -> BAS-835 | C95: Make a tool to check framerates | D95: P5 - Lowest | E95: Closed | F95: 45638.444 | G95: =HYPERLINK("https://hawk-eye.atlassian.net/issues/?atlOrigin=eyJpIjoiYzgwYTQ0ZjEyNzQzNGJhN2JmNjEyZTM0NmRhZWZhNjIiLCJwIjoic2hlZXRzLWppcmEifQ&jql=key+in+%28BAS-809%2CBAS-1036%29","BAS-809;BAS-1036") -> BAS-809;BAS-1036 | H95: Basketball & Baseball Data Platform | M95: [no field found] | N95: [no field found] | O95: [no field found] | Q95: 45714.367 | R95: 2.38 | S95: Basketball | T95: 2.36 | U95: 45665
A96: Bug | B96: =HYPERLINK("https://hawk-eye.atlassian.net/browse/BAS-833?atlOrigin=eyJpIjoiYzgwYTQ0ZjEyNzQzNGJhN2JmNjEyZTM0NmRhZWZhNjIiLCJwIjoic2hlZXRzLWppcmEifQ","BAS-833") -> BAS-833 | C96: When there are errors uploading to Azure from SFG, the number of files expected to be uploaded is showing as negative | D96: P3 - Medium | E96: Backlog | F96: 45637.492 | G96: =HYPERLINK("https://hawk-eye.atlassian.net/browse/?atlOrigin=eyJpIjoiYzgwYTQ0ZjEyNzQzNGJhN2JmNjEyZTM0NmRhZWZhNjIiLCJwIjoic2hlZXRzLWppcmEifQ","") | H96: Basketball & Baseball Data Platform | M96: [no field found] | N96: [no field found] | O96: [no field found] | Q96: 45637.492 | S96: Basketball | T96: 2.36 | U96: 45692
A97: Bug | B97: =HYPERLINK("https://hawk-eye.atlassian.net/browse/BAS-824?atlOrigin=eyJpIjoiYzgwYTQ0ZjEyNzQzNGJhN2JmNjEyZTM0NmRhZWZhNjIiLCJwIjoic2hlZXRzLWppcmEifQ","BAS-824") -> BAS-824 | C97: Last touch details in bson moved | D97: P2 - High | E97: Closed | F97: 45629.927 | G97: =HYPERLINK("https://hawk-eye.atlassian.net/issues/?atlOrigin=eyJpIjoiYzgwYTQ0ZjEyNzQzNGJhN2JmNjEyZTM0NmRhZWZhNjIiLCJwIjoic2hlZXRzLWppcmEifQ&jql=key+in+%28BAS-580%2CBAS-1038%29","BAS-580;BAS-1038") -> BAS-580;BAS-1038 | H97: Basketball & Baseball Data Platform | M97: [no field found] | N97: [no field found] | O97: [no field found] | Q97: 45709.406 | R97: 2.38 | S97: Basketball | T97: 2.36 | U97: 45692
A98: Story | B98: =HYPERLINK("https://hawk-eye.atlassian.net/browse/BAS-821?atlOrigin=eyJpIjoiYzgwYTQ0ZjEyNzQzNGJhN2JmNjEyZTM0NmRhZWZhNjIiLCJwIjoic2hlZXRzLWppcmEifQ","BAS-821") -> BAS-821 | C98: Add log message to PMEG that says how many events weren't backfilled | D98: P2 - High | E98: Closed | F98: 45624.984 | G98: =HYPERLINK("https://hawk-eye.atlassian.net/browse/?atlOrigin=eyJpIjoiYzgwYTQ0ZjEyNzQzNGJhN2JmNjEyZTM0NmRhZWZhNjIiLCJwIjoic2hlZXRzLWppcmEifQ","") | H98: Basketball & Baseball Data Platform | M98: [no field found] | N98: [no field found] | O98: [no field found] | Q98: 45712.546 | R98: 2.38 | S98: Basketball | T98: 2.37 | U98: 45692
A99: Bug | B99: =HYPERLINK("https://hawk-eye.atlassian.net/browse/BAS-815?atlOrigin=eyJpIjoiYzgwYTQ0ZjEyNzQzNGJhN2JmNjEyZTM0NmRhZWZhNjIiLCJwIjoic2hlZXRzLWppcmEifQ","BAS-815") -> BAS-815 | C99: HE Observability call returns NBA keys | D99: P5 - Lowest | E99: Backlog | F99: 45616.581 | G99: =HYPERLINK("https://hawk-eye.atlassian.net/browse/?atlOrigin=eyJpIjoiYzgwYTQ0ZjEyNzQzNGJhN2JmNjEyZTM0NmRhZWZhNjIiLCJwIjoic2hlZXRzLWppcmEifQ","") | H99: Basketball & Baseball Data Platform | M99: [no field found] | N99: [no field found] | O99: [no field found] | Q99: 45616.581 | S99: Basketball | T99: 2.37 | U99: 45692
A100: Bug | B100: =HYPERLINK("https://hawk-eye.atlassian.net/browse/BAS-813?atlOrigin=eyJpIjoiYzgwYTQ0ZjEyNzQzNGJhN2JmNjEyZTM0NmRhZWZhNjIiLCJwIjoic2hlZXRzLWppcmEifQ","BAS-813") -> BAS-813 | C100: Live Events and Officiating Events feedNumber restart from 1 if LFG is restarted | D100: P3 - Medium | E100: Closed | F100: 45615.706 | G100: =HYPERLINK("https://hawk-eye.atlassian.net/browse/BAS-802?atlOrigin=eyJpIjoiYzgwYTQ0ZjEyNzQzNGJhN2JmNjEyZTM0NmRhZWZhNjIiLCJwIjoic2hlZXRzLWppcmEifQ","BAS-802") -> BAS-802 | H100: Basketball & Baseball Data Platform | M100: [no field found] | N100: [no field found] | O100: [no field found] | Q100: 45712.545 | S100: Basketball | U100: 45665
...

Sheet ProjectHealth
B2: Basketball Data platform | F2: release | G2: 2.41 FE
B3: As at
B4: =now() -> 46053.434
B5: Project Health | E5: release readiness
B6: =IF(COUNTIF(F7:G7,"Red")>0,"Red",if(COUNTIF(F7:G7,"Amber")>0,"Amber","Green")) -> Green | E6: Automation | F6: test execution | G6: bugs raised | H6: tech debt
E7: =IF(COUNTIF(N22:P24,"Red")>0,"Red",if(COUNTIF(N22:P24,"Amber")>0,"Amber","Green")) -> Red | F7: =IF(COUNTIF(N30:P32,"Red")>0,"Red",if(COUNTIF(N30:P32,"Amber")>0,"Amber","Green")) -> Green | G7: =IF(COUNTIF(J16,"Red")>0,"Red",if(COUNTIF(J16,"Amber")>0,"Amber","Green")) -> Green | H7: =COUNTIF(JIRA!E:E, "In Review")+COUNTIF(JIRA!E:E, "Backlog")+COUNTIF(JIRA!E:E, "On Hold)") -> 55
B10: Risk profile counts | D10: Release | I10: open bugs | J10: Release
D11: Impact of failure | I11: P1 - Highest | J11: =IF($J$10="Release",COUNTIFS(Issue_Type,"Bug",jira_priority,I11,jira_status,"<>Closed",jira_status,"<>Done",fixVersion,$G$2),COUNTIFS(Issue_Type,"Bug",jira_priority,I11,jira_status,"<>Closed",jira_status,"<>Done")) -> 0
D12: Minor | E12: Visible | F12: Interruption | G12: Total | I12: P2 - High | J12: =IF($J$10="Release",COUNTIFS(Issue_Type,"Bug",jira_priority,I12,jira_status,"<>Closed",jira_status,"<>Done",fixVersion,$G$2),COUNTIFS(Issue_Type,"Bug",jira_priority,I12,jira_status,"<>Closed",jira_status,"<>Done")) -> 0
B13: Likelihood of failure | C13: Very likely | D13: =IF(D10="Release",COUNTIFS(impact_of_failure,3,Likelihood_of_failure,1,release,G2),COUNTIFS(impact_of_failure,3,Likelihood_of_failure,1)) -> 0 | E13: =if(D10="Release",COUNTIFS(impact_of_failure,2,Likelihood_of_failure,1,release,G2),COUNTIFS(impact_of_failure,2,Likelihood_of_failure,1)) -> 0 | F13: =IF(D10="Release",COUNTIFS(impact_of_failure,1,Likelihood_of_failure,1,release,G2),COUNTIFS(impact_of_failure,1,Likelihood_of_failure,1)) -> 0 | G13: =SUM(D13:F13) -> 0 | I13: P3 - Medium | J13: =IF($J$10="Release",COUNTIFS(Issue_Type,"Bug",jira_priority,I13,jira_status,"<>Closed",jira_status,"<>Done",fixVersion,$G$2),COUNTIFS(Issue_Type,"Bug",jira_priority,I13,jira_status,"<>Closed",jira_status,"<>Done")) -> 0
C14: Quite likely | D14: =IF(D10="Release",COUNTIFS(impact_of_failure,3,Likelihood_of_failure,2,release,G2),COUNTIFS(impact_of_failure,3,Likelihood_of_failure,2)) -> 0 | E14: =IF(D10="Release",COUNTIFS(impact_of_failure,2,Likelihood_of_failure,2,release,G2),COUNTIFS(impact_of_failure,2,Likelihood_of_failure,2)) -> 0 | F14: =IF(D10="Release",COUNTIFS(impact_of_failure,1,Likelihood_of_failure,2,release,G2),COUNTIFS(impact_of_failure,1,Likelihood_of_failure,2)) -> 0 | G14: =SUM(D14:F14) -> 0 | I14: P4 - Low | J14: =IF($J$10="Release",COUNTIFS(Issue_Type,"Bug",jira_priority,I14,jira_status,"<>Closed",jira_status,"<>Done",fixVersion,$G$2),COUNTIFS(Issue_Type,"Bug",jira_priority,I14,jira_status,"<>Closed",jira_status,"<>Done")) -> 0
C15: Unlikely | D15: =IF(D10="Release",COUNTIFS(impact_of_failure,3,Likelihood_of_failure,3,release,G2),COUNTIFS(impact_of_failure,3,Likelihood_of_failure,3)) -> 0 | E15: =IF(D10="Release",COUNTIFS(impact_of_failure,2,Likelihood_of_failure,3,release,G2),COUNTIFS(impact_of_failure,2,Likelihood_of_failure,3)) -> 0 | F15: =IF(D10="Release",COUNTIFS(impact_of_failure,1,Likelihood_of_failure,3,release,G2),COUNTIFS(impact_of_failure,1,Likelihood_of_failure,3)) -> 0 | G15: =SUM(D15:F15) -> 0 | I15: P5 - Lowest | J15: =IF($J$10="Release",COUNTIFS(Issue_Type,"Bug",jira_priority,I15,jira_status,"<>Closed",jira_status,"<>Done",fixVersion,$G$2),COUNTIFS(Issue_Type,"Bug",jira_priority,I15,jira_status,"<>Closed",jira_status,"<>Done")) -> 0
C16: Total | D16: =SUM(D13:D15) -> 0 | E16: =SUM(E13:E15) -> 0 | F16: =SUM(F13:F15) -> 0 | G16: =SUM(G13:G15) -> 0 | I16: Status | J16: =IF(or(J11>0,J12>0),"Red",if(J13>0,"Amber","Green")) -> Green
B20: Automation coverage | D20: Project
C21: Minor | D21: Visible | E21: Interruption | F21: Total | I21: Minor | J21: Visible | K21: Interruption | N21: Minor | O21: Visible | P21: Interruption
B22: Very likely | C22: =IF(D20="Release",COUNTIFS(impact_of_failure,3,Likelihood_of_failure,1,can_be_automated,"Yes",release,H7),COUNTIFS(impact_of_failure,3,Likelihood_of_failure,1,can_be_automated,"Yes")) -> 1 | D22: =IF(D20="Release",COUNTIFS(impact_of_failure,2,Likelihood_of_failure,1,can_be_automated,"Yes",release,G2),COUNTIFS(impact_of_failure,2,Likelihood_of_failure,1,can_be_automated,"Yes")) -> 7 | E22: =IF(D20="Release",COUNTIFS(impact_of_failure,1,Likelihood_of_failure,1,can_be_automated,"Yes",release,G2),COUNTIFS(impact_of_failure,1,Likelihood_of_failure,1,can_be_automated,"Yes")) -> 14 | F22: =SUM(C22:E22) -> 22 | H22: Very likely | I22: =IFERROR(if(D20="Release",COUNTIFS(impact_of_failure,3,Likelihood_of_failure,1,Automation_status,"Yes",release,G2),COUNTIFS(impact_of_failure,3,Likelihood_of_failure,1,Automation_status,"Yes"))/C22,1) -> 1 | J22: =IFERROR(if(D20="Release",COUNTIFS(impact_of_failure,2,Likelihood_of_failure,1,Automation_status,"Yes",release,G2),COUNTIFS(impact_of_failure,2,Likelihood_of_failure,1,Automation_status,"Yes"))/D22,1) -> 0.28571429 | K22: =IFERROR(if(D20="Release",COUNTIFS(impact_of_failure,1,Likelihood_of_failure,1,Automation_status,"Yes",release,G2),COUNTIFS(impact_of_failure,1,Likelihood_of_failure,1,Automation_status,"Yes"))/E22,1) -> 0.071428571 | M22: Very likely | N22: =if(instructions!C$4=0,"Green",if(I22<instructions!H$4,"Red",if(AND(I22>=instructions!H$4,I22<instructions!C$4),"Amber","Green"))) -> Green | O22: =if(instructions!D4=0,"Green",if(J22<instructions!I4,"Red",if(AND(J22>=instructions!I4,J22<instructions!D4),"Amber","Green"))) -> Amber | P22: =if(instructions!E4=0,"Green",if(K22<instructions!J4,"Red",if(AND(K22>=instructions!J4,K22<instructions!E4),"Amber","Green"))) -> Red
B23: Quite likely | C23: =IF(D20="Release",COUNTIFS(impact_of_failure,3,Likelihood_of_failure,2,can_be_automated,"Yes",release,G2),COUNTIFS(impact_of_failure,3,Likelihood_of_failure,2,can_be_automated,"Yes")) -> 5 | D23: =IF(D20="Release",COUNTIFS(impact_of_failure,2,Likelihood_of_failure,2,can_be_automated,"Yes",release,G2),COUNTIFS(impact_of_failure,2,Likelihood_of_failure,2,can_be_automated,"Yes")) -> 20 | E23: =IF(D20="Release",COUNTIFS(impact_of_failure,1,Likelihood_of_failure,2,can_be_automated,"Yes",release,G2),COUNTIFS(impact_of_failure,1,Likelihood_of_failure,2,can_be_automated,"Yes")) -> 28 | F23: =SUM(C23:E23) -> 53 | H23: Quite likely | I23: =IFERROR(if(D20="Release",COUNTIFS(impact_of_failure,3,Likelihood_of_failure,2,Automation_status,"Yes",release,G2),COUNTIFS(impact_of_failure,3,Likelihood_of_failure,2,Automation_status,"Yes"))/C23,1) -> 0 | J23: =IFERROR(if(D20="Release", COUNTIFS(impact_of_failure,2,Likelihood_of_failure,2,Automation_status,"Yes",release,G2),COUNTIFS(impact_of_failure,2,Likelihood_of_failure,2,Automation_status,"Yes"))/D23,1) -> 0.15 | K23: =IFERROR(if(D20="Release",COUNTIFS(impact_of_failure,1,Likelihood_of_failure,2,Automation_status,"Yes",release,G2),COUNTIFS(impact_of_failure,1,Likelihood_of_failure,2,Automation_status,"Yes"))/E23,1) -> 0.21428571 | M23: Quite likely | N23: =if(instructions!C5=0,"Green",if(I23<instructions!H5,"Red",if(AND(I23>=instructions!H5,I23<instructions!C5),"Amber","Green"))) -> Green | O23: =if(instructions!D5=0,"Green",if(J23<instructions!I5,"Red",if(AND(J23>=instructions!I5,J23<instructions!D5),"Amber","Green"))) -> Amber | P23: =if(instructions!E5=0,"Green",if(K23<instructions!J5,"Red",if(AND(K23>=instructions!J5,K23<instructions!E5),"Amber","Green"))) -> Red
B24: Unlikely | C24: =IF(D20="Release",COUNTIFS(impact_of_failure,3,Likelihood_of_failure,3,can_be_automated,"Yes",release,G2),COUNTIFS(impact_of_failure,3,Likelihood_of_failure,3,can_be_automated,"Yes")) -> 4 | D24: =IF(D20="Release",COUNTIFS(impact_of_failure,2,Likelihood_of_failure,3,can_be_automated,"Yes",release,G2),COUNTIFS(impact_of_failure,2,Likelihood_of_failure,3,can_be_automated,"Yes")) -> 15 | E24: =IF(D20="Release",COUNTIFS(impact_of_failure,1,Likelihood_of_failure,3,can_be_automated,"Yes",release,G2),COUNTIFS(impact_of_failure,1,Likelihood_of_failure,3,can_be_automated,"Yes")) -> 13 | F24: =SUM(C24:E24) -> 32 | H24: Unlikely | I24: =IFERROR(if(D20="Release", COUNTIFS(impact_of_failure,3,Likelihood_of_failure,3,Automation_status,"Yes",release,G2),COUNTIFS(impact_of_failure,3,Likelihood_of_failure,3,Automation_status,"Yes"))/C24,1) -> 0 | J24: =IFERROR(if(D20="Release",COUNTIFS(impact_of_failure,2,Likelihood_of_failure,3,Automation_status,"Yes",release,G2),COUNTIFS(impact_of_failure,2,Likelihood_of_failure,3,Automation_status,"Yes"))/D24,1) -> 0 | K24: =IFERROR(if(D20="Release",COUNTIFS(impact_of_failure,1,Likelihood_of_failure,3,Automation_status,"Yes",release,G2),COUNTIFS(impact_of_failure,1,Likelihood_of_failure,3,Automation_status,"Yes"))/E24,1) -> 0.23076923 | M24: Unlikely | N24: =if(instructions!C6=0,"Green",if(I24<instructions!H6,"Red",if(AND(I24>=instructions!H6,I24<instructions!C6),"Amber","Green"))) -> Green | O24: =if(instructions!D6=0,"Green",if(J24<instructions!I6,"Red",if(AND(J24>=instructions!I6,J24<instructions!D6),"Amber","Green"))) -> Green | P24: =if(instructions!E6=0,"Green",if(K24<instructions!J6,"Red",if(AND(K24>=instructions!J6,K24<instructions!E6),"Amber","Green"))) -> Red
B25: Total | C25: =SUM(C22:C24) -> 10 | D25: =SUM(D22:D24) -> 42 | E25: =SUM(E22:E24) -> 55 | F25: =SUM(F22:F24) -> 107
B28: Test execution | D28: Release
C29: Minor | D29: Visible | E29: Interruption | F29: Total | I29: Minor | J29: Visible | K29: Interruption | N29: Minor | O29: Visible | P29: Interruption
B30: Very likely | C30: =IFERROR(if(D28="Release",COUNTIFS(impact_of_failure,3,Likelihood_of_failure,1,status,"Passed",release,G2),COUNTIFS(impact_of_failure,1,Likelihood_of_failure,3,status,"Passed")),0) -> 0 | D30: =IFERROR(if(D28="Release",COUNTIFS(impact_of_failure,2,Likelihood_of_failure,1,status,"Passed",release,G2),COUNTIFS(impact_of_failure,2,Likelihood_of_failure,1,status,"Passed")),0) -> 0 | E30: =IFERROR(if(D28="Release",COUNTIFS(impact_of_failure,1,Likelihood_of_failure,1,status,"Passed",release,G2),COUNTIFS(impact_of_failure,1,Likelihood_of_failure,1,status,"Passed")),0) -> 0 | F30: =SUM(C30:E30) -> 0 | H30: Very likely | I30: =IFERROR(C30/D13,1) -> 1 | J30: =IFERROR(D30/E13,1) -> 1 | K30: =IFERROR(E30/F13,1) -> 1 | M30: Very likely | N30: =if(instructions!C$4=0,"Green",if(I30<instructions!H$4,"Red",if(AND(I30>=instructions!H$4,I30<instructions!C$4),"Amber","Green"))) -> Green | O30: =if(instructions!D$4=0,"Green",if(J30<instructions!I$4,"Red",if(AND(J30>=instructions!I$4,J30<instructions!D$4),"Amber","Green"))) -> Green | P30: =if(instructions!E$4=0,"Green",if(K30<instructions!J$4,"Red",if(AND(K30>=instructions!J$4,K30<instructions!E$4),"Amber","Green"))) -> Green
B31: Quite likely | C31: =IFERROR(if(D28="Release",COUNTIFS(impact_of_failure,3,Likelihood_of_failure,2,status,"Passed",release,G2),COUNTIFS(impact_of_failure,3,Likelihood_of_failure,2,status,"Passed")),0) -> 0 | D31: =IFERROR(if(D28="Release",COUNTIFS(impact_of_failure,2,Likelihood_of_failure,2,status,"Passed",release,G2),COUNTIFS(impact_of_failure,2,Likelihood_of_failure,2,status,"Passed")),0) -> 0 | E31: =IFERROR(if(D28="Release",COUNTIFS(impact_of_failure,1,Likelihood_of_failure,2,status,"Passed",release,G2),COUNTIFS(impact_of_failure,1,Likelihood_of_failure,2,status,"Passed")),0) -> 0 | F31: =SUM(C31:E31) -> 0 | H31: Quite likely | I31: =IFERROR(C31/D14,1) -> 1 | J31: =IFERROR(D31/E14,1) -> 1 | K31: =IFERROR(E31/F14,1) -> 1 | M31: Quite likely | N31: =if(instructions!C$4=0,"Green",if(I31<instructions!H$4,"Red",if(AND(I31>=instructions!H$4,I31<instructions!C$4),"Amber","Green"))) -> Green | O31: =if(instructions!D$4=0,"Green",if(J31<instructions!I$4,"Red",if(AND(J31>=instructions!I$4,J31<instructions!D$4),"Amber","Green"))) -> Green | P31: =if(instructions!E$4=0,"Green",if(K31<instructions!J$4,"Red",if(AND(K31>=instructions!J$4,K31<instructions!E$4),"Amber","Green"))) -> Green
B32: Unlikely | C32: =IFERROR(if(D28="Release",COUNTIFS(impact_of_failure,3,Likelihood_of_failure,3,status,"Passed",release,G2),COUNTIFS(impact_of_failure,3,Likelihood_of_failure,3,status,"Passed")),0) -> 0 | D32: =IFERROR(if(D28="Release",COUNTIFS(impact_of_failure,2,Likelihood_of_failure,3,status,"Passed", release,G2),COUNTIFS(impact_of_failure,2,Likelihood_of_failure,3,status,"Passed")),0) -> 0 | E32: =IFERROR(if(D28="Release",COUNTIFS(impact_of_failure,1,Likelihood_of_failure,3,status,"Passed",release,G2),COUNTIFS(impact_of_failure,1,Likelihood_of_failure,3,status,"Passed")),0) -> 0 | F32: =SUM(C32:E32) -> 0 | H32: Unlikely | I32: =IFERROR(C32/D15,1) -> 1 | J32: =IFERROR(D32/E15,1) -> 1 | K32: =IFERROR(E32/F15,1) -> 1 | M32: Unlikely | N32: =if(instructions!C$4=0,"Green",if(I32<instructions!H$4,"Red",if(AND(I32>=instructions!H$4,I32<instructions!C$4),"Amber","Green"))) -> Green | O32: =if(instructions!D$4=0,"Green",if(J32<instructions!I$4,"Red",if(AND(J32>=instructions!I$4,J32<instructions!D$4),"Amber","Green"))) -> Green | P32: =if(instructions!E$4=0,"Green",if(K32<instructions!J$4,"Red",if(AND(K32>=instructions!J$4,K32<instructions!E$4),"Amber","Green"))) -> Green
B33: Total | C33: =SUM(C30:C32) -> 0 | D33: =SUM(D30:D32) -> 0 | E33: =SUM(E30:E32) -> 0 | F33: =SUM(F30:F32) -> 0
B36: Issue ID | C36: Test cases | D36: competed
B37: =IFERROR(__xludf.DUMMYFUNCTION("FILTER(issue_ID,fixVersion=G2)"),"BAS-1294") -> BAS-1294 | C37: =if(B37="","",COUNTIFS(linked_ID,B37)) -> 0 | D37: =if(B37="","",COUNTIFS(linked_ID,B37,status,"Passed")) -> 0
B38: =IFERROR(__xludf.DUMMYFUNCTION("""COMPUTED_VALUE"""),"BAS-1219") -> BAS-1219 | C38: =if(B38="","",COUNTIFS(linked_ID,B38)) -> 0 | D38: =if(B38="","",COUNTIFS(linked_ID,B38,status,"Passed")) -> 0
B39: =IFERROR(__xludf.DUMMYFUNCTION("""COMPUTED_VALUE"""),"BAS-1166") -> BAS-1166 | C39: =if(B39="","",COUNTIFS(linked_ID,B39)) -> 0 | D39: =if(B39="","",COUNTIFS(linked_ID,B39,status,"Passed")) -> 0
B40: =IFERROR(__xludf.DUMMYFUNCTION("""COMPUTED_VALUE"""),"BAS-1165") -> BAS-1165 | C40: =if(B40="","",COUNTIFS(linked_ID,B40)) -> 0 | D40: =if(B40="","",COUNTIFS(linked_ID,B40,status,"Passed")) -> 0
B41: =IFERROR(__xludf.DUMMYFUNCTION("""COMPUTED_VALUE"""),"BAS-1143") -> BAS-1143 | C41: =if(B41="","",COUNTIFS(linked_ID,B41)) -> 0 | D41: =if(B41="","",COUNTIFS(linked_ID,B41,status,"Passed")) -> 0
B42: =IFERROR(__xludf.DUMMYFUNCTION("""COMPUTED_VALUE"""),"BAS-1092") -> BAS-1092 | C42: =if(B42="","",COUNTIFS(linked_ID,B42)) -> 0
B43: =IFERROR(__xludf.DUMMYFUNCTION("""COMPUTED_VALUE"""),"BAS-1054") -> BAS-1054 | C43: =if(B43="","",COUNTIFS(linked_ID,B43)) -> 0
B44: =IFERROR(__xludf.DUMMYFUNCTION("""COMPUTED_VALUE"""),"BAS-1053") -> BAS-1053 | C44: =if(B44="","",COUNTIFS(linked_ID,B44)) -> 0
B45: =IFERROR(__xludf.DUMMYFUNCTION("""COMPUTED_VALUE"""),"BAS-1050") -> BAS-1050 | C45: =if(B45="","",COUNTIFS(linked_ID,B45)) -> 0
B46: =IFERROR(__xludf.DUMMYFUNCTION("""COMPUTED_VALUE"""),"BAS-1044") -> BAS-1044 | C46: =if(B46="","",COUNTIFS(linked_ID,B46)) -> 0
C47: =if(B47="","",COUNTIFS(linked_ID,B47))
C48: =if(B48="","",COUNTIFS(linked_ID,B48))
C49: =if(B49="","",COUNTIFS(linked_ID,B49))

Sheet Sheet10
B3: Release date | C3: Fix versions | D3: development | E3: tests | F3: bugs
B4: =VLOOKUP(C4,JIRA!$R$2:$U$1000,4,FALSE) -> 45692 | C4: {=UNIQUE(JIRA!R2:R1000)} | D4: =COUNTIFS(JIRA!$R$2:$R$1000,C4) -> 942 | E4: =COUNTIF('testmo-export-repository'!$Y$2:$Y$1000,C4) -> 940 | F4: =COUNTIFS(JIRA!$T$2:$T$1000,C4,JIRA!$A$2:$A$1000,"Bug") -> 25
B5: =VLOOKUP(C5,JIRA!$R$2:$U$1000,4,FALSE) -> 45658 | C5: 2.42 | D5: =COUNTIFS(JIRA!$R$2:$R$1000,C5) -> 3 | E5: =COUNTIF('testmo-export-repository'!$Y$2:$Y$1000,C5) -> 0 | F5: =COUNTIFS(JIRA!$T$2:$T$1000,C5,JIRA!$A$2:$A$1000,"Bug") -> 0
B6: =VLOOKUP(C6,JIRA!$R$2:$U$1000,4,FALSE) -> 45658 | C6: 2.41 | D6: =COUNTIFS(JIRA!$R$2:$R$1000,C6) -> 16 | E6: =COUNTIF('testmo-export-repository'!$Y$2:$Y$1000,C6) -> 0 | F6: =COUNTIFS(JIRA!$T$2:$T$1000,C6,JIRA!$A$2:$A$1000,"Bug") -> 0
B7: =VLOOKUP(C7,JIRA!$R$2:$U$1000,4,FALSE) -> 45667 | C7: 2.41 FE | D7: =COUNTIFS(JIRA!$R$2:$R$1000,C7) -> 10 | E7: =COUNTIF('testmo-export-repository'!$Y$2:$Y$1000,C7) -> 0 | F7: =COUNTIFS(JIRA!$T$2:$T$1000,C7,JIRA!$A$2:$A$1000,"Bug") -> 0
B8: =VLOOKUP(C8,JIRA!$R$2:$U$1000,4,FALSE) -> 45672 | C8: 2.40 | D8: =COUNTIFS(JIRA!$R$2:$R$1000,C8) -> 5 | E8: =COUNTIF('testmo-export-repository'!$Y$2:$Y$1000,C8) -> 0 | F8: =COUNTIFS(JIRA!$T$2:$T$1000,C8,JIRA!$A$2:$A$1000,"Bug") -> 0
B9: =VLOOKUP(C9,JIRA!$R$2:$U$1000,4,FALSE) -> 45674 | C9: 2.38.2 | D9: =COUNTIFS(JIRA!$R$2:$R$1000,C9) -> 1 | E9: =COUNTIF('testmo-export-repository'!$Y$2:$Y$1000,C9) -> 0 | F9: =COUNTIFS(JIRA!$T$2:$T$1000,C9,JIRA!$A$2:$A$1000,"Bug") -> 0
B10: =VLOOKUP(C10,JIRA!$R$2:$U$1000,4,FALSE) -> 45674 | C10: 2.39 | D10: =COUNTIFS(JIRA!$R$2:$R$1000,C10) -> 4 | E10: =COUNTIF('testmo-export-repository'!$Y$2:$Y$1000,C10) -> 7 | F10: =COUNTIFS(JIRA!$T$2:$T$1000,C10,JIRA!$A$2:$A$1000,"Bug") -> 0
B11: =VLOOKUP(C11,JIRA!$R$2:$U$1000,4,FALSE) -> 45692 | C11: 2.38.1 | D11: =COUNTIFS(JIRA!$R$2:$R$1000,C11) -> 1 | E11: =COUNTIF('testmo-export-repository'!$Y$2:$Y$1000,C11) -> 0 | F11: =COUNTIFS(JIRA!$T$2:$T$1000,C11,JIRA!$A$2:$A$1000,"Bug") -> 0
B12: =VLOOKUP(C12,JIRA!$R$2:$U$1000,4,FALSE) -> 45658 | C12: 2.38 | D12: =COUNTIFS(JIRA!$R$2:$R$1000,C12) -> 6 | E12: =COUNTIF('testmo-export-repository'!$Y$2:$Y$1000,C12) -> 27 | F12: =COUNTIFS(JIRA!$T$2:$T$1000,C12,JIRA!$A$2:$A$1000,"Bug") -> 0
B13: =VLOOKUP(C13,JIRA!$R$2:$U$1000,4,FALSE) -> 45658 | C13: 2.37 | D13: =COUNTIFS(JIRA!$R$2:$R$1000,C13) -> 7 | E13: =COUNTIF('testmo-export-repository'!$Y$2:$Y$1000,C13) -> 15 | F13: =COUNTIFS(JIRA!$T$2:$T$1000,C13,JIRA!$A$2:$A$1000,"Bug") -> 3
B14: =VLOOKUP(C14,JIRA!$R$2:$U$1000,4,FALSE) -> 45699 | C14: 2.38;2.39 | D14: =COUNTIFS(JIRA!$R$2:$R$1000,C14) -> 1 | E14: =COUNTIF('testmo-export-repository'!$Y$2:$Y$1000,C14) -> 0 | F14: =COUNTIFS(JIRA!$T$2:$T$1000,C14,JIRA!$A$2:$A$1000,"Bug") -> 0
B15: =VLOOKUP(C15,JIRA!$R$2:$U$1000,4,FALSE) -> 45699 | C15: 2.35.2 | D15: =COUNTIFS(JIRA!$R$2:$R$1000,C15) -> 2 | E15: =COUNTIF('testmo-export-repository'!$Y$2:$Y$1000,C15) -> 0 | F15: =COUNTIFS(JIRA!$T$2:$T$1000,C15,JIRA!$A$2:$A$1000,"Bug") -> 1
B16: =VLOOKUP(C16,JIRA!$R$2:$U$1000,4,FALSE) -> 45692 | C16: 2.36 | D16: =COUNTIFS(JIRA!$R$2:$R$1000,C16) -> 1 | E16: =COUNTIF('testmo-export-repository'!$Y$2:$Y$1000,C16) -> 0 | F16: =COUNTIFS(JIRA!$T$2:$T$1000,C16,JIRA!$A$2:$A$1000,"Bug") -> 2

Sheet testmo-export-repository
A1: ﻿"Case ID" | B1: Case | C1: Configurations | D1: Created at | E1: Created by | F1: Description | G1: Estimate | H1: Expected | I1: Folder | J1: Forecast | K1: Issues | L1: Priority | M1: State | N1: Status (latest) | O1: Status date | P1: Steps (Expected) | Q1: Steps (Step) | R1: Tags | S1: Template | T1: Updated at | U1: Updated by | V1: Automation status | W1: can be automated | X1: complexity | Y1: Release
A2: 1110 | B2: create new datadog metrics so we can set up automated alerts | D2: 2024-04-29T06:40:29.651Z | E2: Matthew East | I2: BAS-474 Create new metrics for reporting on number of files sent | K2: BAS-474 | L2: High | M2: Active | N2: Passed | O2: 2025-01-22T11:08:25.359Z | S2: Gherkin syntax | T2: 2025-01-22T08:28:24.023Z | U2: Matthew East | V2: No | W2: Yes | X2: Low
A3: 2033 | B3: Endpoint for starting feed generation - success | D3: 2024-07-30T08:00:49.587Z | E3: Matthew East | F3: <p>Given: SFG is running<br />and: request json contains gameID <br />and request json contains tracking Path<br />and game took place in last 48 hour window<br />When endpoint put request sent to endpoint<br />Then 200 status is returned<br /><br /><strong>examples</strong></p><figure class="table"><table><tbody><tr><td>request perimeters</td><td>included</td><td>valid</td><td>response</td></tr><tr><td>gameID</td><td>TRUE</td><td>TRUE</td><td>200</td></tr><tr><td>tracking path</td><td>TRUE</td><td>TRUE</td><td>200</td></tr><tr><td>events path</td><td>TRUE</td><td>TRUE</td><td>200</td></tr><tr><td>offset</td><td>TRUE</td><td>TRUE</td><td>200</td></tr><tr><td>force</td><td>FALSE</td><td>n/a</td><td>200</td></tr><tr><td>force</td><td>TRUE</td><td>n/a</td><td>200</td></tr></tbody></table></figure><p><br /> </p><p>endpoint<br />http://localhost:9229/scrubbedFeedGenerator/scrubbed/start</p> | I3: BAS-123 Scrubbed feed generator API | K3: BAS-121 | L3: High | M3: Active | S3: Gherkin syntax | T3: 2025-01-22T08:32:24.903Z | U3: Matthew East | V3: Yes | W3: Yes | X3: Normal
A4: 2034 | B4: request json bad request | D4: 2024-07-30T08:01:17.298Z | E4: Matthew East | F4: <p>Given SFG is running<br />and request json excludes &lt;parameter&gt;<br />and parameter is &lt;valid&gt;<br />when put request is sent to endpoint<br />then status 400 is returned<br /> </p><figure class="table"><table><tbody><tr><td>request permeteres</td><td>included</td><td>valid</td><td>response</td></tr><tr><td>gameID</td><td>FALSE</td><td>N/a</td><td>400</td></tr><tr><td>tracking path</td><td>FALSE</td><td>N/a</td><td>400</td></tr><tr><td>events path</td><td>FALSE</td><td>N/a</td><td>400</td></tr><tr><td>force</td><td>FALSE</td><td>FALSE</td><td>400</td></tr><tr><td>gameID</td><td>TRUE</td><td>FALSE</td><td>400</td></tr><tr><td>tracking path</td><td>TRUE</td><td>FALSE</td><td>400</td></tr><tr><td>events path</td><td>TRUE</td><td>FALSE</td><td>400</td></tr></tbody></table></figure><p><br /><br /><br /> </p> | I4: BAS-123 Scrubbed feed generator API | K4: BAS-121 | L4: Normal | M4: Active | S4: Gherkin syntax | T4: 2025-01-22T08:33:35.113Z | U4: Matthew East | V4: No | W4: No | X4: Normal
A5: 2044 | B5: SFG Scrubbed feeds | D5: 2024-07-30T15:18:29.475Z | E5: Matthew East | F5: <p>Given SFG is running<br />and put request has returned 200 response<br />when SFG reads data from directory<br />Then feed is assembled<br /><br />examples<br />feed<br />processed.pose.clean<br />processed.pose.complete</p> | I5: BAS-125 Assemble scrubbed pose feeds | K5: BAS-121 | L5: High | M5: Active | S5: Gherkin syntax | T5: 2025-01-22T08:34:30.908Z | U5: Matthew East | V5: Yes | W5: Yes | X5: Normal
A6: 2247 | B6: validate feed data processed.pose.clean | D6: 2024-07-31T12:56:45.304Z | E6: Matthew East | I6: BAS-125 Assemble scrubbed pose feeds | L6: High | M6: Active | S6: Gherkin syntax | T6: 2025-01-22T08:34:59.020Z | U6: Matthew East | V6: No | W6: Yes | X6: High
A7: 2248 | B7: validate feed data processed.pose.complete | D7: 2024-07-31T12:57:53.689Z | E7: Matthew East | I7: BAS-125 Assemble scrubbed pose feeds | L7: High | M7: Active | S7: Gherkin syntax | T7: 2025-01-22T08:35:33.654Z | U7: Matthew East | V7: No | W7: Yes | X7: High
A8: 2249 | B8: validate feed data processed.events.complete | D8: 2024-07-31T12:58:06.666Z | E8: Matthew East | I8: BAS-125 Assemble scrubbed pose feeds | L8: High | M8: Active | S8: Gherkin syntax | T8: 2025-01-22T08:35:54.333Z | U8: Matthew East | V8: No | W8: Yes | X8: High
A9: 2250 | B9: validate feed data processed.events.clean | D9: 2024-07-31T12:58:20.542Z | E9: Matthew East | I9: BAS-125 Assemble scrubbed pose feeds | L9: High | M9: Active | S9: Gherkin syntax | T9: 2025-01-22T08:36:21.667Z | U9: Matthew East | V9: No | W9: Yes | X9: High
A10: 2046 | B10: SFG Write feeds to disk | D10: 2024-07-30T15:26:05.246Z | E10: Matthew East | F10: <p>Given SFG is running<br />and put request returns 200 response<br />and output to disk is set in config <br />and assemblers have consumed bson data<br />Then feed is output to disk location </p> | I10: BAS-126 Output scrubbed feeds to disk | K10: BAS-121 | L10: Normal | M10: Active | S10: Gherkin syntax | T10: 2025-01-22T08:36:55.131Z | U10: Matthew East | V10: No | W10: Yes | X10: Normal
A11: 2047 | B11: SFG write to disk false | D11: 2024-07-30T15:31:34.840Z | E11: Matthew East | F11: <p>Given SFG is running<br />and put request returns 200 response<br />and output to disk is set to false in config <br />and assemblers have consumed bson data<br />Then feed is not output disk location</p> | I11: BAS-126 Output scrubbed feeds to disk | L11: Normal | M11: Active | S11: Gherkin syntax | T11: 2025-01-22T08:37:10.692Z | U11: Matthew East | V11: No | W11: Yes | X11: Normal
A12: 2224 | B12: Get and populate game details | D12: 2024-07-31T06:36:10.906Z | E12: Matthew East | F12: <p>Given SFG is running<br />and 200 response returned from endpoint<br />when SFG send get request to NGSS API &lt;endpoint&gt;<br />then data returned is used to populate game details<br /> </p><figure class="table"><table><tbody><tr><td>endpoint</td></tr><tr><td>/leagues/00/seasons?Format=json&amp;limit=0</td></tr><tr><td>/Games/0022301113/officials?Format=json</td></tr><tr><td>/Games/0022301113/rosters?Format=json</td></tr><tr><td>/Games/0022301113?Format=json</td></tr><tr><td>leagues/00/seasons?Format=json&amp;limit=0</td></tr><tr><td>/Games/0022301113/officials?Format=json</td></tr><tr><td>/Games/0022301113/rosters?Format=json</td></tr></tbody></table></figure> | I12: BAS-124 Populate game details from scrubbed API game id | L12: High | M12: Active | S12: Gherkin syntax | T12: 2025-01-22T08:37:39.933Z | U12: Matthew East | V12: No | W12: Yes | X12: High
A13: 7118 | B13: end to end SFG | D13: 2025-01-22T08:38:13.754Z | E13: Matthew East | I13: BAS-122 Setup Scrubbed Feed Generator module | L13: High | M13: Active | S13: Gherkin syntax | T13: 2025-01-22T08:38:29.485Z | U13: Matthew East | V13: No | W13: Yes | X13: High
A14: 2225 | B14: write feed to Azure | D14: 2024-07-31T08:06:28.665Z | E14: Matthew East | F14: <p><strong>Given</strong> SFG is running<br />and put request to start endpoint returned success code<br /><strong>When</strong> data is processed by SFG<br /><strong>Then</strong> feeds are output to Azure<br /><br />feeds.<br />Processed.events.clean<br />Processed.events.complete<br />Processed.pose.clean<br />Processed.pose.ccomplete</p><p><br /> </p> | I14: BAS-127 Output scrubbed feeds to Azure storage | L14: High | M14: Active | S14: Gherkin syntax | T14: 2025-01-22T08:38:46.527Z | U14: Matthew East | V14: No | W14: Yes | X14: High
A15: 2226 | B15: Write feeds to S3 | D15: 2024-07-31T08:34:01.466Z | E15: Matthew East | F15: <p>GIven SFG is running<br />And put request returns success code<br />and SFG has processed feed data<br />Then feeds are output to S3<br /><br />feeds<br /> </p> | I15: BAS-128 Output scrubbed feeds to S3 | L15: High | M15: Active | S15: Gherkin syntax | T15: 2025-01-22T08:39:22.013Z | U15: Matthew East | V15: No | W15: Yes | X15: Normal
A16: 2228 | B16: Get status - queued | D16: 2024-07-31T08:47:18.755Z | E16: Matthew East | F16: <p>Given SFG is running<br />and user has send request to endpoint scrubbed/start<br />When get request sent to endpoint /status<br />Then status "queued" is returned in response </p> | I16: BAS-129 Scrubbed progress metrics | L16: Normal | M16: Active | S16: Gherkin syntax | T16: 2025-01-22T08:40:01.593Z | U16: Matthew East | V16: No | W16: Yes | X16: Normal
A17: 2229 | B17: Get status - in progress | D17: 2024-07-31T09:19:31.874Z | E17: Matthew East | F17: <p>Given SFG is running<br />and scrubbed/batch request has returned status 200 ok<br />when get request is sent to /status endpoint<br />Then status is returned as state "in progress" with timestamp</p> | I17: BAS-129 Scrubbed progress metrics | L17: Normal | M17: Active | S17: Gherkin syntax | T17: 2025-01-22T08:40:16.389Z | U17: Matthew East | V17: No | W17: Yes | X17: Normal
A18: 2231 | B18: get status - finished | D18: 2024-07-31T09:29:46.563Z | E18: Matthew East | F18: <p>Given SFG is running<br />and scrubbed/ batch endpoint has returned code 200<br />and scrubbed/ finish endpoint has returned code 200<br />and all files have have finished processing<br />when get request is sent to endpoint /status<br /><br />Then status is returned state is equal to "finished<br />and started timestamp is true<br />and finished timestamp is true</p> | I18: BAS-129 Scrubbed progress metrics | L18: Normal | M18: Active | S18: Gherkin syntax | T18: 2025-01-22T08:40:35.861Z | U18: Matthew East | V18: No | W18: Yes | X18: Normal
A19: 2230 | B19: scrubbed status - progress 1 | D19: 2024-07-31T09:22:47.309Z | E19: Matthew East | F19: <p>Given SFG is running<br />and scrubbed/ batch endpoint has returned code 200<br />and scrubbed/ finish endpoint has returned code 200<br />and all files have have finished processing<br />when get request is sent to endpoint /status<br />Then progress is returned for &lt;target&gt; &lt;message type&gt; &lt;name&gt; <br />and total should equal attempted <br />and total should equal succeeded<br />and failed should equal 0<br />and skipped should = 0<br /> </p><figure class="table"><table><tbody><tr><td> </td><td>HEI</td><td>NBA</td><td>2S</td><td>Local</td></tr><tr><td>processed.events.complete</td><td>S3</td><td>Azure</td><td> </td><td> </td></tr><tr><td>processed.events.clean</td><td>S3</td><td>Azure</td><td> </td><td> </td></tr><tr><td>processed.pose.complete</td><td>S3</td><td>Azure</td><td>S3</td><td>Disk</td></tr><tr><td>processed.pose.clean</td><td>S3</td><td>Azure</td><td> </td><td>Disk</td></tr></tbody></table></figure> | I19: BAS-129 Scrubbed progress metrics | L19: Normal | M19: Active | S19: Gherkin syntax | T19: 2025-01-22T08:41:06.179Z | U19: Matthew East | V19: Yes | W19: Yes | X19: High
A20: 2240 | B20: silently Ignore frames missing with zero tracking data | D20: 2024-07-31T10:46:54.268Z | E20: Matthew East | F20: <p>Given SFG is running<br />and bson file does not contain &lt;samples&gt;<br />and &lt;gameClock&gt; is equal to false<br />when frame is processed by SFG<br />then error message is no sent to log<br />and counter is incremented by 1<br /><br /> </p><figure class="table"><table><tbody><tr><td> </td><td>Scenario 1</td><td>Scenario 2</td><td>Scenario 3</td><td>Scenario 4</td></tr><tr><td>ballSamples</td><td>Null</td><td>Null</td><td>Null</td><td>Null</td></tr><tr><td>peopleSamples</td><td>Null</td><td>Null</td><td>Null</td><td>Null</td></tr><tr><td>officialsSamples</td><td>Null</td><td>Null</td><td>Null</td><td>Null</td></tr><tr><td>GameClock</td><td>TRUE</td><td>FALSE</td><td>TRUE</td><td>FALSE</td></tr><tr><td>Shotclock</td><td>TRUE</td><td>TRUE</td><td>FALSE</td><td>FALSE</td></tr><tr><td>error message?</td><td>log</td><td>log</td><td>log</td><td>no log</td></tr></tbody></table></figure> | I20: BAS-164 Frames with no tracking data are being reported as errors | L20: Normal | M20: Active | S20: Gherkin syntax | T20: 2025-01-22T08:42:13.693Z | U20: Matthew East | V20: Yes | W20: Yes | X20: High
A21: 2026 | B21: run batch queue game | D21: 2024-07-24T15:39:32.305Z | E21: Matthew East | F21: <p>Given SFG is running<br />and game took place in 48 hour window<br />When put request sent to endpoint scrubbed/stat<br />then status code 200 is returned<br />and game status is queued </p> | I21: BAS-183 Scrubbed chunked uploads | L21: High | M21: Active | S21: Gherkin syntax | T21: 2025-01-22T08:42:44.576Z | U21: Matthew East | V21: Yes | W21: Yes | X21: Normal
A22: 2241 | B22: run batch queue game - bad request | D22: 2024-07-31T12:28:49.496Z | E22: Matthew East | F22: <p>Given SFG is running<br />and game took place in 48 hour window<br />When put request sent to endpoint scrubbed/stat<br />then status code 200 is returned<br />and game status is queued <br /><br /> </p><figure class="table"><table><tbody><tr><td>request permeteres</td><td>included</td><td>valid</td><td>response</td></tr><tr><td>gameID</td><td>FALSE</td><td>N/a</td><td>400</td></tr><tr><td>tracking path</td><td>FALSE</td><td>N/a</td><td>400</td></tr><tr><td>events path</td><td>FALSE</td><td>N/a</td><td>400</td></tr><tr><td>force</td><td>FALSE</td><td>FALSE</td><td>400</td></tr><tr><td>gameID</td><td>TRUE</td><td>FALSE</td><td>400</td></tr><tr><td>tracking path</td><td>TRUE</td><td>FALSE</td><td>400</td></tr><tr><td>events path</td><td>TRUE</td><td>FALSE</td><td>400</td></tr></tbody></table></figure> | I22: BAS-183 Scrubbed chunked uploads | L22: Normal | M22: Active | S22: Gherkin syntax | T22: 2025-01-22T08:43:06.750Z | U22: Matthew East | V22: No | W22: Yes | X22: High
A23: 2242 | B23: run batched upload | D23: 2024-07-31T12:33:12.112Z | E23: Matthew East | F23: <p><strong>Given</strong> SFG is running<br />and game is in queued state<br /><strong>when</strong> put request /batch sent to endpoint<br /><strong>then</strong> status code 200 is returned <br />and all files in directory are processed in SFG<br /><br />request json<br />{</p><p> "gameId": "0022301113", </p><p> "trackingPath": "C:/Users/MatthewEast/work/DataPlatforms/java-backend-automation-pilot/inputData/SFG/BSONS_0022301113_2024-04-050000_HOU_GSW_+500_V11/tracking/1215", </p><p> "trackingEventPath": "C:/Users/MatthewEast/work/DataPlatforms/java-backend-automation-pilot/inputData/SFG/BSONS_0022301113_2024-04-050000_HOU_GSW_+500_V11/events/1215", </p><p> "trackingOffset": "Z"</p><p>}</p> | I23: BAS-183 Scrubbed chunked uploads | L23: High | M23: Active | S23: Gherkin syntax | T23: 2025-01-22T08:43:28.986Z | U23: Matthew East | V23: Yes | W23: Yes | X23: Normal
A24: 2243 | B24: finish batch | D24: 2024-07-31T12:40:45.995Z | E24: Matthew East | I24: BAS-183 Scrubbed chunked uploads | L24: Normal | M24: Active | S24: Case (text)
A25: 2244 | B25: validate order of batch | D25: 2024-07-31T12:42:18.829Z | E25: Matthew East | I25: BAS-183 Scrubbed chunked uploads | L25: High | M25: Active | S25: Gherkin syntax | T25: 2025-01-22T08:43:57.465Z | U25: Matthew East | V25: No | W25: Yes | X25: High
A26: 2245 | B26: Scrubbed chunks - monitoring metrics | D26: 2024-07-31T12:43:33.844Z | E26: Matthew East | I26: BAS-183 Scrubbed chunked uploads | L26: Normal | M26: Active | S26: Gherkin syntax | T26: 2025-01-22T08:44:17.354Z | U26: Matthew East | V26: No | W26: Yes | X26: Normal
A27: 2246 | B27: Notification that scrubbing is complete | D27: 2024-07-31T12:43:45.825Z | E27: Matthew East | I27: BAS-183 Scrubbed chunked uploads | L27: High | M27: Active | S27: Gherkin syntax | T27: 2025-01-22T08:44:43.094Z | U27: Matthew East | V27: No | W27: Yes | X27: Normal
A28: 1900 | B28: BAS-579 Provide a status endpoint for OPs status | D28: 2024-07-08T07:28:42.581Z | E28: Matthew East | F28: <p>Given SFG is running<br />And request body contains accepted json<br />When get request is made to API endpoint &lt;URI&gt; <br />Then correct API status returned</p><p>request json | API status<br />True | 200 <br />Fale | 400<br /> </p> | I28: BAS-579 Provide a status endpoint for OPs | K28: BAS-579 | L28: High | M28: Active | N28: Passed | O28: 2024-07-11T15:49:52.052Z | S28: Gherkin syntax | T28: 2025-01-22T11:06:10.894Z | U28: Matthew East | V28: Yes | W28: Yes | X28: Normal
A29: 1901 | B29: BAS-579 Provide a status endpoint for OPs active outputs | D29: 2024-07-08T08:14:36.864Z | E29: Matthew East | F29: <p>Given SFG is running<br />and &lt;active outputs&gt; are &lt;running&gt;<br />and user sends get request to endpoint uri<br />Then feed details for each active output is returned </p><p>active output | running | Active output<br />processed.pose.clean | True | True<br />processed.pose.complete | True | True<br />Combined.events.clean | True | True<br />Combined.events.complete | True | True<br />processed.pose.clean | False | False<br />processed.pose.complete | False | False<br />Combined.events.clean | False | False<br />Combined.events.complete | False | False</p> | I29: BAS-579 Provide a status endpoint for OPs | K29: BAS-579 | L29: High | M29: Active | N29: Passed | O29: 2024-07-11T15:49:56.204Z | S29: Gherkin syntax | T29: 2025-01-22T08:45:39.547Z | U29: Matthew East | V29: Yes | W29: Yes | X29: Normal
A30: 1902 | B30: BAS-579 Provide a status endpoint for OPs health check status | D30: 2024-07-08T08:44:32.243Z | E30: Matthew East | F30: <p>Given SFG is running<br />and &lt;service&gt; status is &lt;status&gt;<br />When get request is sent to endpoint URI "/scrubbed/env"<br />Then correct health check status is returned<br /><br />service | status | health check status<br />Azure | up | Active<br />S3 | up | Active <br />Azure | down | Inactive<br />S3 | down | Inactive</p> | I30: BAS-579 Provide a status endpoint for OPs | K30: BAS-579 | L30: High | M30: Active | N30: Passed | O30: 2024-07-11T15:50:00.015Z | S30: Gherkin syntax | T30: 2025-01-22T08:46:02.956Z | U30: Matthew East | V30: No | W30: Yes | X30: Normal
A31: 1903 | B31: BAS-579 Provide a status endpoint for OPs arenaID | D31: 2024-07-08T08:44:54.802Z | E31: Matthew East | F31: <p>GIven SFG is running<br />and gameID is set<br />When get request is sent to URI<br />Then the correct arena ID is returned for the game</p> | I31: BAS-579 Provide a status endpoint for OPs | K31: BAS-579 | L31: High | M31: Active | N31: Passed | O31: 2025-01-22T09:17:49.140Z | S31: Gherkin syntax | T31: 2025-01-22T08:46:24.999Z | U31: Matthew East | V31: No | W31: Yes | X31: Normal
A32: 1904 | B32: BAS-515 Simplified config | D32: 2024-07-08T09:30:30.455Z | E32: Matthew East | F32: <p>Given config contains arenaID <br />and config contains encrypted credentials <br />When &lt;service&gt; is started<br />Then service runs without error<br /><br />service<br />LFG<br />SFG</p> | I32: BAS -515 Create new encrypted configurations for SFG & LFG | K32: BAS-515 | L32: High | M32: Active | N32: Passed | O32: 2024-07-15T11:41:00.151Z | S32: Gherkin syntax | T32: 2025-01-22T08:47:00.842Z | U32: Matthew East | V32: Yes | W32: Yes | X32: Low
A33: 1906 | B33: New API endpoint | D33: 2024-07-08T12:05:23.626Z | E33: Matthew East | F33: <p>Given SFG is running<br />When I send post request to endpoint "scrubbed/start/session"<br />Then status code 201 is returned</p> | I33: BAS-606 Scrubbed output for non-game events | K33: BAS-606 | L33: High | M33: Active | N33: Passed | O33: 2024-07-16T14:54:42.975Z | S33: Gherkin syntax | T33: 2025-01-22T08:47:34.977Z | U33: Matthew East | V33: Yes | W33: Yes | X33: Low
A34: 1907 | B34: Run data as single request | D34: 2024-07-08T12:06:21.792Z | E34: Matthew East | F34: <p>Given SFG is running<br />And data is stored in a single directory (not batched)<br />When send post request to SFG<br />Then output process is completed</p> | I34: BAS-606 Scrubbed output for non-game events | K34: BAS-606 | L34: Normal | M34: Active | N34: Passed | O34: 2024-07-16T14:54:47.004Z | S34: Gherkin syntax | T34: 2025-01-22T08:48:12.309Z | U34: Matthew East | V34: Yes | W34: Yes | X34: Normal
A35: 1908 | B35: Json request body | D35: 2024-07-08T12:06:42.781Z | E35: Matthew East | F35: <p>Given SFG is running<br />And request json contains all &lt;mandatory data&gt;<br />When post request is send to endpoint<br />Then &lt;status code&gt; is returned<br /><br />mandatory fields | completed<br />True | 202<br />false | 400 </p> | I35: BAS-606 Scrubbed output for non-game events | K35: BAS-606 | L35: High | M35: Active | N35: Passed | O35: 2024-07-16T14:54:51.207Z | S35: Gherkin syntax | T35: 2025-01-22T08:48:37.830Z | U35: Matthew East | V35: Yes | W35: Yes | X35: Low
A36: 1909 | B36: request ID | D36: 2024-07-08T12:06:52.800Z | E36: Matthew East | I36: BAS-606 Scrubbed output for non-game events | L36: Normal | M36: Active | N36: Passed | O36: 2024-07-16T14:54:55.672Z | S36: Gherkin syntax | T36: 2025-01-22T08:49:42.091Z | U36: Matthew East | V36: Yes | W36: Yes | X36: Normal
A37: 1910 | B37: game active filtering | D37: 2024-07-08T12:07:16.703Z | E37: Matthew East | F37: <p>Given SFG is running<br />and BSON contains game active field &lt;isActive&gt;<br />When data is processed<br />Then json data is produced <br /><br />is Active<br />True<br />False</p> | I37: BAS-606 Scrubbed output for non-game events | K37: BAS-606 | L37: Normal | M37: Active | N37: Passed | O37: 2024-07-16T14:54:59.191Z | S37: Gherkin syntax | T37: 2025-01-22T08:52:11.205Z | U37: Matthew East | V37: Yes | W37: Yes | X37: Normal
A38: 1911 | B38: output data path format | D38: 2024-07-08T12:07:30.440Z | E38: Matthew East | F38: <p>Given BSON data is consumed in SFG<br />When JSON data is output to disc<br />Then JSON data matches is written to path <br /> </p><p>{seasonYear}/{leagueCode}_{leagueName}/{arenaId}_{arenaName}/{sessionName}/{YYYY-MM-DD}/{messageType}</p> | I38: BAS-606 Scrubbed output for non-game events | K38: BAS-606 | L38: Normal | M38: Active | N38: Passed | O38: 2024-07-16T14:55:01.814Z | S38: Gherkin syntax | T38: 2025-01-22T08:52:18.424Z | U38: Matthew East | V38: No | W38: Yes | X38: Low
A39: 1912 | B39: batch data | D39: 2024-07-08T12:07:55.059Z | E39: Matthew East | F39: <p>Given SFG is consuming Bson data<br />When data is output to disk<br />Then data is batched containing 1000 json lines per files</p> | I39: BAS-606 Scrubbed output for non-game events | K39: BAS-606 | L39: Normal | M39: Active | N39: Passed | O39: 2024-07-16T14:55:04.899Z | S39: Gherkin syntax | T39: 2025-01-22T08:52:26.329Z | U39: Matthew East | V39: No | W39: Yes | X39: Normal
A40: 1913 | B40: data accuracy validation | D40: 2024-07-08T13:10:02.110Z | E40: Matthew East | F40: <p>Given bson data is consumed via SFG<br />and API call includes session and player details<br />When json data is compared again source data<br />Then all fields are populated as expected, containing accurate data </p> | I40: BAS-606 Scrubbed output for non-game events | K40: BAS-606 | L40: High | M40: Active | N40: Passed | O40: 2024-07-16T14:55:08.157Z | S40: Gherkin syntax | T40: 2025-01-22T08:52:38.616Z | U40: Matthew East | V40: No | W40: Yes | X40: High
A41: 1916 | B41: Already subscribed message - Info | D41: 2024-07-08T14:42:43.249Z | E41: Matthew East | F41: <p>Given SFG has started <br />When a new quarter starts processing <br />Then message is written out at info level "Already subscribed for game 0042300202" NOT an error</p> | I41: BAS-619 Convert "Already subscribed for game x" error | K41: BAS-619 | L41: High | M41: Active | N41: Passed | O41: 2024-07-10T10:33:53.297Z | S41: Gherkin syntax | T41: 2025-01-22T08:53:05.861Z | U41: Matthew East | V41: No | W41: Yes | X41: Normal
A42: 1917 | B42: Already subscribed for game message | D42: 2024-07-08T14:48:17.056Z | E42: Matthew East | F42: <p>Given SFG has started <br />When a new quarter starts processing <br />Then message is written out at info level "Already subscribed for game xxxx" <br />NOT an error</p> | I42: BAS-619 Convert "Already subscribed for game x" error | K42: BAS-619 | L42: Normal | M42: Active | N42: Passed | O42: 2024-07-15T11:41:26.272Z | S42: Gherkin syntax | T42: 2025-01-22T08:53:15.999Z | U42: Matthew East | V42: No | W42: Yes | X42: Normal
A43: 1918 | B43: Add string prefix to be set on log messages | D43: 2024-07-08T14:51:26.664Z | E43: Matthew East | I43: BAS-592 Easier querying for SFG upload log message | K43: BAS-592 | L43: Low | M43: Active | S43: Gherkin syntax | T43: 2025-01-22T08:53:42.334Z | U43: Matthew East | V43: No | W43: Yes | X43: Low
A44: 1919 | B44: Datadog metric for messages sent | D44: 2024-07-08T14:53:19.813Z | E44: Matthew East | I44: BAS-474 Create new metrics for reporting on number of files sent | K44: BAS-474 | L44: High | M44: Active | N44: Passed | O44: 2024-07-15T11:41:35.359Z | S44: Gherkin syntax | T44: 2025-01-22T08:54:30.808Z | U44: Matthew East | V44: No | W44: Yes | X44: Low
A45: 2264 | B45: metric in datadog for number of messages | D45: 2024-08-02T12:24:03.848Z | E45: Matthew East | F45: <p><strong>Given</strong> SFG is running<br />and files have been processed<br />When dataDog is viewed<br /><strong>Then </strong>metric with number of files send to NBA displays total number of files processed. </p> | I45: BAS-471 Report on number of files sent by SFG to NBA | L45: High | M45: Active | S45: Gherkin syntax | T45: 2025-01-22T08:55:04.419Z | U45: Matthew East | V45: No | W45: Yes | X45: Low
A46: 5327 | B46: Alert NBA when post-match feeds have been uploaded to Azure | D46: 2024-10-21T10:51:10.862Z | E46: Matthew East | I46: BAS-760 Alert NBA when Azure uploads of processed feeds are complete | L46: High | M46: Active | S46: Gherkin syntax | T46: 2025-01-22T08:55:28.154Z | U46: Matthew East | V46: No | W46: Yes | X46: Low
A47: 7114 | B47: Add multiple players to put request | D47: 2025-01-21T10:31:23.713Z | E47: Matthew East | I47: BAS-733 Allow for players to be assigned to home or away teams in SFG without NGSS | K47: BAS-733 | L47: Low | M47: Active | N47: Passed | O47: 2025-02-05T13:59:16.550Z | S47: Gherkin syntax | T47: 2025-02-03T16:58:22.363Z | U47: Matthew East | V47: No | W47: Yes | X47: Normal | Y47: 2.37
A48: 7115 | B48: add player team ID to put request | D48: 2025-01-21T10:31:38.344Z | E48: Matthew East | I48: BAS-733 Allow for players to be assigned to home or away teams in SFG without NGSS | K48: BAS-733 | L48: Low | M48: Active | N48: Passed | O48: 2025-02-05T13:59:20.267Z | S48: Gherkin syntax | T48: 2025-02-03T16:58:27.777Z | U48: Matthew East | V48: No | W48: Yes | X48: Normal | Y48: 2.37
A49: 7116 | B49: Players output to json | D49: 2025-01-21T10:31:50.733Z | E49: Matthew East | I49: BAS-733 Allow for players to be assigned to home or away teams in SFG without NGSS | K49: BAS-733 | L49: Low | M49: Active | N49: Passed | O49: 2025-02-05T13:59:25.369Z | S49: Gherkin syntax | T49: 2025-02-03T16:58:33.398Z | U49: Matthew East | V49: No | W49: Yes | X49: Normal | Y49: 2.37
A50: 7117 | B50: teams output to json | D50: 2025-01-21T10:32:03.722Z | E50: Matthew East | I50: BAS-733 Allow for players to be assigned to home or away teams in SFG without NGSS | K50: BAS-733 | L50: Low | M50: Active | N50: Passed | O50: 2025-02-07T14:12:42.870Z | S50: Gherkin syntax | T50: 2025-02-03T16:58:40.966Z | U50: Matthew East | V50: No | W50: Yes | X50: Normal | Y50: 2.37
A51: 7120 | B51: Pose backfill selectively not applied | D51: 2025-01-22T14:49:39.645Z | E51: Matthew East | I51: BAS-838 Pose backfill selectively not applied | K51: BAS-838 | L51: Normal | M51: Active | N51: Passed | O51: 2025-02-03T10:44:04.923Z | S51: Gherkin syntax | T51: 2025-01-27T15:16:58.092Z | U51: Matthew East | V51: No | W51: Yes | X51: High | Y51: 2.37
A52: 7121 | B52: Reprocessing Manager fails when selecting season | D52: 2025-01-22T14:53:08.987Z | E52: Matthew East | I52: BAS-844 Reprocessing Manager fails when selecting season | K52: BAS-844 | L52: Low | M52: Active | N52: Passed | O52: 2025-01-27T12:36:45.150Z | S52: Gherkin syntax | T52: 2025-01-27T15:17:16.143Z | U52: Matthew East | V52: No | W52: No | X52: Low | Y52: 2.37
A53: 7138 | B53: find the frame time which is closest to the timeUTC | D53: 2025-01-22T15:29:34.593Z | E53: Matthew East | I53: BAS-964 Pose backfill not working for event 660 in game 0022400007 | K53: BAS-964 | L53: Normal | M53: Active | N53: Passed | O53: 2025-02-03T10:44:17.692Z | S53: Gherkin syntax | T53: 2025-01-27T15:17:54.954Z | U53: Matthew East | V53: No | W53: Yes | X53: High | Y53: 2.37
A54: 7131 | B54: launch4J configuration will have a new parameter added to it | D54: 2025-01-22T15:23:33.710Z | E54: Matthew East | I54: BAS-957 SFG need to write a process file on startup for Configurator | K54: BAS-957 | L54: Normal | M54: Active | N54: Passed | O54: 2025-01-28T11:04:31.956Z | S54: Gherkin syntax | T54: 2025-01-27T15:13:43.792Z | U54: Matthew East | V54: No | W54: Yes | X54: Low | Y54: 2.37
A55: 7132 | B55: When SFG is launched it will create a file named ProcessInfo.json in the directory it was launched from | D55: 2025-01-22T15:23:33.710Z | E55: Matthew East | I55: BAS-957 SFG need to write a process file on startup for Configurator | K55: BAS-957 | L55: Normal | M55: Active | N55: Passed | O55: 2025-01-28T11:04:37.507Z | S55: Gherkin syntax | T55: 2025-01-27T15:13:52.628Z | U55: Matthew East | V55: No | W55: Yes | X55: Low | Y55: 2.37
A56: 7133 | B56: f this file exists then SFG should refuse to launch and issue an appropriate error message. | D56: 2025-01-22T15:23:33.710Z | E56: Matthew East | I56: BAS-957 SFG need to write a process file on startup for Configurator | K56: BAS-957 | L56: Normal | M56: Active | N56: Passed | O56: 2025-01-28T14:15:01.379Z | S56: Gherkin syntax | T56: 2025-01-27T15:14:01.882Z | U56: Matthew East | V56: No | W56: Yes | X56: Low | Y56: 2.37
A57: 7134 | B57: ProcessInfo.json | D57: 2025-01-22T15:23:33.710Z | E57: Matthew East | I57: BAS-957 SFG need to write a process file on startup for Configurator | K57: BAS-957 | L57: Normal | M57: Active | N57: Passed | O57: 2025-01-28T12:46:06.928Z | S57: Gherkin syntax | T57: 2025-01-27T15:14:11.025Z | U57: Matthew East | V57: No | W57: Yes | X57: Low | Y57: 2.37
A58: 20376 | B58: LFG PMEG Pose backfill BAD_PASS | D58: 2025-04-01T13:21:49.977Z | E58: Matthew East | I58: BAS-807 Pose backfill turnovers in post game combined events | K58: BAS-807 | L58: High | M58: Active | S58: Gherkin syntax | V58: No | W58: Yes | X58: Normal | Y58: 2.38
A59: 20377 | B59: LFG PMEG Pose backfill LOST_BALL | D59: 2025-04-01T13:21:49.977Z | E59: Matthew East | I59: BAS-807 Pose backfill turnovers in post game combined events | K59: BAS-807 | L59: High | M59: Active | S59: Gherkin syntax | V59: No | W59: Yes | X59: Normal | Y59: 2.38
A60: 20378 | B60: LFG PMEG Pose backfill OUT_OF_BOUNDS | D60: 2025-04-01T13:21:49.977Z | E60: Matthew East | I60: BAS-807 Pose backfill turnovers in post game combined events | K60: BAS-807 | L60: High | M60: Active | S60: Gherkin syntax | V60: No | W60: Yes | X60: Normal | Y60: 2.38
A61: 20379 | B61: match the turnover to a tracking event | D61: 2025-04-01T13:21:49.977Z | E61: Matthew East | I61: BAS-808 Listen for updates on turnovers in live workflow | K61: BAS-808 | L61: Normal | M61: Active | S61: Gherkin syntax | V61: No | W61: Yes | X61: High | Y61: 2.38
A62: 20380 | B62: delete the existing ngss only event | D62: 2025-04-01T13:21:49.977Z | E62: Matthew East | I62: BAS-808 Listen for updates on turnovers in live workflow | K62: BAS-808 | L62: Normal | M62: Active | S62: Gherkin syntax | V62: No | W62: Yes | X62: Normal | Y62: 2.38
A63: 20381 | B63: Last touch details in bson moved | D63: 2025-04-01T13:21:49.977Z | E63: Matthew East | I63: BAS-824 Last touch details in bson moved | L63: High | M63: Active | S63: Gherkin syntax | V63: No | W63: Yes | X63: Normal | Y63: 2.38
A64: 20382 | B64: SFG send final box message | D64: 2025-04-01T13:21:49.977Z | E64: Matthew East | F64: <p>Given: Game has ended<br />When: Stats crew send finalbox message to NGSS<br />Then: service is disconnected from websocket </p> | I64: BAS-836 Change reconnect policy on Websocket when game not active | K64: BAS-836 | L64: Low | M64: Active | S64: Gherkin syntax | T64: 2025-04-17T07:13:36.771Z | U64: Matthew East | V64: No | W64: Yes | X64: Low | Y64: 2.39
A65: 9376 | B65: SFG Pose backfill BAD_PASS | D65: 2025-02-13T10:06:01.611Z | E65: Matthew East | I65: BAS-807 Pose backfill turnovers in post game combined events | K65: BAS-807 | L65: High | M65: Active | N65: Passed | O65: 2025-02-18T12:48:38.586Z | S65: Gherkin syntax | T65: 2025-02-14T08:09:52.843Z | U65: Matthew East | V65: No | W65: Yes | X65: Normal | Y65: 2.38
A66: 9377 | B66: SFG Pose backfill LOST_BALL | D66: 2025-02-13T10:06:23.927Z | E66: Matthew East | I66: BAS-807 Pose backfill turnovers in post game combined events | K66: BAS-807 | L66: High | M66: Active | N66: Passed | O66: 2025-02-18T12:48:42.975Z | S66: Gherkin syntax | T66: 2025-02-14T08:10:02.270Z | U66: Matthew East | V66: No | W66: Yes | X66: Normal | Y66: 2.38
A67: 9378 | B67: SFG Pose backfill OUT_OF_BOUNDS | D67: 2025-02-13T10:08:16.427Z | E67: Matthew East | I67: BAS-807 Pose backfill turnovers in post game combined events | K67: BAS-807 | L67: High | M67: Active | N67: Passed | O67: 2025-02-18T12:48:46.110Z | S67: Gherkin syntax | T67: 2025-02-14T08:10:10.407Z | U67: Matthew East | V67: No | W67: Yes | X67: Normal | Y67: 2.38
A68: 20385 | B68: SFG Pose backfill when NGSS event sent during break in play | D68: 2025-04-01T13:36:59.141Z | E68: Matthew East | F68: <p>Given: Game clock has stopped<br />When: NGSS event is sent after a delay<br />Then: POSE data is back filled to match event<br /> </p> | I68: BAS-1073 PMEG not finding pose backfill when event is recorded during long break in play | K68: BAS-1073 | L68: Normal | M68: Active | N68: Passed | O68: 2025-04-16T14:02:18.185Z | S68: Gherkin syntax | T68: 2025-04-01T13:38:17.726Z | U68: Matthew East | V68: No | W68: No | X68: High | Y68: 2.39
A69: 21429 | B69: Ngss messages saved to S3 | D69: 2025-04-08T13:54:24.601Z | E69: Matthew East | F69: <p>Given: SFG is running<br />When: raw-admin finalbox ngss event message is received<br />Then: NGSS events are saved to S3</p> | I69: BAS-1070 Fix saving live ngss websocket messages | K69: BAS-1070 | L69: Low | M69: Active | N69: Passed | O69: 2025-04-16T14:02:23.817Z | S69: Gherkin syntax | T69: 2025-04-08T13:56:13.284Z | U69: Matthew East | V69: No | W69: No | X69: Normal | Y69: 2.39
A70: 5325 | B70: Initial events that exist in multiple other refined events and have the same type, player and timestamp also have the same UUID | D70: 2024-10-21T10:47:28.474Z | E70: Matthew East | I70: BAS-727 Modify how we handle duplicated events | L70: High | M70: Active | S70: Gherkin syntax | T70: 2025-01-20T15:45:20.466Z | U70: Matthew East | V70: No | W70: Yes | X70: High
A71: 5326 | B71: There aren’t any standalone event messages which have the same type, player and timestamp | D71: 2024-10-21T10:47:45.857Z | E71: Matthew East | I71: BAS-727 Modify how we handle duplicated events | L71: High | M71: Active | S71: Gherkin syntax | T71: 2025-01-20T15:45:57.005Z | U71: Matthew East | V71: No | W71: Yes | X71: Normal
A72: 5276 | B72: BAS-748 Not parsing Throw-OutOfBounds events properly | D72: 2024-10-16T11:06:26.926Z | E72: Matthew East | I72: BAS-666 Combined Events Completeness | K72: BAS-748 | L72: Normal | M72: Active | N72: Passed | O72: 2025-01-21T10:22:14.031Z | S72: Case (text) | T72: 2024-10-16T11:13:54.224Z | U72: Matthew East
A73: 5278 | B73: Pull together meeting to discuss options | D73: 2024-10-16T11:10:09.091Z | E73: Matthew East | I73: BAS-675 Understand where to pull pose data from for backfilling | K73: BAS-675 | L73: Low | M73: Active | N73: Passed | O73: 2025-01-22T09:16:49.969Z | R73: bas-675 | S73: Gherkin syntax | T73: 2025-01-20T15:46:33.654Z | U73: Matthew East | V73: Yes | W73: Yes | X73: High
A74: 5279 | B74: Investigate the best way to search for the right data | D74: 2024-10-16T11:10:14.660Z | E74: Matthew East | I74: BAS-675 Understand where to pull pose data from for backfilling | K74: BAS-675 | L74: High | M74: Active | N74: Passed | O74: 2025-01-22T09:16:53.639Z | S74: Gherkin syntax | T74: 2025-01-22T15:39:04.700Z | U74: Matthew East | V74: No | W74: Yes | X74: High
A75: 5280 | B75: Decision on how to index pose data | D75: 2024-10-16T11:10:19.949Z | E75: Matthew East | I75: BAS-675 Understand where to pull pose data from for backfilling | K75: BAS-675 | L75: Normal | M75: Active | N75: Passed | O75: 2025-01-22T09:16:56.909Z | S75: Case (text) | T75: 2024-10-16T11:12:31.368Z | U75: Matthew East
A76: 5281 | B76: Implement what has been decided above | D76: 2024-10-16T11:10:24.791Z | E76: Matthew East | I76: BAS-675 Understand where to pull pose data from for backfilling | K76: BAS-675 | L76: Normal | M76: Active | N76: Passed | O76: 2025-01-22T09:17:00.370Z | S76: Case (text) | T76: 2024-10-16T11:12:41.535Z | U76: Matthew East
A77: 5282 | B77: create a new event in the Combined Events feeds (both live and post match) | D77: 2024-10-16T11:15:33.895Z | E77: Matthew East | I77: BAS-719 parse jumpBall events to find players involved | K77: BAS-719 | L77: Normal | M77: Active | N77: Passed | O77: 2025-01-22T09:17:05.457Z | S77: Gherkin syntax | T77: 2025-01-20T15:46:59.195Z | U77: Matthew East | V77: No | W77: Yes | X77: Low
A78: 5283 | B78: A player is related to this new event, with their pose data listed in the events[0].people section | D78: 2024-10-16T11:16:03.722Z | E78: Matthew East | I78: BAS-719 parse jumpBall events to find players involved | K78: BAS-719 | L78: Normal | M78: Active | N78: Passed | O78: 2025-01-22T09:17:09.198Z | S78: Case (text) | T78: 2024-10-16T11:16:15.427Z | U78: Matthew East
A79: 5284 | B79: events[0].officials should not exist | D79: 2024-10-16T11:16:41.926Z | E79: Matthew East | I79: BAS-719 parse jumpBall events to find players involved | K79: BAS-719 | L79: Normal | M79: Active | N79: Passed | O79: 2025-01-22T09:17:12.658Z | S79: Case (text) | T79: 2024-10-16T11:16:55.492Z | U79: Matthew East
A80: 5285 | B80: improve the quality of the pose backfilling | D80: 2024-10-16T11:17:56.362Z | E80: Matthew East | I80: BAS-680 Improve pose backfilling model | K80: BAS-680 | L80: Normal | M80: Active | N80: Passed | O80: 2025-01-22T09:17:17.628Z | S80: Case (text) | T80: 2024-10-16T11:18:10.064Z | U80: Matthew East
A81: 2266 | B81: BAS-561 Add nearest frame number to events | D81: 2024-08-05T08:52:48.088Z | E81: Matthew East | F81: <p>Given LFG is running<br />When an &lt;event&gt; is generated<br />Then nearestFrameTIme filed is populated with UTC time from pose feed in summary<br />and nearestFrameNumber is populated from pose feed in summary</p> | I81: BAS-628 Summer 2024 feed changes | K81: BAS-561 | L81: Normal | M81: Active | N81: Passed | O81: 2025-01-21T10:22:19.965Z | S81: Gherkin syntax | T81: 2024-08-05T09:00:20.987Z | U81: Matthew East
A82: 2268 | B82: BAS-631 Include CloseInBounds into the Officiating Events feed | D82: 2024-08-05T08:54:04.832Z | E82: Matthew East | I82: BAS-628 Summer 2024 feed changes | L82: Normal | M82: Active | N82: Passed | O82: 2025-01-21T10:22:23.334Z | S82: Case (text)
A83: 2270 | B83: create new message in the Live Events queue - LFG message not set | D83: 2024-08-05T10:03:40.183Z | E83: Matthew East | F83: <p>Given LFG is running<br />and game is about to end<br />and game status is &lt;active&gt;<br />When operator sends request to API<br />Then status code 400 is returned<br />and last frame not set <br /><br /> </p> | I83: BAS-614 Include game over message in Live Events feed | K83: BAS-614 | L83: Normal | M83: Active | N83: Passed | O83: 2025-01-22T09:17:26.043Z | S83: Gherkin syntax
A84: 2267 | B84: create new message in the Live Events queue - LFG message set | D84: 2024-08-05T08:53:43.814Z | E84: Matthew East | F84: <p>Given LFG is running<br />and game is about to end<br />and game status is &lt;finished&gt;<br />When operator sends request to API<br />Then status code 200 is returned<br />and last frame set <br /><br />Given LFG is running<br />and game is about to end<br />and game status is &lt;active&gt;<br />and force "true" <br />When operator sends request to API<br />Then status code 200 is returned<br />and last frame is set <br /><br /> </p> | I84: BAS-614 Include game over message in Live Events feed | K84: BAS-614 | L84: Normal | M84: Active | N84: Passed | O84: 2025-01-22T09:17:29.509Z | S84: Gherkin syntax | T84: 2024-08-05T10:04:45.864Z | U84: Matthew East
A85: 5328 | B85: dd a new field in the live combined events feed | D85: 2024-10-21T10:52:06.265Z | E85: Matthew East | I85: BAS-709 Add message counter to live combined events feed | L85: Normal | M85: Active | S85: Case (text)
A86: 1905 | B86: BAS-489 set last frame | D86: 2024-07-08T09:57:26.278Z | E86: Matthew East | F86: <p>Given LFG is running<br />and game status is &lt;game status&gt;<br />and time end actual filed value is &lt;Time end actual &gt;<br />When user sends request to API<br />Then lastframe filed is &lt;set&gt;<br /><br />game status | time end actual | set<br /> finished | true | True<br /> finished | NUL L | True<br /> active | true | True<br />active | NULL | False</p> | I86: BAS-489 update logic to use gameActive status for TrackingStopped API | K86: BAS-489 | L86: Normal | M86: Active | N86: Passed | O86: 2024-07-16T14:55:28.737Z | S86: Gherkin syntax | T86: 2024-07-08T10:05:34.958Z | U86: Matthew East
A87: 1124 | B87: match NGSS events entered after timeActual by adding a 2 second window | D87: 2024-04-29T06:59:52.014Z | E87: Matthew East | I87: BAS-552 Combined events - Match NGSS events ahead | K87: BAS-552 | L87: High | M87: Active | S87: Gherkin syntax | T87: 2025-01-21T09:03:45.279Z | U87: Matthew East | V87: Yes | W87: Yes | X87: High
A88: 1125 | B88: Add contestingPlayer into feed model | D88: 2024-04-29T07:08:30.683Z | E88: Matthew East | I88: BAS-559 Use the new "ContestingPlayer" player role provided by tracking to backfill touches for blocks, steals and rebounds | K88: BAS-559 | L88: Normal | M88: Active | S88: Case (text) | T88: 2024-04-29T07:14:10.049Z | U88: Matthew East
A89: 1126 | B89: Pass on the player contesting information within the live events feed | D89: 2024-04-29T07:08:39.103Z | E89: Matthew East | I89: BAS-559 Use the new "ContestingPlayer" player role provided by tracking to backfill touches for blocks, steals and rebounds | K89: BAS-559 | L89: Normal | M89: Active | S89: Case (text) | T89: 2024-04-29T07:14:18.586Z | U89: Matthew East
A90: 1127 | B90: record will exist as an extra player in the events[0].eventDetails[n].people[n] array where the roleInEvent will be “contestingPlayer” | D90: 2024-04-29T07:09:12.097Z | E90: Matthew East | I90: BAS-559 Use the new "ContestingPlayer" player role provided by tracking to backfill touches for blocks, steals and rebounds | K90: BAS-559 | L90: Normal | M90: Active | S90: Case (text) | T90: 2024-04-29T07:14:26.732Z | U90: Matthew East
A91: 1128 | B91: Match to NGSS block, steal or rebound that we cannot match to Hawkeye data through the touch events | D91: 2024-04-29T07:10:17.098Z | E91: Matthew East | I91: BAS-559 Use the new "ContestingPlayer" player role provided by tracking to backfill touches for blocks, steals and rebounds | K91: BAS-559 | L91: Normal | M91: Active | S91: Case (text) | T91: 2024-04-29T07:14:35.271Z | U91: Matthew East
A92: 1129 | B92: only match within time window | D92: 2024-04-29T07:10:38.158Z | E92: Matthew East | I92: BAS-559 Use the new "ContestingPlayer" player role provided by tracking to backfill touches for blocks, steals and rebounds | K92: BAS-559 | L92: Normal | M92: Active | S92: Case (text) | T92: 2024-04-29T07:14:49.951Z | U92: Matthew East
A93: 1130 | B93: Match the NGSS data with that event | D93: 2024-04-29T07:10:47.443Z | E93: Matthew East | I93: BAS-559 Use the new "ContestingPlayer" player role provided by tracking to backfill touches for blocks, steals and rebounds | K93: BAS-559 | L93: Normal | M93: Active | S93: Case (text) | T93: 2024-04-29T07:14:57.357Z | U93: Matthew East
A94: 1131 | B94: Use the tracking data from the contesting player in the combined events feed | D94: 2024-04-29T07:10:57.043Z | E94: Matthew East | I94: BAS-559 Use the new "ContestingPlayer" player role provided by tracking to backfill touches for blocks, steals and rebounds | K94: BAS-559 | L94: Normal | M94: Active | S94: Case (text) | T94: 2024-04-29T07:15:09.672Z | U94: Matthew East
A95: 1132 | B95: Include their roleInEvent as contestingPlayer | D95: 2024-04-29T07:11:11.378Z | E95: Matthew East | I95: BAS-559 Use the new "ContestingPlayer" player role provided by tracking to backfill touches for blocks, steals and rebounds | K95: BAS-559 | L95: Normal | M95: Active | S95: Case (text) | T95: 2024-04-29T07:15:19.172Z | U95: Matthew East
A96: 1123 | B96: Live & deplayed feed batch every 1000 files before sending to S3 | D96: 2024-04-29T06:54:56.377Z | E96: Matthew East | I96: BAS-538 Batched delivery for live & delayed feeds | K96: BAS-538 | L96: Normal | M96: Active | S96: Case (text) | T96: 2024-04-29T06:55:09.862Z | U96: Matthew East
A97: 1111 | B97: The centre of each basket from a single frame at tip-off is applied into all feeds for the remainder of the entire game | D97: 2024-04-29T06:45:36.876Z | E97: Matthew East | I97: BAS-523 Add Centre of Basket co-ordinates to pose, fast & event feed | K97: BAS-523 | L97: Normal | M97: Active | S97: Case (text) | T97: 2024-04-29T06:49:15.864Z | U97: Matthew East
A98: 1112 | B98: The value for each basket is taken from the first frame we get through from Tracking where gameActive is true | D98: 2024-04-29T06:45:46.016Z | E98: Matthew East | I98: BAS-523 Add Centre of Basket co-ordinates to pose, fast & event feed | K98: BAS-523 | L98: Normal | M98: Active | S98: Case (text) | T98: 2024-04-29T06:49:28.919Z | U98: Matthew East
A99: 1113 | B99: The value for each basket is stored and made available in all feeds - including events, even though this information is not sent from Tracking in Event BSONs | D99: 2024-04-29T06:46:00.638Z | E99: Matthew East | I99: BAS-523 Add Centre of Basket co-ordinates to pose, fast & event feed | K99: BAS-523 | L99: Normal | M99: Active | S99: Case (text) | T99: 2024-04-29T06:49:37.894Z | U99: Matthew East
A100: 1114 | B100: Add a new basketInformation array into the details object according to the code snippet below to expose this data to customers via our feeds | D100: 2024-04-29T06:46:24.833Z | E100: Matthew East | I100: BAS-523 Add Centre of Basket co-ordinates to pose, fast & event feed | L100: Normal | M100: Active | S100: Case (text)
...

Sheet Sheet11
A1: Issue Type | B1: Key | C1: Summary | D1: Priority | E1: Status | F1: Created | G1: Linked Issues | H1: Project | I1: Sport | J1: Squad | K1: Components | L1: Test event date | M1: customfield_10436 | N1: Linked issues | O1: Links | P1: Status Category Changed
A2: New Feature | B2: =HYPERLINK("https://hawk-eye.atlassian.net/browse/HWKREPORT-3385?atlOrigin=eyJpIjoiYzgwYTQ0ZjEyNzQzNGJhN2JmNjEyZTM0NmRhZWZhNjIiLCJwIjoic2hlZXRzLWppcmEifQ","HWKREPORT-3385") -> HWKREPORT-3385 | C2: NHL Tracking | Classification Metrics In Tracking Control | D2: P4 - Low | E2: Open | F2: 45749.576 | G2: =HYPERLINK("https://hawk-eye.atlassian.net/browse/?atlOrigin=eyJpIjoiYzgwYTQ0ZjEyNzQzNGJhN2JmNjEyZTM0NmRhZWZhNjIiLCJwIjoic2hlZXRzLWppcmEifQ","") | H2: Hawk Report | I2: Ice Hockey | K2: TrackingControlUI | M2: [no field found] | P2: 45749.576
A3: New Feature | B3: =HYPERLINK("https://hawk-eye.atlassian.net/browse/HWKREPORT-3386?atlOrigin=eyJpIjoiYzgwYTQ0ZjEyNzQzNGJhN2JmNjEyZTM0NmRhZWZhNjIiLCJwIjoic2hlZXRzLWppcmEifQ","HWKREPORT-3386") -> HWKREPORT-3386 | C3: NHL Tracking | Ability to Sort Lineups by Jersey Numbers Instead of Alphanumerically | D3: P4 - Low | E3: Open | F3: 45749.577 | G3: =HYPERLINK("https://hawk-eye.atlassian.net/browse/?atlOrigin=eyJpIjoiYzgwYTQ0ZjEyNzQzNGJhN2JmNjEyZTM0NmRhZWZhNjIiLCJwIjoic2hlZXRzLWppcmEifQ","") | H3: Hawk Report | I3: Ice Hockey | K3: TrackingControlUI | M3: [no field found] | P3: 45749.577
A4: New Feature | B4: =HYPERLINK("https://hawk-eye.atlassian.net/browse/HWKREPORT-3387?atlOrigin=eyJpIjoiYzgwYTQ0ZjEyNzQzNGJhN2JmNjEyZTM0NmRhZWZhNjIiLCJwIjoic2hlZXRzLWppcmEifQ","HWKREPORT-3387") -> HWKREPORT-3387 | C4: NHL Tracking | Add DebugViewer to Appstream | D4: P3 - Medium | E4: Done | F4: 45749.579 | G4: =HYPERLINK("https://hawk-eye.atlassian.net/browse/?atlOrigin=eyJpIjoiYzgwYTQ0ZjEyNzQzNGJhN2JmNjEyZTM0NmRhZWZhNjIiLCJwIjoic2hlZXRzLWppcmEifQ","") | H4: Hawk Report | I4: Ice Hockey | K4: TrackingControlUI | M4: [no field found] | P4: 45749.841
A5: New Feature | B5: =HYPERLINK("https://hawk-eye.atlassian.net/browse/HWKREPORT-3388?atlOrigin=eyJpIjoiYzgwYTQ0ZjEyNzQzNGJhN2JmNjEyZTM0NmRhZWZhNjIiLCJwIjoic2hlZXRzLWppcmEifQ","HWKREPORT-3388") -> HWKREPORT-3388 | C5: NHL Tracking | Ability to Take Classification References From Top Down View in TrackingControl | D5: P4 - Low | E5: Open | F5: 45749.584 | G5: =HYPERLINK("https://hawk-eye.atlassian.net/browse/?atlOrigin=eyJpIjoiYzgwYTQ0ZjEyNzQzNGJhN2JmNjEyZTM0NmRhZWZhNjIiLCJwIjoic2hlZXRzLWppcmEifQ","") | H5: Hawk Report | I5: Ice Hockey | K5: TrackingControlUI | M5: [no field found] | P5: 45749.584
A6: New Feature | B6: =HYPERLINK("https://hawk-eye.atlassian.net/browse/HWKREPORT-3389?atlOrigin=eyJpIjoiYzgwYTQ0ZjEyNzQzNGJhN2JmNjEyZTM0NmRhZWZhNjIiLCJwIjoic2hlZXRzLWppcmEifQ","HWKREPORT-3389") -> HWKREPORT-3389 | C6: NHL Tracking | When Switching Tabs in TrackingControl, Feeds Should Remain At Live Rather than Paused | D6: P4 - Low | E6: Open | F6: 45749.587 | G6: =HYPERLINK("https://hawk-eye.atlassian.net/browse/?atlOrigin=eyJpIjoiYzgwYTQ0ZjEyNzQzNGJhN2JmNjEyZTM0NmRhZWZhNjIiLCJwIjoic2hlZXRzLWppcmEifQ","") | H6: Hawk Report | I6: Ice Hockey | K6: TrackingControlUI | M6: [no field found] | P6: 45749.587
A7: New Feature | B7: =HYPERLINK("https://hawk-eye.atlassian.net/browse/HWKREPORT-3390?atlOrigin=eyJpIjoiYzgwYTQ0ZjEyNzQzNGJhN2JmNjEyZTM0NmRhZWZhNjIiLCJwIjoic2hlZXRzLWppcmEifQ","HWKREPORT-3390") -> HWKREPORT-3390 | C7: NHL Tracking | Ability to Pop Out Game Tabs in Appstream | D7: P3 - Medium | E7: Open | F7: 45749.591 | G7: =HYPERLINK("https://hawk-eye.atlassian.net/browse/?atlOrigin=eyJpIjoiYzgwYTQ0ZjEyNzQzNGJhN2JmNjEyZTM0NmRhZWZhNjIiLCJwIjoic2hlZXRzLWppcmEifQ","") | H7: Hawk Report | I7: Ice Hockey | K7: TrackingControlUI | M7: [no field found] | P7: 45749.591
A8: New Feature | B8: =HYPERLINK("https://hawk-eye.atlassian.net/browse/HWKREPORT-3391?atlOrigin=eyJpIjoiYzgwYTQ0ZjEyNzQzNGJhN2JmNjEyZTM0NmRhZWZhNjIiLCJwIjoic2hlZXRzLWppcmEifQ","HWKREPORT-3391") -> HWKREPORT-3391 | C8: NHL Tracking | Viewing/Reading Data - JSON File from Stored DynamoDB tables | D8: P3 - Medium | E8: Open | F8: 45749.594 | G8: =HYPERLINK("https://hawk-eye.atlassian.net/browse/?atlOrigin=eyJpIjoiYzgwYTQ0ZjEyNzQzNGJhN2JmNjEyZTM0NmRhZWZhNjIiLCJwIjoic2hlZXRzLWppcmEifQ","") | H8: Hawk Report | I8: Ice Hockey | K8: TrackingControlUI | M8: [no field found] | P8: 45749.594
A9: Bug | B9: =HYPERLINK("https://hawk-eye.atlassian.net/browse/HWKREPORT-3392?atlOrigin=eyJpIjoiYzgwYTQ0ZjEyNzQzNGJhN2JmNjEyZTM0NmRhZWZhNjIiLCJwIjoic2hlZXRzLWppcmEifQ","HWKREPORT-3392") -> HWKREPORT-3392 | C9: NHL Tracking | Calibration Models not Populating - Potential Triton Issue Resulting in Need to Respin Orbitals | D9: P2 - High | E9: Done | F9: 45749.602 | G9: =HYPERLINK("https://hawk-eye.atlassian.net/browse/?atlOrigin=eyJpIjoiYzgwYTQ0ZjEyNzQzNGJhN2JmNjEyZTM0NmRhZWZhNjIiLCJwIjoic2hlZXRzLWppcmEifQ","") | H9: Hawk Report | I9: Ice Hockey | K9: TrackingControlUI | M9: [no field found] | P9: 45749.839
A10: Bug | B10: =HYPERLINK("https://hawk-eye.atlassian.net/browse/HWKREPORT-3393?atlOrigin=eyJpIjoiYzgwYTQ0ZjEyNzQzNGJhN2JmNjEyZTM0NmRhZWZhNjIiLCJwIjoic2hlZXRzLWppcmEifQ","HWKREPORT-3393") -> HWKREPORT-3393 | C10: NHL Tracking | Stick Data Not Appearing in Multiple Frames | D10: P1 - Highest | E10: Done | F10: 45749.607 | G10: =HYPERLINK("https://hawk-eye.atlassian.net/browse/HWKREPORT-3342?atlOrigin=eyJpIjoiYzgwYTQ0ZjEyNzQzNGJhN2JmNjEyZTM0NmRhZWZhNjIiLCJwIjoic2hlZXRzLWppcmEifQ","HWKREPORT-3342") -> HWKREPORT-3342 | H10: Hawk Report | I10: Ice Hockey | K10: TrackingControlUI | M10: [no field found] | P10: 45778.49
A11: Bug | B11: =HYPERLINK("https://hawk-eye.atlassian.net/browse/HWKREPORT-3394?atlOrigin=eyJpIjoiYzgwYTQ0ZjEyNzQzNGJhN2JmNjEyZTM0NmRhZWZhNjIiLCJwIjoic2hlZXRzLWppcmEifQ","HWKREPORT-3394") -> HWKREPORT-3394 | C11: NHL Tracking | Multiple Players with Missing Jersey Numbers | D11: P2 - High | E11: Open | F11: 45749.611 | G11: =HYPERLINK("https://hawk-eye.atlassian.net/issues/?atlOrigin=eyJpIjoiYzgwYTQ0ZjEyNzQzNGJhN2JmNjEyZTM0NmRhZWZhNjIiLCJwIjoic2hlZXRzLWppcmEifQ&jql=key+in+%28RTT-10035%2CRTT-9468%2CRTT-10034%29","RTT-10035;RTT-9468;RTT-10034") -> RTT-10035;RTT-9468;RTT-10034 | H11: Hawk Report | I11: Ice Hockey | K11: TrackingControlUI | M11: [no field found] | P11: 45749.611
A12: Bug | B12: =HYPERLINK("https://hawk-eye.atlassian.net/browse/HWKREPORT-3395?atlOrigin=eyJpIjoiYzgwYTQ0ZjEyNzQzNGJhN2JmNjEyZTM0NmRhZWZhNjIiLCJwIjoic2hlZXRzLWppcmEifQ","HWKREPORT-3395") -> HWKREPORT-3395 | C12: Issues with inferred bat data | D12: P3 - Medium | E12: Open | F12: 45749.718 | G12: =HYPERLINK("https://hawk-eye.atlassian.net/browse/?atlOrigin=eyJpIjoiYzgwYTQ0ZjEyNzQzNGJhN2JmNjEyZTM0NmRhZWZhNjIiLCJwIjoic2hlZXRzLWppcmEifQ","") | H12: Hawk Report | I12: Baseball | K12: MulticamAnalysis | M12: [no field found] | P12: 45749.718
A13: Bug | B13: =HYPERLINK("https://hawk-eye.atlassian.net/browse/HWKREPORT-3396?atlOrigin=eyJpIjoiYzgwYTQ0ZjEyNzQzNGJhN2JmNjEyZTM0NmRhZWZhNjIiLCJwIjoic2hlZXRzLWppcmEifQ","HWKREPORT-3396") -> HWKREPORT-3396 | C13: 2 BMCC Crashes in Same System (Not PP Queue Related) | D13: P1 - Highest | E13: Work in progress | F13: 45750.143 | G13: =HYPERLINK("https://hawk-eye.atlassian.net/browse/RTT-10318?atlOrigin=eyJpIjoiYzgwYTQ0ZjEyNzQzNGJhN2JmNjEyZTM0NmRhZWZhNjIiLCJwIjoic2hlZXRzLWppcmEifQ","RTT-10318") -> RTT-10318 | H13: Hawk Report | I13: Baseball | K13: MulticamAnalysis | M13: [no field found] | P13: 45762.406
A14: Bug | B14: =HYPERLINK("https://hawk-eye.atlassian.net/browse/HWKREPORT-3397?atlOrigin=eyJpIjoiYzgwYTQ0ZjEyNzQzNGJhN2JmNjEyZTM0NmRhZWZhNjIiLCJwIjoic2hlZXRzLWppcmEifQ","HWKREPORT-3397") -> HWKREPORT-3397 | C14: Unable to Archive Cvids through RemoteFS network Pathway | D14: P2 - High | E14: Open | F14: 45750.159 | G14: =HYPERLINK("https://hawk-eye.atlassian.net/browse/?atlOrigin=eyJpIjoiYzgwYTQ0ZjEyNzQzNGJhN2JmNjEyZTM0NmRhZWZhNjIiLCJwIjoic2hlZXRzLWppcmEifQ","") | H14: Hawk Report | I14: Aussie Rules Football;Football;Horse Racing;Rugby | K14: DokanSetup or RemoteFIle System;SMARTArchiver;SMARTViewer | M14: [no field found] | P14: 45750.159
A15: Bug | B15: =HYPERLINK("https://hawk-eye.atlassian.net/browse/HWKREPORT-3398?atlOrigin=eyJpIjoiYzgwYTQ0ZjEyNzQzNGJhN2JmNjEyZTM0NmRhZWZhNjIiLCJwIjoic2hlZXRzLWppcmEifQ","HWKREPORT-3398") -> HWKREPORT-3398 | C15: Unable to pull cvid data through RemoteFS to Slave Replay Out & FPS is limited in Slave Replay Viewer when pulling cvid data through RemoteFS | D15: P2 - High | E15: Open | F15: 45750.413 | G15: =HYPERLINK("https://hawk-eye.atlassian.net/browse/?atlOrigin=eyJpIjoiYzgwYTQ0ZjEyNzQzNGJhN2JmNjEyZTM0NmRhZWZhNjIiLCJwIjoic2hlZXRzLWppcmEifQ","") | H15: Hawk Report | I15: Aussie Rules Football;Football;Rugby | K15: Slave Replay Output | M15: [no field found] | P15: 45750.413
A16: New Feature | B16: =HYPERLINK("https://hawk-eye.atlassian.net/browse/HWKREPORT-3399?atlOrigin=eyJpIjoiYzgwYTQ0ZjEyNzQzNGJhN2JmNjEyZTM0NmRhZWZhNjIiLCJwIjoic2hlZXRzLWppcmEifQ","HWKREPORT-3399") -> HWKREPORT-3399 | C16: PSL Format needs to be created | D16: P5 - Lowest | E16: Done | F16: 45751.628 | G16: =HYPERLINK("https://hawk-eye.atlassian.net/browse/CTK-197?atlOrigin=eyJpIjoiYzgwYTQ0ZjEyNzQzNGJhN2JmNjEyZTM0NmRhZWZhNjIiLCJwIjoic2hlZXRzLWppcmEifQ","CTK-197") -> CTK-197 | H16: Hawk Report | I16: Cricket | K16: CricketTimeKeeper | M16: [no field found] | P16: 45762.436
A17: New Feature | B17: =HYPERLINK("https://hawk-eye.atlassian.net/browse/HWKREPORT-3400?atlOrigin=eyJpIjoiYzgwYTQ0ZjEyNzQzNGJhN2JmNjEyZTM0NmRhZWZhNjIiLCJwIjoic2hlZXRzLWppcmEifQ","HWKREPORT-3400") -> HWKREPORT-3400 | C17: AOT - Tracked player off pitch contributing to 10/11 attckers in offside incident | D17: P5 - Lowest | E17: Open | F17: 45751.765 | G17: =HYPERLINK("https://hawk-eye.atlassian.net/browse/RTT-10537?atlOrigin=eyJpIjoiYzgwYTQ0ZjEyNzQzNGJhN2JmNjEyZTM0NmRhZWZhNjIiLCJwIjoic2hlZXRzLWppcmEifQ","RTT-10537") -> RTT-10537 | H17: Hawk Report | I17: Football | K17: MulticamAnalysis | M17: [no field found] | P17: 45751.765
A18: Bug | B18: =HYPERLINK("https://hawk-eye.atlassian.net/browse/HWKREPORT-3401?atlOrigin=eyJpIjoiYzgwYTQ0ZjEyNzQzNGJhN2JmNjEyZTM0NmRhZWZhNjIiLCJwIjoic2hlZXRzLWppcmEifQ","HWKREPORT-3401") -> HWKREPORT-3401 | C18: Error processing scorecard status with SMT data | D18: P3 - Medium | E18: Open | F18: 45753.635 | G18: =HYPERLINK("https://hawk-eye.atlassian.net/browse/GDS-431?atlOrigin=eyJpIjoiYzgwYTQ0ZjEyNzQzNGJhN2JmNjEyZTM0NmRhZWZhNjIiLCJwIjoic2hlZXRzLWppcmEifQ","GDS-431") -> GDS-431 | H18: Hawk Report | I18: Broadcast Systems;Golf | K18: GolfDataServer | M18: [no field found] | P18: 45753.636
A19: Bug | B19: =HYPERLINK("https://hawk-eye.atlassian.net/browse/HWKREPORT-3402?atlOrigin=eyJpIjoiYzgwYTQ0ZjEyNzQzNGJhN2JmNjEyZTM0NmRhZWZhNjIiLCJwIjoic2hlZXRzLWppcmEifQ","HWKREPORT-3402") -> HWKREPORT-3402 | C19: GDS Requests for AWS Images | D19: P5 - Lowest | E19: Open | F19: 45753.65 | G19: =HYPERLINK("https://hawk-eye.atlassian.net/browse/GDS-432?atlOrigin=eyJpIjoiYzgwYTQ0ZjEyNzQzNGJhN2JmNjEyZTM0NmRhZWZhNjIiLCJwIjoic2hlZXRzLWppcmEifQ","GDS-432") -> GDS-432 | H19: Hawk Report | I19: Broadcast Systems;Golf | K19: GolfDataServer | M19: [no field found] | P19: 45753.65
A20: Bug | B20: =HYPERLINK("https://hawk-eye.atlassian.net/browse/HWKREPORT-3403?atlOrigin=eyJpIjoiYzgwYTQ0ZjEyNzQzNGJhN2JmNjEyZTM0NmRhZWZhNjIiLCJwIjoic2hlZXRzLWppcmEifQ","HWKREPORT-3403") -> HWKREPORT-3403 | C20: BMCA crash | D20: P1 - Highest | E20: On Hold | F20: 45754.581 | G20: =HYPERLINK("https://hawk-eye.atlassian.net/browse/RTT-10332?atlOrigin=eyJpIjoiYzgwYTQ0ZjEyNzQzNGJhN2JmNjEyZTM0NmRhZWZhNjIiLCJwIjoic2hlZXRzLWppcmEifQ","RTT-10332") -> RTT-10332 | H20: Hawk Report | I20: Baseball | K20: MulticamAnalysis | M20: [no field found] | P20: 45770.653
A21: Bug | B21: =HYPERLINK("https://hawk-eye.atlassian.net/browse/HWKREPORT-3404?atlOrigin=eyJpIjoiYzgwYTQ0ZjEyNzQzNGJhN2JmNjEyZTM0NmRhZWZhNjIiLCJwIjoic2hlZXRzLWppcmEifQ","HWKREPORT-3404") -> HWKREPORT-3404 | C21: BPP crash on the same server as control, seems to also crash MCC | D21: P1 - Highest | E21: Open | F21: 45754.585 | G21: =HYPERLINK("https://hawk-eye.atlassian.net/browse/RTT-10333?atlOrigin=eyJpIjoiYzgwYTQ0ZjEyNzQzNGJhN2JmNjEyZTM0NmRhZWZhNjIiLCJwIjoic2hlZXRzLWppcmEifQ","RTT-10333") -> RTT-10333 | H21: Hawk Report | I21: Baseball | K21: MulticamAnalysis;MulticamPostProcess | M21: [no field found] | P21: 45754.585
A22: New Feature | B22: =HYPERLINK("https://hawk-eye.atlassian.net/browse/HWKREPORT-3405?atlOrigin=eyJpIjoiYzgwYTQ0ZjEyNzQzNGJhN2JmNjEyZTM0NmRhZWZhNjIiLCJwIjoic2hlZXRzLWppcmEifQ","HWKREPORT-3405") -> HWKREPORT-3405 | C22: Improvements to CPU usage for on prem BCPP | D22: P5 - Lowest | E22: Open | F22: 45754.588 | G22: =HYPERLINK("https://hawk-eye.atlassian.net/browse/?atlOrigin=eyJpIjoiYzgwYTQ0ZjEyNzQzNGJhN2JmNjEyZTM0NmRhZWZhNjIiLCJwIjoic2hlZXRzLWppcmEifQ","") | H22: Hawk Report | I22: Baseball | K22: BaseballCloudPostProcess | M22: [no field found] | P22: 45754.588
A23: New Feature | B23: =HYPERLINK("https://hawk-eye.atlassian.net/browse/HWKREPORT-3406?atlOrigin=eyJpIjoiYzgwYTQ0ZjEyNzQzNGJhN2JmNjEyZTM0NmRhZWZhNjIiLCJwIjoic2hlZXRzLWppcmEifQ","HWKREPORT-3406") -> HWKREPORT-3406 | C23: Improve BCPP processing time | D23: P2 - High | E23: On Hold | F23: 45754.589 | G23: =HYPERLINK("https://hawk-eye.atlassian.net/browse/RTT-10465?atlOrigin=eyJpIjoiYzgwYTQ0ZjEyNzQzNGJhN2JmNjEyZTM0NmRhZWZhNjIiLCJwIjoic2hlZXRzLWppcmEifQ","RTT-10465") -> RTT-10465 | H23: Hawk Report | I23: Baseball | K23: BaseballCloudPostProcess | M23: [no field found] | P23: 45779.585
A24: New Feature | B24: =HYPERLINK("https://hawk-eye.atlassian.net/browse/HWKREPORT-3407?atlOrigin=eyJpIjoiYzgwYTQ0ZjEyNzQzNGJhN2JmNjEyZTM0NmRhZWZhNjIiLCJwIjoic2hlZXRzLWppcmEifQ","HWKREPORT-3407") -> HWKREPORT-3407 | C24: Create ComputeCore DLL for AMD CPUs to improve BCPP CPU usage | D24: P5 - Lowest | E24: Open | F24: 45754.593 | G24: =HYPERLINK("https://hawk-eye.atlassian.net/browse/?atlOrigin=eyJpIjoiYzgwYTQ0ZjEyNzQzNGJhN2JmNjEyZTM0NmRhZWZhNjIiLCJwIjoic2hlZXRzLWppcmEifQ","") | H24: Hawk Report | I24: Baseball | K24: BaseballCloudPostProcess | M24: [no field found] | P24: 45754.593
A25: Bug | B25: =HYPERLINK("https://hawk-eye.atlassian.net/browse/HWKREPORT-3408?atlOrigin=eyJpIjoiYzgwYTQ0ZjEyNzQzNGJhN2JmNjEyZTM0NmRhZWZhNjIiLCJwIjoic2hlZXRzLWppcmEifQ","HWKREPORT-3408") -> HWKREPORT-3408 | C25: BkPP gives touch too early | D25: P3 - Medium | E25: Open | F25: 45754.752 | G25: =HYPERLINK("https://hawk-eye.atlassian.net/browse/RTT-10528?atlOrigin=eyJpIjoiYzgwYTQ0ZjEyNzQzNGJhN2JmNjEyZTM0NmRhZWZhNjIiLCJwIjoic2hlZXRzLWppcmEifQ","RTT-10528") -> RTT-10528 | H25: Hawk Report | I25: Basketball | K25: MulticamPostProcess | M25: [no field found] | P25: 45754.752
A26: Bug | B26: =HYPERLINK("https://hawk-eye.atlassian.net/browse/HWKREPORT-3409?atlOrigin=eyJpIjoiYzgwYTQ0ZjEyNzQzNGJhN2JmNjEyZTM0NmRhZWZhNjIiLCJwIjoic2hlZXRzLWppcmEifQ","HWKREPORT-3409") -> HWKREPORT-3409 | C26: Losing the "pencil" & "three dots" after clicking the expand button in Elastic bookmark panel | D26: P3 - Medium | E26: Open | F26: 45755.618 | G26: =HYPERLINK("https://hawk-eye.atlassian.net/browse/SO-2415?atlOrigin=eyJpIjoiYzgwYTQ0ZjEyNzQzNGJhN2JmNjEyZTM0NmRhZWZhNjIiLCJwIjoic2hlZXRzLWppcmEifQ","SO-2415") -> SO-2415 | H26: Hawk Report | I26: Motorsport;Rugby | K26: SMARTElastic;SMARTViewer | M26: [no field found] | P26: 45755.618
A27: New Feature | B27: =HYPERLINK("https://hawk-eye.atlassian.net/browse/HWKREPORT-3410?atlOrigin=eyJpIjoiYzgwYTQ0ZjEyNzQzNGJhN2JmNjEyZTM0NmRhZWZhNjIiLCJwIjoic2hlZXRzLWppcmEifQ","HWKREPORT-3410") -> HWKREPORT-3410 | C27: Plugin for stype / Mosys integration | D27: P5 - Lowest | E27: Open | F27: 45755.685 | G27: =HYPERLINK("https://hawk-eye.atlassian.net/browse/?atlOrigin=eyJpIjoiYzgwYTQ0ZjEyNzQzNGJhN2JmNjEyZTM0NmRhZWZhNjIiLCJwIjoic2hlZXRzLWppcmEifQ","") | H27: Hawk Report | I27: Cricket;Tennis | K27: HawkVR | M27: [no field found] | P27: 45755.685
A28: Bug | B28: =HYPERLINK("https://hawk-eye.atlassian.net/browse/HWKREPORT-3411?atlOrigin=eyJpIjoiYzgwYTQ0ZjEyNzQzNGJhN2JmNjEyZTM0NmRhZWZhNjIiLCJwIjoic2hlZXRzLWppcmEifQ","HWKREPORT-3411") -> HWKREPORT-3411 | C28: Camera Names.Ini not updated with correct heading | D28: P4 - Low | E28: Open | F28: 45756.165 | G28: =HYPERLINK("https://hawk-eye.atlassian.net/browse/?atlOrigin=eyJpIjoiYzgwYTQ0ZjEyNzQzNGJhN2JmNjEyZTM0NmRhZWZhNjIiLCJwIjoic2hlZXRzLWppcmEifQ","") | H28: Hawk Report | I28: Broadcast Systems | K28: SMARTMultiViewer | M28: [no field found] | P28: 45756.165
A29: Bug | B29: =HYPERLINK("https://hawk-eye.atlassian.net/browse/HWKREPORT-3412?atlOrigin=eyJpIjoiYzgwYTQ0ZjEyNzQzNGJhN2JmNjEyZTM0NmRhZWZhNjIiLCJwIjoic2hlZXRzLWppcmEifQ","HWKREPORT-3412") -> HWKREPORT-3412 | C29: "BallBoundary" events do not include clock data in output from Data Platform Sender | D29: P2 - High | E29: Done | F29: 45756.663 | G29: =HYPERLINK("https://hawk-eye.atlassian.net/browse/RTT-10412?atlOrigin=eyJpIjoiYzgwYTQ0ZjEyNzQzNGJhN2JmNjEyZTM0NmRhZWZhNjIiLCJwIjoic2hlZXRzLWppcmEifQ","RTT-10412") -> RTT-10412 | H29: Hawk Report | I29: Basketball | K29: MulticamAnalysis | M29: [no field found] | P29: 45762.405
A30: Bug | B30: =HYPERLINK("https://hawk-eye.atlassian.net/browse/HWKREPORT-3413?atlOrigin=eyJpIjoiYzgwYTQ0ZjEyNzQzNGJhN2JmNjEyZTM0NmRhZWZhNjIiLCJwIjoic2hlZXRzLWppcmEifQ","HWKREPORT-3413") -> HWKREPORT-3413 | C30: BMCA Crash | D30: P1 - Highest | E30: Done | F30: 45756.709 | G30: =HYPERLINK("https://hawk-eye.atlassian.net/browse/RTT-10410?atlOrigin=eyJpIjoiYzgwYTQ0ZjEyNzQzNGJhN2JmNjEyZTM0NmRhZWZhNjIiLCJwIjoic2hlZXRzLWppcmEifQ","RTT-10410") -> RTT-10410 | H30: Hawk Report | I30: Baseball | K30: MulticamAnalysis | M30: [no field found] | P30: 45762.482
A31: Bug | B31: =HYPERLINK("https://hawk-eye.atlassian.net/browse/HWKREPORT-3414?atlOrigin=eyJpIjoiYzgwYTQ0ZjEyNzQzNGJhN2JmNjEyZTM0NmRhZWZhNjIiLCJwIjoic2hlZXRzLWppcmEifQ","HWKREPORT-3414") -> HWKREPORT-3414 | C31: Missing hit_data packets because BTC frames dropping from BTC when hit complete is sent | D31: P2 - High | E31: On Hold | F31: 45756.716 | G31: =HYPERLINK("https://hawk-eye.atlassian.net/browse/RTT-10411?atlOrigin=eyJpIjoiYzgwYTQ0ZjEyNzQzNGJhN2JmNjEyZTM0NmRhZWZhNjIiLCJwIjoic2hlZXRzLWppcmEifQ","RTT-10411") -> RTT-10411 | H31: Hawk Report | I31: Baseball | K31: MulticamAnalysis | M31: [no field found] | P31: 45777.435
A32: New Feature | B32: =HYPERLINK("https://hawk-eye.atlassian.net/browse/HWKREPORT-3415?atlOrigin=eyJpIjoiYzgwYTQ0ZjEyNzQzNGJhN2JmNjEyZTM0NmRhZWZhNjIiLCJwIjoic2hlZXRzLWppcmEifQ","HWKREPORT-3415") -> HWKREPORT-3415 | C32: SAOOD to return VRDraw | D32: P5 - Lowest | E32: Open | F32: 45757.374 | G32: =HYPERLINK("https://hawk-eye.atlassian.net/browse/RTT-10437?atlOrigin=eyJpIjoiYzgwYTQ0ZjEyNzQzNGJhN2JmNjEyZTM0NmRhZWZhNjIiLCJwIjoic2hlZXRzLWppcmEifQ","RTT-10437") -> RTT-10437 | H32: Hawk Report | I32: Football | K32: MulticamAnalysis | M32: [no field found] | P32: 45757.374
A33: New Feature | B33: =HYPERLINK("https://hawk-eye.atlassian.net/browse/HWKREPORT-3416?atlOrigin=eyJpIjoiYzgwYTQ0ZjEyNzQzNGJhN2JmNjEyZTM0NmRhZWZhNjIiLCJwIjoic2hlZXRzLWppcmEifQ","HWKREPORT-3416") -> HWKREPORT-3416 | C33: Session name in VRControl to populate automatically from SMARTConfiguator | D33: P5 - Lowest | E33: Open | F33: 45757.523 | G33: =HYPERLINK("https://hawk-eye.atlassian.net/browse/?atlOrigin=eyJpIjoiYzgwYTQ0ZjEyNzQzNGJhN2JmNjEyZTM0NmRhZWZhNjIiLCJwIjoic2hlZXRzLWppcmEifQ","") | H33: Hawk Report | I33: Football | K33: VRControl | M33: [no field found] | P33: 45757.523
A34: New Feature | B34: =HYPERLINK("https://hawk-eye.atlassian.net/browse/HWKREPORT-3417?atlOrigin=eyJpIjoiYzgwYTQ0ZjEyNzQzNGJhN2JmNjEyZTM0NmRhZWZhNjIiLCJwIjoic2hlZXRzLWppcmEifQ","HWKREPORT-3417") -> HWKREPORT-3417 | C34: Ability to disable individual key and fills in SMARTViewer | D34: P5 - Lowest | E34: Open | F34: 45757.531 | G34: =HYPERLINK("https://hawk-eye.atlassian.net/browse/SO-2432?atlOrigin=eyJpIjoiYzgwYTQ0ZjEyNzQzNGJhN2JmNjEyZTM0NmRhZWZhNjIiLCJwIjoic2hlZXRzLWppcmEifQ","SO-2432") -> SO-2432 | H34: Hawk Report | I34: Football | K34: SMARTViewer | M34: [no field found] | P34: 45757.531
A35: New Feature | B35: =HYPERLINK("https://hawk-eye.atlassian.net/browse/HWKREPORT-3418?atlOrigin=eyJpIjoiYzgwYTQ0ZjEyNzQzNGJhN2JmNjEyZTM0NmRhZWZhNjIiLCJwIjoic2hlZXRzLWppcmEifQ","HWKREPORT-3418") -> HWKREPORT-3418 | C35: Add a logging feature to RabbitZMQ for non-delivered messages | D35: P4 - Low | E35: Open | F35: 45757.665 | G35: =HYPERLINK("https://hawk-eye.atlassian.net/browse/?atlOrigin=eyJpIjoiYzgwYTQ0ZjEyNzQzNGJhN2JmNjEyZTM0NmRhZWZhNjIiLCJwIjoic2hlZXRzLWppcmEifQ","") | H35: Hawk Report | I35: Baseball | K35: BaseballCloudPostProcess;BaseballDataPlatform | M35: [no field found] | P35: 45757.665
A36: New Feature | B36: =HYPERLINK("https://hawk-eye.atlassian.net/browse/HWKREPORT-3419?atlOrigin=eyJpIjoiYzgwYTQ0ZjEyNzQzNGJhN2JmNjEyZTM0NmRhZWZhNjIiLCJwIjoic2hlZXRzLWppcmEifQ","HWKREPORT-3419") -> HWKREPORT-3419 | C36: Add "Redundant Task, Not Processed" option to BMCC | D36: P4 - Low | E36: Open | F36: 45757.666 | G36: =HYPERLINK("https://hawk-eye.atlassian.net/browse/?atlOrigin=eyJpIjoiYzgwYTQ0ZjEyNzQzNGJhN2JmNjEyZTM0NmRhZWZhNjIiLCJwIjoic2hlZXRzLWppcmEifQ","") | H36: Hawk Report | I36: Baseball | K36: MulticamAnalysis | M36: [no field found] | P36: 45757.666
A37: New Feature | B37: =HYPERLINK("https://hawk-eye.atlassian.net/browse/HWKREPORT-3420?atlOrigin=eyJpIjoiYzgwYTQ0ZjEyNzQzNGJhN2JmNjEyZTM0NmRhZWZhNjIiLCJwIjoic2hlZXRzLWppcmEifQ","HWKREPORT-3420") -> HWKREPORT-3420 | C37: Have more than 1 RabbitZmq consumer per Live CPP queue | D37: P3 - Medium | E37: Open | F37: 45757.667 | G37: =HYPERLINK("https://hawk-eye.atlassian.net/browse/?atlOrigin=eyJpIjoiYzgwYTQ0ZjEyNzQzNGJhN2JmNjEyZTM0NmRhZWZhNjIiLCJwIjoic2hlZXRzLWppcmEifQ","") | H37: Hawk Report | I37: Baseball | K37: BaseballCloudPostProcess;BaseballDataPlatform | M37: [no field found] | P37: 45757.667
A38: New Feature | B38: =HYPERLINK("https://hawk-eye.atlassian.net/browse/HWKREPORT-3421?atlOrigin=eyJpIjoiYzgwYTQ0ZjEyNzQzNGJhN2JmNjEyZTM0NmRhZWZhNjIiLCJwIjoic2hlZXRzLWppcmEifQ","HWKREPORT-3421") -> HWKREPORT-3421 | C38: Return PP results to Control Main and Control Spare | D38: P4 - Low | E38: Open | F38: 45757.675 | G38: =HYPERLINK("https://hawk-eye.atlassian.net/browse/?atlOrigin=eyJpIjoiYzgwYTQ0ZjEyNzQzNGJhN2JmNjEyZTM0NmRhZWZhNjIiLCJwIjoic2hlZXRzLWppcmEifQ","") | H38: Hawk Report | I38: Baseball | K38: MulticamAnalysis;MulticamPostProcess | M38: [no field found] | P38: 45757.675
A39: Bug | B39: =HYPERLINK("https://hawk-eye.atlassian.net/browse/HWKREPORT-3422?atlOrigin=eyJpIjoiYzgwYTQ0ZjEyNzQzNGJhN2JmNjEyZTM0NmRhZWZhNjIiLCJwIjoic2hlZXRzLWppcmEifQ","HWKREPORT-3422") -> HWKREPORT-3422 | C39: NHl Cloud PH&S | Specific User Account Slowly Drifting Further Behind Live | D39: P2 - High | E39: Open | F39: 45757.709 | G39: =HYPERLINK("https://hawk-eye.atlassian.net/browse/?atlOrigin=eyJpIjoiYzgwYTQ0ZjEyNzQzNGJhN2JmNjEyZTM0NmRhZWZhNjIiLCJwIjoic2hlZXRzLWppcmEifQ","") | H39: Hawk Report | I39: Ice Hockey | K39: SMARTViewer | M39: [no field found] | P39: 45757.709
A40: Bug | B40: =HYPERLINK("https://hawk-eye.atlassian.net/browse/HWKREPORT-3423?atlOrigin=eyJpIjoiYzgwYTQ0ZjEyNzQzNGJhN2JmNjEyZTM0NmRhZWZhNjIiLCJwIjoic2hlZXRzLWppcmEifQ","HWKREPORT-3423") -> HWKREPORT-3423 | C40: SAOOD - App crashing when using direct connection from OMCC1 to SAOOD1 | D40: P2 - High | E40: Open | F40: 45758.443 | G40: =HYPERLINK("https://hawk-eye.atlassian.net/browse/?atlOrigin=eyJpIjoiYzgwYTQ0ZjEyNzQzNGJhN2JmNjEyZTM0NmRhZWZhNjIiLCJwIjoic2hlZXRzLWppcmEifQ","") | H40: Hawk Report | I40: Football | K40: MulticamAnalysis | M40: [no field found] | P40: 45758.443
A41: Bug | B41: =HYPERLINK("https://hawk-eye.atlassian.net/browse/HWKREPORT-3424?atlOrigin=eyJpIjoiYzgwYTQ0ZjEyNzQzNGJhN2JmNjEyZTM0NmRhZWZhNjIiLCJwIjoic2hlZXRzLWppcmEifQ","HWKREPORT-3424") -> HWKREPORT-3424 | C41: BMCC Crash - 4/13/2025 | D41: P1 - Highest | E41: Done | F41: 45761.591 | G41: =HYPERLINK("https://hawk-eye.atlassian.net/browse/RTT-10427?atlOrigin=eyJpIjoiYzgwYTQ0ZjEyNzQzNGJhN2JmNjEyZTM0NmRhZWZhNjIiLCJwIjoic2hlZXRzLWppcmEifQ","RTT-10427") -> RTT-10427 | H41: Hawk Report | I41: Baseball | K41: MulticamAnalysis | M41: [no field found] | P41: 45762.494
A42: New Feature | B42: =HYPERLINK("https://hawk-eye.atlassian.net/browse/HWKREPORT-3425?atlOrigin=eyJpIjoiYzgwYTQ0ZjEyNzQzNGJhN2JmNjEyZTM0NmRhZWZhNjIiLCJwIjoic2hlZXRzLWppcmEifQ","HWKREPORT-3425") -> HWKREPORT-3425 | C42: Adding a 'Test Audio' button to the testing side-panel that will play an 'AudioTest.wav' audio file | D42: P5 - Lowest | E42: Open | F42: 45761.721 | G42: =HYPERLINK("https://hawk-eye.atlassian.net/browse/?atlOrigin=eyJpIjoiYzgwYTQ0ZjEyNzQzNGJhN2JmNjEyZTM0NmRhZWZhNjIiLCJwIjoic2hlZXRzLWppcmEifQ","") | H42: Hawk Report | I42: Tennis | K42: RTTDataBridge | M42: [no field found] | P42: 45761.721
A43: Bug | B43: =HYPERLINK("https://hawk-eye.atlassian.net/browse/HWKREPORT-3426?atlOrigin=eyJpIjoiYzgwYTQ0ZjEyNzQzNGJhN2JmNjEyZTM0NmRhZWZhNjIiLCJwIjoic2hlZXRzLWppcmEifQ","HWKREPORT-3426") -> HWKREPORT-3426 | C43: OMCC1 & OMCC2 crashing at exactly the same time (3 matches in one weekend) | D43: P1 - Highest | E43: Done | F43: 45762.412 | G43: =HYPERLINK("https://hawk-eye.atlassian.net/issues/?atlOrigin=eyJpIjoiYzgwYTQ0ZjEyNzQzNGJhN2JmNjEyZTM0NmRhZWZhNjIiLCJwIjoic2hlZXRzLWppcmEifQ&jql=key+in+%28RTT-10433%2CRTT-10446%29","RTT-10433;RTT-10446") -> RTT-10433;RTT-10446 | H43: Hawk Report | I43: Football | K43: MulticamAnalysis | M43: [no field found] | P43: 45778.638
A44: New Feature | B44: =HYPERLINK("https://hawk-eye.atlassian.net/browse/HWKREPORT-3427?atlOrigin=eyJpIjoiYzgwYTQ0ZjEyNzQzNGJhN2JmNjEyZTM0NmRhZWZhNjIiLCJwIjoic2hlZXRzLWppcmEifQ","HWKREPORT-3427") -> HWKREPORT-3427 | C44: Baseball Reprocessing Dashboard Update | D44: P2 - High | E44: Open | F44: 45763.632 | G44: =HYPERLINK("https://hawk-eye.atlassian.net/issues/?atlOrigin=eyJpIjoiYzgwYTQ0ZjEyNzQzNGJhN2JmNjEyZTM0NmRhZWZhNjIiLCJwIjoic2hlZXRzLWppcmEifQ&jql=key+in+%28BAS-1131%2CBAS-1132%2CBAS-1133%2CBAS-1134%29","BAS-1131;BAS-1132;BAS-1133;BAS-1134") -> BAS-1131;BAS-1132;BAS-1133;BAS-1134 | H44: Hawk Report | I44: Baseball | K44: BaseballDataPlatform | M44: [no field found] | P44: 45763.632
A45: Bug | B45: =HYPERLINK("https://hawk-eye.atlassian.net/browse/HWKREPORT-3428?atlOrigin=eyJpIjoiYzgwYTQ0ZjEyNzQzNGJhN2JmNjEyZTM0NmRhZWZhNjIiLCJwIjoic2hlZXRzLWppcmEifQ","HWKREPORT-3428") -> HWKREPORT-3428 | C45: BkPP - Chance to Score projection goes through backboard | D45: P3 - Medium | E45: Open | F45: 45763.935 | G45: =HYPERLINK("https://hawk-eye.atlassian.net/browse/?atlOrigin=eyJpIjoiYzgwYTQ0ZjEyNzQzNGJhN2JmNjEyZTM0NmRhZWZhNjIiLCJwIjoic2hlZXRzLWppcmEifQ","") | H45: Hawk Report | I45: Basketball | K45: MulticamPostProcess | M45: [no field found] | P45: 45763.935
A46: New Feature | B46: =HYPERLINK("https://hawk-eye.atlassian.net/browse/HWKREPORT-3429?atlOrigin=eyJpIjoiYzgwYTQ0ZjEyNzQzNGJhN2JmNjEyZTM0NmRhZWZhNjIiLCJwIjoic2hlZXRzLWppcmEifQ","HWKREPORT-3429") -> HWKREPORT-3429 | C46: Option to disable the "Do you want to save your smartfile?" prompt when closing configurator | D46: P5 - Lowest | E46: Open | F46: 45764.415 | G46: =HYPERLINK("https://hawk-eye.atlassian.net/browse/?atlOrigin=eyJpIjoiYzgwYTQ0ZjEyNzQzNGJhN2JmNjEyZTM0NmRhZWZhNjIiLCJwIjoic2hlZXRzLWppcmEifQ","") | H46: Hawk Report | I46: Horse Racing;Motorsport | K46: SMARTConfigurator | M46: [no field found] | P46: 45764.415
A47: Bug | B47: =HYPERLINK("https://hawk-eye.atlassian.net/browse/HWKREPORT-3430?atlOrigin=eyJpIjoiYzgwYTQ0ZjEyNzQzNGJhN2JmNjEyZTM0NmRhZWZhNjIiLCJwIjoic2hlZXRzLWppcmEifQ","HWKREPORT-3430") -> HWKREPORT-3430 | C47: MLB not receiving pitch_refined data for pitches | D47: P2 - High | E47: On Hold | F47: 45764.654 | G47: =HYPERLINK("https://hawk-eye.atlassian.net/browse/RTT-10459?atlOrigin=eyJpIjoiYzgwYTQ0ZjEyNzQzNGJhN2JmNjEyZTM0NmRhZWZhNjIiLCJwIjoic2hlZXRzLWppcmEifQ","RTT-10459") -> RTT-10459 | H47: Hawk Report | I47: Baseball | K47: MulticamAnalysis | M47: [no field found] | P47: 45783.398
A48: New Feature | B48: =HYPERLINK("https://hawk-eye.atlassian.net/browse/HWKREPORT-3431?atlOrigin=eyJpIjoiYzgwYTQ0ZjEyNzQzNGJhN2JmNjEyZTM0NmRhZWZhNjIiLCJwIjoic2hlZXRzLWppcmEifQ","HWKREPORT-3431") -> HWKREPORT-3431 | C48: FIFA Club World Cup Balls | D48: P2 - High | E48: Open | F48: 45764.663 | G48: =HYPERLINK("https://hawk-eye.atlassian.net/browse/AT-1802?atlOrigin=eyJpIjoiYzgwYTQ0ZjEyNzQzNGJhN2JmNjEyZTM0NmRhZWZhNjIiLCJwIjoic2hlZXRzLWppcmEifQ","AT-1802") -> AT-1802 | H48: Hawk Report | I48: Football | M48: [no field found] | P48: 45764.663
A49: New Feature | B49: =HYPERLINK("https://hawk-eye.atlassian.net/browse/HWKREPORT-3432?atlOrigin=eyJpIjoiYzgwYTQ0ZjEyNzQzNGJhN2JmNjEyZTM0NmRhZWZhNjIiLCJwIjoic2hlZXRzLWppcmEifQ","HWKREPORT-3432") -> HWKREPORT-3432 | C49: .CSV OMCC Export Ticket | D49: P5 - Lowest | E49: Open | F49: 45764.785 | G49: =HYPERLINK("https://hawk-eye.atlassian.net/browse/RTT-10501?atlOrigin=eyJpIjoiYzgwYTQ0ZjEyNzQzNGJhN2JmNjEyZTM0NmRhZWZhNjIiLCJwIjoic2hlZXRzLWppcmEifQ","RTT-10501") -> RTT-10501 | H49: Hawk Report | I49: Football | K49: MulticamAnalysis | M49: [no field found] | P49: 45764.785
A50: New Feature | B50: =HYPERLINK("https://hawk-eye.atlassian.net/browse/HWKREPORT-3433?atlOrigin=eyJpIjoiYzgwYTQ0ZjEyNzQzNGJhN2JmNjEyZTM0NmRhZWZhNjIiLCJwIjoic2hlZXRzLWppcmEifQ","HWKREPORT-3433") -> HWKREPORT-3433 | C50: AOT - Add logic for when sub frame decision is different to decision on frame | D50: P5 - Lowest | E50: Open | F50: 45764.794 | G50: =HYPERLINK("https://hawk-eye.atlassian.net/browse/RTT-10499?atlOrigin=eyJpIjoiYzgwYTQ0ZjEyNzQzNGJhN2JmNjEyZTM0NmRhZWZhNjIiLCJwIjoic2hlZXRzLWppcmEifQ","RTT-10499") -> RTT-10499 | H50: Hawk Report | I50: Football | K50: MulticamAnalysis | M50: [no field found] | P50: 45764.794
A51: Bug | B51: =HYPERLINK("https://hawk-eye.atlassian.net/browse/HWKREPORT-3434?atlOrigin=eyJpIjoiYzgwYTQ0ZjEyNzQzNGJhN2JmNjEyZTM0NmRhZWZhNjIiLCJwIjoic2hlZXRzLWppcmEifQ","HWKREPORT-3434") -> HWKREPORT-3434 | C51: Layouts Panel Not Updating With Active Layout | D51: P1 - Highest | E51: Open | F51: 45764.853 | G51: =HYPERLINK("https://hawk-eye.atlassian.net/browse/?atlOrigin=eyJpIjoiYzgwYTQ0ZjEyNzQzNGJhN2JmNjEyZTM0NmRhZWZhNjIiLCJwIjoic2hlZXRzLWppcmEifQ","") | H51: Hawk Report | I51: Broadcast Systems | K51: SMARTMultiViewer | M51: [no field found] | P51: 45764.853
A52: Bug | B52: =HYPERLINK("https://hawk-eye.atlassian.net/browse/HWKREPORT-3435?atlOrigin=eyJpIjoiYzgwYTQ0ZjEyNzQzNGJhN2JmNjEyZTM0NmRhZWZhNjIiLCJwIjoic2hlZXRzLWppcmEifQ","HWKREPORT-3435") -> HWKREPORT-3435 | C52: Incorrect touch points for Goaltending Events | D52: P1 - Highest | E52: Work in progress | F52: 45765.723 | G52: =HYPERLINK("https://hawk-eye.atlassian.net/issues/?atlOrigin=eyJpIjoiYzgwYTQ0ZjEyNzQzNGJhN2JmNjEyZTM0NmRhZWZhNjIiLCJwIjoic2hlZXRzLWppcmEifQ&jql=key+in+%28RTT-10504%2CRTT-10526%29","RTT-10504;RTT-10526") -> RTT-10504;RTT-10526 | H52: Hawk Report | I52: Basketball | K52: MulticamAnalysis | M52: [no field found] | P52: 45777.464
A53: Bug | B53: =HYPERLINK("https://hawk-eye.atlassian.net/browse/HWKREPORT-3436?atlOrigin=eyJpIjoiYzgwYTQ0ZjEyNzQzNGJhN2JmNjEyZTM0NmRhZWZhNjIiLCJwIjoic2hlZXRzLWppcmEifQ","HWKREPORT-3436") -> HWKREPORT-3436 | C53: Ball position jitter causing fluctuating up/down determinations | D53: P1 - Highest | E53: Done | F53: 45765.781 | G53: =HYPERLINK("https://hawk-eye.atlassian.net/browse/RTT-10450?atlOrigin=eyJpIjoiYzgwYTQ0ZjEyNzQzNGJhN2JmNjEyZTM0NmRhZWZhNjIiLCJwIjoic2hlZXRzLWppcmEifQ","RTT-10450") -> RTT-10450 | H53: Hawk Report | I53: Basketball | K53: MulticamAnalysis | M53: [no field found] | P53: 45778.634
A54: Bug | B54: =HYPERLINK("https://hawk-eye.atlassian.net/browse/HWKREPORT-3437?atlOrigin=eyJpIjoiYzgwYTQ0ZjEyNzQzNGJhN2JmNjEyZTM0NmRhZWZhNjIiLCJwIjoic2hlZXRzLWppcmEifQ","HWKREPORT-3437") -> HWKREPORT-3437 | C54: GroundControl not sending session ID to BaseballDataConverter | D54: P2 - High | E54: Open | F54: 45768.797 | G54: =HYPERLINK("https://hawk-eye.atlassian.net/browse/?atlOrigin=eyJpIjoiYzgwYTQ0ZjEyNzQzNGJhN2JmNjEyZTM0NmRhZWZhNjIiLCJwIjoic2hlZXRzLWppcmEifQ","") | H54: Hawk Report | I54: Baseball | K54: GroundControl | M54: [no field found] | P54: 45768.797
A55: Bug | B55: =HYPERLINK("https://hawk-eye.atlassian.net/browse/HWKREPORT-3438?atlOrigin=eyJpIjoiYzgwYTQ0ZjEyNzQzNGJhN2JmNjEyZTM0NmRhZWZhNjIiLCJwIjoic2hlZXRzLWppcmEifQ","HWKREPORT-3438") -> HWKREPORT-3438 | C55: Elastic Panel - Dropdowns Will Scroll When The Mouse Scroll Wheel Is Used | D55: P5 - Lowest | E55: Open | F55: 45769.441 | G55: =HYPERLINK("https://hawk-eye.atlassian.net/browse/?atlOrigin=eyJpIjoiYzgwYTQ0ZjEyNzQzNGJhN2JmNjEyZTM0NmRhZWZhNjIiLCJwIjoic2hlZXRzLWppcmEifQ","") | H55: Hawk Report | I55: Motorsport;Rugby | K55: SMARTViewer | M55: [no field found] | P55: 45769.441
A56: Bug | B56: =HYPERLINK("https://hawk-eye.atlassian.net/browse/HWKREPORT-3439?atlOrigin=eyJpIjoiYzgwYTQ0ZjEyNzQzNGJhN2JmNjEyZTM0NmRhZWZhNjIiLCJwIjoic2hlZXRzLWppcmEifQ","HWKREPORT-3439") -> HWKREPORT-3439 | C56: No Ball Panel Track Selection Issues | D56: P3 - Medium | E56: Done | F56: 45769.566 | G56: =HYPERLINK("https://hawk-eye.atlassian.net/browse/SO-2454?atlOrigin=eyJpIjoiYzgwYTQ0ZjEyNzQzNGJhN2JmNjEyZTM0NmRhZWZhNjIiLCJwIjoic2hlZXRzLWppcmEifQ","SO-2454") -> SO-2454 | H56: Hawk Report | I56: Cricket | K56: SMARTViewer | M56: [no field found] | P56: 45776.679
A57: Bug | B57: =HYPERLINK("https://hawk-eye.atlassian.net/browse/HWKREPORT-3440?atlOrigin=eyJpIjoiYzgwYTQ0ZjEyNzQzNGJhN2JmNjEyZTM0NmRhZWZhNjIiLCJwIjoic2hlZXRzLWppcmEifQ","HWKREPORT-3440") -> HWKREPORT-3440 | C57: Incorrect traj ordering in No Ball Panel | D57: P3 - Medium | E57: Done | F57: 45769.568 | G57: =HYPERLINK("https://hawk-eye.atlassian.net/browse/SO-2455?atlOrigin=eyJpIjoiYzgwYTQ0ZjEyNzQzNGJhN2JmNjEyZTM0NmRhZWZhNjIiLCJwIjoic2hlZXRzLWppcmEifQ","SO-2455") -> SO-2455 | H57: Hawk Report | I57: Cricket | K57: SMARTViewer | M57: [no field found] | P57: 45777.545
A58: New Feature | B58: =HYPERLINK("https://hawk-eye.atlassian.net/browse/HWKREPORT-3441?atlOrigin=eyJpIjoiYzgwYTQ0ZjEyNzQzNGJhN2JmNjEyZTM0NmRhZWZhNjIiLCJwIjoic2hlZXRzLWppcmEifQ","HWKREPORT-3441") -> HWKREPORT-3441 | C58: Having to put a debug command in HawkVR so that models don't block preset moves for LBWs | D58: P5 - Lowest | E58: Open | F58: 45769.578 | G58: =HYPERLINK("https://hawk-eye.atlassian.net/browse/?atlOrigin=eyJpIjoiYzgwYTQ0ZjEyNzQzNGJhN2JmNjEyZTM0NmRhZWZhNjIiLCJwIjoic2hlZXRzLWppcmEifQ","") | H58: Hawk Report | I58: Cricket | K58: HawkVR;VRControl | M58: [no field found] | P58: 45769.578
A59: New Feature | B59: =HYPERLINK("https://hawk-eye.atlassian.net/browse/HWKREPORT-3442?atlOrigin=eyJpIjoiYzgwYTQ0ZjEyNzQzNGJhN2JmNjEyZTM0NmRhZWZhNjIiLCJwIjoic2hlZXRzLWppcmEifQ","HWKREPORT-3442") -> HWKREPORT-3442 | C59: Ball Spanish King´s Cup "Victoria" | D59: P2 - High | E59: Open | F59: 45769.65 | G59: =HYPERLINK("https://hawk-eye.atlassian.net/browse/AT-1804?atlOrigin=eyJpIjoiYzgwYTQ0ZjEyNzQzNGJhN2JmNjEyZTM0NmRhZWZhNjIiLCJwIjoic2hlZXRzLWppcmEifQ","AT-1804") -> AT-1804 | H59: Hawk Report | I59: Football | M59: [no field found] | P59: 45769.65
A60: New Feature | B60: =HYPERLINK("https://hawk-eye.atlassian.net/browse/HWKREPORT-3443?atlOrigin=eyJpIjoiYzgwYTQ0ZjEyNzQzNGJhN2JmNjEyZTM0NmRhZWZhNjIiLCJwIjoic2hlZXRzLWppcmEifQ","HWKREPORT-3443") -> HWKREPORT-3443 | C60: Option to have Camera Coverage map with up to 8+ cameras | D60: P5 - Lowest | E60: Open | F60: 45769.808 | G60: =HYPERLINK("https://hawk-eye.atlassian.net/browse/RTT-10498?atlOrigin=eyJpIjoiYzgwYTQ0ZjEyNzQzNGJhN2JmNjEyZTM0NmRhZWZhNjIiLCJwIjoic2hlZXRzLWppcmEifQ","RTT-10498") -> RTT-10498 | H60: Hawk Report | I60: American Football | K60: MulticamAnalysis | M60: [no field found] | P60: 45769.808
A61: Bug | B61: =HYPERLINK("https://hawk-eye.atlassian.net/browse/HWKREPORT-3444?atlOrigin=eyJpIjoiYzgwYTQ0ZjEyNzQzNGJhN2JmNjEyZTM0NmRhZWZhNjIiLCJwIjoic2hlZXRzLWppcmEifQ","HWKREPORT-3444") -> HWKREPORT-3444 | C61: Combination logic: sending many events in a very short period of time(1s) | D61: P3 - Medium | E61: Open | F61: 45770.469 | G61: =HYPERLINK("https://hawk-eye.atlassian.net/browse/?atlOrigin=eyJpIjoiYzgwYTQ0ZjEyNzQzNGJhN2JmNjEyZTM0NmRhZWZhNjIiLCJwIjoic2hlZXRzLWppcmEifQ","") | H61: Hawk Report | I61: Football | K61: FELA;FootballDataPlatform | M61: [no field found] | P61: 45770.469
A62: New Feature | B62: =HYPERLINK("https://hawk-eye.atlassian.net/browse/HWKREPORT-3445?atlOrigin=eyJpIjoiYzgwYTQ0ZjEyNzQzNGJhN2JmNjEyZTM0NmRhZWZhNjIiLCJwIjoic2hlZXRzLWppcmEifQ","HWKREPORT-3445") -> HWKREPORT-3445 | C62: Timeline marker to indicate that a loop in-point has been set | D62: P5 - Lowest | E62: Open | F62: 45770.591 | G62: =HYPERLINK("https://hawk-eye.atlassian.net/browse/SO-2456?atlOrigin=eyJpIjoiYzgwYTQ0ZjEyNzQzNGJhN2JmNjEyZTM0NmRhZWZhNjIiLCJwIjoic2hlZXRzLWppcmEifQ","SO-2456") -> SO-2456 | H62: Hawk Report | I62: Horse Racing;Rugby | K62: SMARTViewer | M62: [no field found] | P62: 45770.591
A63: Bug | B63: =HYPERLINK("https://hawk-eye.atlassian.net/browse/HWKREPORT-3446?atlOrigin=eyJpIjoiYzgwYTQ0ZjEyNzQzNGJhN2JmNjEyZTM0NmRhZWZhNjIiLCJwIjoic2hlZXRzLWppcmEifQ","HWKREPORT-3446") -> HWKREPORT-3446 | C63: Match summary feeds & match summary heatmaps not producing aggregated files for summary and segments | D63: P2 - High | E63: Open | F63: 45770.813 | G63: =HYPERLINK("https://hawk-eye.atlassian.net/browse/?atlOrigin=eyJpIjoiYzgwYTQ0ZjEyNzQzNGJhN2JmNjEyZTM0NmRhZWZhNjIiLCJwIjoic2hlZXRzLWppcmEifQ","") | H63: Hawk Report | I63: Football | K63: FootballDataPlatform | M63: [no field found] | P63: 45770.813
A64: Bug | B64: =HYPERLINK("https://hawk-eye.atlassian.net/browse/HWKREPORT-3447?atlOrigin=eyJpIjoiYzgwYTQ0ZjEyNzQzNGJhN2JmNjEyZTM0NmRhZWZhNjIiLCJwIjoic2hlZXRzLWppcmEifQ","HWKREPORT-3447") -> HWKREPORT-3447 | C64: Refeee Role Id in match.summary and match.heatmap is different in JAVA vs C# | D64: P2 - High | E64: Open | F64: 45770.834 | G64: =HYPERLINK("https://hawk-eye.atlassian.net/browse/?atlOrigin=eyJpIjoiYzgwYTQ0ZjEyNzQzNGJhN2JmNjEyZTM0NmRhZWZhNjIiLCJwIjoic2hlZXRzLWppcmEifQ","") | H64: Hawk Report | I64: Football | K64: FootballDataPlatform | M64: [no field found] | P64: 45770.834
A65: New Feature | B65: =HYPERLINK("https://hawk-eye.atlassian.net/browse/HWKREPORT-3448?atlOrigin=eyJpIjoiYzgwYTQ0ZjEyNzQzNGJhN2JmNjEyZTM0NmRhZWZhNjIiLCJwIjoic2hlZXRzLWppcmEifQ","HWKREPORT-3448") -> HWKREPORT-3448 | C65: Make it more obvious when a bookmark has been favorited | D65: P5 - Lowest | E65: Open | F65: 45771.418 | G65: =HYPERLINK("https://hawk-eye.atlassian.net/browse/?atlOrigin=eyJpIjoiYzgwYTQ0ZjEyNzQzNGJhN2JmNjEyZTM0NmRhZWZhNjIiLCJwIjoic2hlZXRzLWppcmEifQ","") | H65: Hawk Report | I65: Horse Racing;Motorsport | K65: SMARTViewer | M65: [no field found] | P65: 45771.418
A66: Bug | B66: =HYPERLINK("https://hawk-eye.atlassian.net/browse/HWKREPORT-3449?atlOrigin=eyJpIjoiYzgwYTQ0ZjEyNzQzNGJhN2JmNjEyZTM0NmRhZWZhNjIiLCJwIjoic2hlZXRzLWppcmEifQ","HWKREPORT-3449") -> HWKREPORT-3449 | C66: Team in Yellow not tracking many players | D66: P2 - High | E66: Open | F66: 45772.646 | G66: =HYPERLINK("https://hawk-eye.atlassian.net/browse/?atlOrigin=eyJpIjoiYzgwYTQ0ZjEyNzQzNGJhN2JmNjEyZTM0NmRhZWZhNjIiLCJwIjoic2hlZXRzLWppcmEifQ","") | H66: Hawk Report | I66: American Football | K66: Annotation | M66: [no field found] | P66: 45772.646
A67: Bug | B67: =HYPERLINK("https://hawk-eye.atlassian.net/browse/HWKREPORT-3450?atlOrigin=eyJpIjoiYzgwYTQ0ZjEyNzQzNGJhN2JmNjEyZTM0NmRhZWZhNjIiLCJwIjoic2hlZXRzLWppcmEifQ","HWKREPORT-3450") -> HWKREPORT-3450 | C67: OMCA - Focus peaking not enabling | D67: P3 - Medium | E67: Open | F67: 45775.656 | G67: =HYPERLINK("https://hawk-eye.atlassian.net/browse/RTT-10502?atlOrigin=eyJpIjoiYzgwYTQ0ZjEyNzQzNGJhN2JmNjEyZTM0NmRhZWZhNjIiLCJwIjoic2hlZXRzLWppcmEifQ","RTT-10502") -> RTT-10502 | H67: Hawk Report | I67: Football | K67: MulticamAnalysis | M67: [no field found] | P67: 45775.656
A68: New Feature | B68: =HYPERLINK("https://hawk-eye.atlassian.net/browse/HWKREPORT-3451?atlOrigin=eyJpIjoiYzgwYTQ0ZjEyNzQzNGJhN2JmNjEyZTM0NmRhZWZhNjIiLCJwIjoic2hlZXRzLWppcmEifQ","HWKREPORT-3451") -> HWKREPORT-3451 | C68: New Emergent Firmwares for V2 | D68: P2 - High | E68: Open | F68: 45775.683 | G68: =HYPERLINK("https://hawk-eye.atlassian.net/browse/RTT-10503?atlOrigin=eyJpIjoiYzgwYTQ0ZjEyNzQzNGJhN2JmNjEyZTM0NmRhZWZhNjIiLCJwIjoic2hlZXRzLWppcmEifQ","RTT-10503") -> RTT-10503 | H68: Hawk Report | I68: Baseball | K68: MulticamAnalysis | M68: [no field found] | P68: 45775.683
A69: Bug | B69: =HYPERLINK("https://hawk-eye.atlassian.net/browse/HWKREPORT-3452?atlOrigin=eyJpIjoiYzgwYTQ0ZjEyNzQzNGJhN2JmNjEyZTM0NmRhZWZhNjIiLCJwIjoic2hlZXRzLWppcmEifQ","HWKREPORT-3452") -> HWKREPORT-3452 | C69: Player distance avg field added in Java summary feed but always reports 0.0 | D69: P3 - Medium | E69: Open | F69: 45775.724 | G69: =HYPERLINK("https://hawk-eye.atlassian.net/browse/?atlOrigin=eyJpIjoiYzgwYTQ0ZjEyNzQzNGJhN2JmNjEyZTM0NmRhZWZhNjIiLCJwIjoic2hlZXRzLWppcmEifQ","") | H69: Hawk Report | I69: Football | K69: FootballDataPlatform | M69: [no field found] | P69: 45775.724
A70: Bug | B70: =HYPERLINK("https://hawk-eye.atlassian.net/browse/HWKREPORT-3453?atlOrigin=eyJpIjoiYzgwYTQ0ZjEyNzQzNGJhN2JmNjEyZTM0NmRhZWZhNjIiLCJwIjoic2hlZXRzLWppcmEifQ","HWKREPORT-3453") -> HWKREPORT-3453 | C70: "time" differences in summary feed between C# and Java | D70: P4 - Low | E70: Open | F70: 45775.732 | G70: =HYPERLINK("https://hawk-eye.atlassian.net/browse/?atlOrigin=eyJpIjoiYzgwYTQ0ZjEyNzQzNGJhN2JmNjEyZTM0NmRhZWZhNjIiLCJwIjoic2hlZXRzLWppcmEifQ","") | H70: Hawk Report | I70: Football | K70: FootballDataPlatform | M70: [no field found] | P70: 45775.732
A71: Bug | B71: =HYPERLINK("https://hawk-eye.atlassian.net/browse/HWKREPORT-3454?atlOrigin=eyJpIjoiYzgwYTQ0ZjEyNzQzNGJhN2JmNjEyZTM0NmRhZWZhNjIiLCJwIjoic2hlZXRzLWppcmEifQ","HWKREPORT-3454") -> HWKREPORT-3454 | C71: Z Cam Mirror packet loss statistics on the UI | D71: P3 - Medium | E71: Open | F71: 45775.893 | G71: =HYPERLINK("https://hawk-eye.atlassian.net/browse/?atlOrigin=eyJpIjoiYzgwYTQ0ZjEyNzQzNGJhN2JmNjEyZTM0NmRhZWZhNjIiLCJwIjoic2hlZXRzLWppcmEifQ","") | H71: Hawk Report | I71: American Football | K71: ZCamMirror | M71: [no field found] | P71: 45775.893
A72: New Feature | B72: =HYPERLINK("https://hawk-eye.atlassian.net/browse/HWKREPORT-3455?atlOrigin=eyJpIjoiYzgwYTQ0ZjEyNzQzNGJhN2JmNjEyZTM0NmRhZWZhNjIiLCJwIjoic2hlZXRzLWppcmEifQ","HWKREPORT-3455") -> HWKREPORT-3455 | C72: BBC Plaque | D72: P3 - Medium | E72: Open | F72: 45776.602 | G72: =HYPERLINK("https://hawk-eye.atlassian.net/browse/AT-1817?atlOrigin=eyJpIjoiYzgwYTQ0ZjEyNzQzNGJhN2JmNjEyZTM0NmRhZWZhNjIiLCJwIjoic2hlZXRzLWppcmEifQ","AT-1817") -> AT-1817 | H72: Hawk Report | I72: Cricket | M72: [no field found] | P72: 45776.602
A73: Bug | B73: =HYPERLINK("https://hawk-eye.atlassian.net/browse/HWKREPORT-3456?atlOrigin=eyJpIjoiYzgwYTQ0ZjEyNzQzNGJhN2JmNjEyZTM0NmRhZWZhNjIiLCJwIjoic2hlZXRzLWppcmEifQ","HWKREPORT-3456") -> HWKREPORT-3456 | C73: NHL Cloud PH&S | All Feeds Falling Further Behind Live as the Game Progresses | D73: P2 - High | E73: Open | F73: 45776.621 | G73: =HYPERLINK("https://hawk-eye.atlassian.net/browse/?atlOrigin=eyJpIjoiYzgwYTQ0ZjEyNzQzNGJhN2JmNjEyZTM0NmRhZWZhNjIiLCJwIjoic2hlZXRzLWppcmEifQ","") | H73: Hawk Report | I73: Ice Hockey | K73: SMARTViewer | M73: [no field found] | P73: 45776.621
A74: Bug | B74: =HYPERLINK("https://hawk-eye.atlassian.net/browse/HWKREPORT-3457?atlOrigin=eyJpIjoiYzgwYTQ0ZjEyNzQzNGJhN2JmNjEyZTM0NmRhZWZhNjIiLCJwIjoic2hlZXRzLWppcmEifQ","HWKREPORT-3457") -> HWKREPORT-3457 | C74: All full field cameras in V2 crash at the same time | D74: P2 - High | E74: Open | F74: 45776.742 | G74: =HYPERLINK("https://hawk-eye.atlassian.net/browse/RTT-10523?atlOrigin=eyJpIjoiYzgwYTQ0ZjEyNzQzNGJhN2JmNjEyZTM0NmRhZWZhNjIiLCJwIjoic2hlZXRzLWppcmEifQ","RTT-10523") -> RTT-10523 | H74: Hawk Report | I74: Baseball | K74: MulticamAnalysis | M74: [no field found] | P74: 45776.742
A75: New Feature | B75: =HYPERLINK("https://hawk-eye.atlassian.net/browse/HWKREPORT-3458?atlOrigin=eyJpIjoiYzgwYTQ0ZjEyNzQzNGJhN2JmNjEyZTM0NmRhZWZhNjIiLCJwIjoic2hlZXRzLWppcmEifQ","HWKREPORT-3458") -> HWKREPORT-3458 | C75: UEFA Clip Delivery Timeline markers to be visible for all operations | D75: P5 - Lowest | E75: Open | F75: 45777.429 | G75: =HYPERLINK("https://hawk-eye.atlassian.net/browse/SO-2471?atlOrigin=eyJpIjoiYzgwYTQ0ZjEyNzQzNGJhN2JmNjEyZTM0NmRhZWZhNjIiLCJwIjoic2hlZXRzLWppcmEifQ","SO-2471") -> SO-2471 | H75: Hawk Report | I75: Football | K75: SMARTViewer | M75: [no field found] | P75: 45777.429
A76: New Feature | B76: =HYPERLINK("https://hawk-eye.atlassian.net/browse/HWKREPORT-3459?atlOrigin=eyJpIjoiYzgwYTQ0ZjEyNzQzNGJhN2JmNjEyZTM0NmRhZWZhNjIiLCJwIjoic2hlZXRzLWppcmEifQ","HWKREPORT-3459") -> HWKREPORT-3459 | C76: Include the ability to ingest data from 9th and 10th videocapture | D76: P5 - Lowest | E76: Open | F76: 45777.674 | G76: =HYPERLINK("https://hawk-eye.atlassian.net/browse/?atlOrigin=eyJpIjoiYzgwYTQ0ZjEyNzQzNGJhN2JmNjEyZTM0NmRhZWZhNjIiLCJwIjoic2hlZXRzLWppcmEifQ","") | H76: Hawk Report | I76: Cricket | K76: ProcessingControl | M76: [no field found] | P76: 45777.674
A77: New Feature | B77: =HYPERLINK("https://hawk-eye.atlassian.net/browse/HWKREPORT-3460?atlOrigin=eyJpIjoiYzgwYTQ0ZjEyNzQzNGJhN2JmNjEyZTM0NmRhZWZhNjIiLCJwIjoic2hlZXRzLWppcmEifQ","HWKREPORT-3460") -> HWKREPORT-3460 | C77: Additional trackIds (with no personId) present in all centroids and joints feeds in Java (but not C#) | D77: P5 - Lowest | E77: Open | F77: 45777.788 | G77: =HYPERLINK("https://hawk-eye.atlassian.net/browse/?atlOrigin=eyJpIjoiYzgwYTQ0ZjEyNzQzNGJhN2JmNjEyZTM0NmRhZWZhNjIiLCJwIjoic2hlZXRzLWppcmEifQ","") | H77: Hawk Report | I77: Football | K77: FootballDataPlatform | M77: [no field found] | P77: 45777.788
A78: New Feature | B78: =HYPERLINK("https://hawk-eye.atlassian.net/browse/HWKREPORT-3461?atlOrigin=eyJpIjoiYzgwYTQ0ZjEyNzQzNGJhN2JmNjEyZTM0NmRhZWZhNjIiLCJwIjoic2hlZXRzLWppcmEifQ","HWKREPORT-3461") -> HWKREPORT-3461 | C78: C# using mph/mps = 0 where Java is { } for speed and distance when values are 0/null in centroids samples | D78: P5 - Lowest | E78: Open | F78: 45777.801 | G78: =HYPERLINK("https://hawk-eye.atlassian.net/browse/?atlOrigin=eyJpIjoiYzgwYTQ0ZjEyNzQzNGJhN2JmNjEyZTM0NmRhZWZhNjIiLCJwIjoic2hlZXRzLWppcmEifQ","") | H78: Hawk Report | I78: Football | K78: FootballDataPlatform | M78: [no field found] | P78: 45777.801
A79: New Feature | B79: =HYPERLINK("https://hawk-eye.atlassian.net/browse/HWKREPORT-3462?atlOrigin=eyJpIjoiYzgwYTQ0ZjEyNzQzNGJhN2JmNjEyZTM0NmRhZWZhNjIiLCJwIjoic2hlZXRzLWppcmEifQ","HWKREPORT-3462") -> HWKREPORT-3462 | C79: Roles in samples feeds not matching between details and samples sections | D79: P5 - Lowest | E79: Open | F79: 45777.809 | G79: =HYPERLINK("https://hawk-eye.atlassian.net/browse/?atlOrigin=eyJpIjoiYzgwYTQ0ZjEyNzQzNGJhN2JmNjEyZTM0NmRhZWZhNjIiLCJwIjoic2hlZXRzLWppcmEifQ","") | H79: Hawk Report | I79: Football | K79: FootballDataPlatform | M79: [no field found] | P79: 45777.809
A80: New Feature | B80: =HYPERLINK("https://hawk-eye.atlassian.net/browse/HWKREPORT-3463?atlOrigin=eyJpIjoiYzgwYTQ0ZjEyNzQzNGJhN2JmNjEyZTM0NmRhZWZhNjIiLCJwIjoic2hlZXRzLWppcmEifQ","HWKREPORT-3463") -> HWKREPORT-3463 | C80: Ability for Cortex to ignore feeds | D80: P5 - Lowest | E80: Open | F80: 45778.806 | G80: =HYPERLINK("https://hawk-eye.atlassian.net/browse/?atlOrigin=eyJpIjoiYzgwYTQ0ZjEyNzQzNGJhN2JmNjEyZTM0NmRhZWZhNjIiLCJwIjoic2hlZXRzLWppcmEifQ","") | H80: Hawk Report | I80: American Football;Ice Hockey | K80: Cortex | M80: [no field found] | P80: 45778.806
A81: New Feature | B81: =HYPERLINK("https://hawk-eye.atlassian.net/browse/HWKREPORT-3464?atlOrigin=eyJpIjoiYzgwYTQ0ZjEyNzQzNGJhN2JmNjEyZTM0NmRhZWZhNjIiLCJwIjoic2hlZXRzLWppcmEifQ","HWKREPORT-3464") -> HWKREPORT-3464 | C81: qty (number of instances) are significantly different between C# & Java despite time, distances & percentages in acceptable ranges | D81: P5 - Lowest | E81: Open | F81: 45779.591 | G81: =HYPERLINK("https://hawk-eye.atlassian.net/browse/?atlOrigin=eyJpIjoiYzgwYTQ0ZjEyNzQzNGJhN2JmNjEyZTM0NmRhZWZhNjIiLCJwIjoic2hlZXRzLWppcmEifQ","") | H81: Hawk Report | I81: Football | K81: FootballDataPlatform | M81: [no field found] | P81: 45779.591
A82: New Feature | B82: =HYPERLINK("https://hawk-eye.atlassian.net/browse/HWKREPORT-3465?atlOrigin=eyJpIjoiYzgwYTQ0ZjEyNzQzNGJhN2JmNjEyZTM0NmRhZWZhNjIiLCJwIjoic2hlZXRzLWppcmEifQ","HWKREPORT-3465") -> HWKREPORT-3465 | C82: In Java, scrubbed data is significantly less than delayed data and not matching % differences to C# | D82: P5 - Lowest | E82: Open | F82: 45779.598 | G82: =HYPERLINK("https://hawk-eye.atlassian.net/browse/?atlOrigin=eyJpIjoiYzgwYTQ0ZjEyNzQzNGJhN2JmNjEyZTM0NmRhZWZhNjIiLCJwIjoic2hlZXRzLWppcmEifQ","") | H82: Hawk Report | I82: Football | K82: FootballDataPlatform | M82: [no field found] | P82: 45779.598
A83: New Feature | B83: =HYPERLINK("https://hawk-eye.atlassian.net/browse/HWKREPORT-3466?atlOrigin=eyJpIjoiYzgwYTQ0ZjEyNzQzNGJhN2JmNjEyZTM0NmRhZWZhNjIiLCJwIjoic2hlZXRzLWppcmEifQ","HWKREPORT-3466") -> HWKREPORT-3466 | C83: max_speed significantly higher in Java vs C# | D83: P5 - Lowest | E83: Open | F83: 45779.606 | G83: =HYPERLINK("https://hawk-eye.atlassian.net/browse/?atlOrigin=eyJpIjoiYzgwYTQ0ZjEyNzQzNGJhN2JmNjEyZTM0NmRhZWZhNjIiLCJwIjoic2hlZXRzLWppcmEifQ","") | H83: Hawk Report | I83: Football | K83: FootballDataPlatform | M83: [no field found] | P83: 45779.606
A84: Bug | B84: =HYPERLINK("https://hawk-eye.atlassian.net/browse/HWKREPORT-3467?atlOrigin=eyJpIjoiYzgwYTQ0ZjEyNzQzNGJhN2JmNjEyZTM0NmRhZWZhNjIiLCJwIjoic2hlZXRzLWppcmEifQ","HWKREPORT-3467") -> HWKREPORT-3467 | C84: BMCA Crash - 5/1/2025 | D84: P1 - Highest | E84: Open | F84: 45779.636 | G84: =HYPERLINK("https://hawk-eye.atlassian.net/browse/?atlOrigin=eyJpIjoiYzgwYTQ0ZjEyNzQzNGJhN2JmNjEyZTM0NmRhZWZhNjIiLCJwIjoic2hlZXRzLWppcmEifQ","") | H84: Hawk Report | I84: Baseball | K84: MulticamAnalysis | M84: [no field found] | P84: 45779.636
A85: Bug | B85: =HYPERLINK("https://hawk-eye.atlassian.net/browse/HWKREPORT-3468?atlOrigin=eyJpIjoiYzgwYTQ0ZjEyNzQzNGJhN2JmNjEyZTM0NmRhZWZhNjIiLCJwIjoic2hlZXRzLWppcmEifQ","HWKREPORT-3468") -> HWKREPORT-3468 | C85: BMCC Crash - 5/1/2025 | D85: P1 - Highest | E85: Open | F85: 45779.64 | G85: =HYPERLINK("https://hawk-eye.atlassian.net/browse/?atlOrigin=eyJpIjoiYzgwYTQ0ZjEyNzQzNGJhN2JmNjEyZTM0NmRhZWZhNjIiLCJwIjoic2hlZXRzLWppcmEifQ","") | H85: Hawk Report | I85: Baseball | K85: MulticamAnalysis | M85: [no field found] | P85: 45779.64
A86: Bug | B86: =HYPERLINK("https://hawk-eye.atlassian.net/browse/HWKREPORT-3469?atlOrigin=eyJpIjoiYzgwYTQ0ZjEyNzQzNGJhN2JmNjEyZTM0NmRhZWZhNjIiLCJwIjoic2hlZXRzLWppcmEifQ","HWKREPORT-3469") -> HWKREPORT-3469 | C86: 8K calibrations not updating; showing previous calibration | D86: P2 - High | E86: Open | F86: 45781.799 | G86: =HYPERLINK("https://hawk-eye.atlassian.net/browse/?atlOrigin=eyJpIjoiYzgwYTQ0ZjEyNzQzNGJhN2JmNjEyZTM0NmRhZWZhNjIiLCJwIjoic2hlZXRzLWppcmEifQ","") | H86: Hawk Report | I86: American Football | K86: TrackingControlUI | M86: [no field found] | P86: 45781.799
A87: Bug | B87: =HYPERLINK("https://hawk-eye.atlassian.net/browse/HWKREPORT-3470?atlOrigin=eyJpIjoiYzgwYTQ0ZjEyNzQzNGJhN2JmNjEyZTM0NmRhZWZhNjIiLCJwIjoic2hlZXRzLWppcmEifQ","HWKREPORT-3470") -> HWKREPORT-3470 | C87: Masking_Get_Polygons error every time you switch feed | D87: P4 - Low | E87: Open | F87: 45781.801 | G87: =HYPERLINK("https://hawk-eye.atlassian.net/browse/?atlOrigin=eyJpIjoiYzgwYTQ0ZjEyNzQzNGJhN2JmNjEyZTM0NmRhZWZhNjIiLCJwIjoic2hlZXRzLWppcmEifQ","") | H87: Hawk Report | I87: American Football | K87: TrackingControlUI | M87: [no field found] | P87: 45781.801
A88: New Feature | B88: =HYPERLINK("https://hawk-eye.atlassian.net/browse/HWKREPORT-3471?atlOrigin=eyJpIjoiYzgwYTQ0ZjEyNzQzNGJhN2JmNjEyZTM0NmRhZWZhNjIiLCJwIjoic2hlZXRzLWppcmEifQ","HWKREPORT-3471") -> HWKREPORT-3471 | C88: Ability to create Multiview presets / save them so they appear on load | D88: P5 - Lowest | E88: Open | F88: 45781.803 | G88: =HYPERLINK("https://hawk-eye.atlassian.net/browse/?atlOrigin=eyJpIjoiYzgwYTQ0ZjEyNzQzNGJhN2JmNjEyZTM0NmRhZWZhNjIiLCJwIjoic2hlZXRzLWppcmEifQ","") | H88: Hawk Report | I88: American Football | K88: TrackingControlUI | M88: [no field found] | P88: 45781.803
A89: Bug | B89: =HYPERLINK("https://hawk-eye.atlassian.net/browse/HWKREPORT-3472?atlOrigin=eyJpIjoiYzgwYTQ0ZjEyNzQzNGJhN2JmNjEyZTM0NmRhZWZhNjIiLCJwIjoic2hlZXRzLWppcmEifQ","HWKREPORT-3472") -> HWKREPORT-3472 | C89: No Classification cutouts / Refetch images not working | D89: P1 - Highest | E89: Open | F89: 45781.807 | G89: =HYPERLINK("https://hawk-eye.atlassian.net/browse/?atlOrigin=eyJpIjoiYzgwYTQ0ZjEyNzQzNGJhN2JmNjEyZTM0NmRhZWZhNjIiLCJwIjoic2hlZXRzLWppcmEifQ","") | H89: Hawk Report | I89: American Football | K89: TrackingControlUI | M89: [no field found] | P89: 45781.807
A90: Bug | B90: =HYPERLINK("https://hawk-eye.atlassian.net/browse/HWKREPORT-3473?atlOrigin=eyJpIjoiYzgwYTQ0ZjEyNzQzNGJhN2JmNjEyZTM0NmRhZWZhNjIiLCJwIjoic2hlZXRzLWppcmEifQ","HWKREPORT-3473") -> HWKREPORT-3473 | C90: Unsure if 120fps feeds are tracking at 60fps | D90: P2 - High | E90: Open | F90: 45781.81 | G90: =HYPERLINK("https://hawk-eye.atlassian.net/browse/?atlOrigin=eyJpIjoiYzgwYTQ0ZjEyNzQzNGJhN2JmNjEyZTM0NmRhZWZhNjIiLCJwIjoic2hlZXRzLWppcmEifQ","") | H90: Hawk Report | I90: American Football | K90: Cortex | M90: [no field found] | P90: 45781.81
A91: Bug | B91: =HYPERLINK("https://hawk-eye.atlassian.net/browse/HWKREPORT-3474?atlOrigin=eyJpIjoiYzgwYTQ0ZjEyNzQzNGJhN2JmNjEyZTM0NmRhZWZhNjIiLCJwIjoic2hlZXRzLWppcmEifQ","HWKREPORT-3474") -> HWKREPORT-3474 | C91: BMCA Crash - 5/5/2025 | D91: P1 - Highest | E91: Open | F91: 45782.619 | G91: =HYPERLINK("https://hawk-eye.atlassian.net/browse/?atlOrigin=eyJpIjoiYzgwYTQ0ZjEyNzQzNGJhN2JmNjEyZTM0NmRhZWZhNjIiLCJwIjoic2hlZXRzLWppcmEifQ","") | H91: Hawk Report | I91: Baseball | K91: MulticamAnalysis | M91: [no field found] | P91: 45782.619
A92: New Feature | B92: =HYPERLINK("https://hawk-eye.atlassian.net/browse/HWKREPORT-3475?atlOrigin=eyJpIjoiYzgwYTQ0ZjEyNzQzNGJhN2JmNjEyZTM0NmRhZWZhNjIiLCJwIjoic2hlZXRzLWppcmEifQ","HWKREPORT-3475") -> HWKREPORT-3475 | C92: Request Coppa Italia Final Ball 24/25 | D92: P1 - Highest | E92: Open | F92: 45782.658 | G92: =HYPERLINK("https://hawk-eye.atlassian.net/browse/?atlOrigin=eyJpIjoiYzgwYTQ0ZjEyNzQzNGJhN2JmNjEyZTM0NmRhZWZhNjIiLCJwIjoic2hlZXRzLWppcmEifQ","") | H92: Hawk Report | I92: Football | M92: [no field found] | P92: 45782.658
A93: Bug | B93: =HYPERLINK("https://hawk-eye.atlassian.net/browse/HWKREPORT-3476?atlOrigin=eyJpIjoiYzgwYTQ0ZjEyNzQzNGJhN2JmNjEyZTM0NmRhZWZhNjIiLCJwIjoic2hlZXRzLWppcmEifQ","HWKREPORT-3476") -> HWKREPORT-3476 | C93: BMCA Crash - 5/5/2025 | D93: P1 - Highest | E93: Open | F93: 45782.736 | G93: =HYPERLINK("https://hawk-eye.atlassian.net/browse/?atlOrigin=eyJpIjoiYzgwYTQ0ZjEyNzQzNGJhN2JmNjEyZTM0NmRhZWZhNjIiLCJwIjoic2hlZXRzLWppcmEifQ","") | H93: Hawk Report | I93: Baseball | K93: MulticamAnalysis | M93: [no field found] | P93: 45782.736
A94: Bug | B94: =HYPERLINK("https://hawk-eye.atlassian.net/browse/HWKREPORT-3477?atlOrigin=eyJpIjoiYzgwYTQ0ZjEyNzQzNGJhN2JmNjEyZTM0NmRhZWZhNjIiLCJwIjoic2hlZXRzLWppcmEifQ","HWKREPORT-3477") -> HWKREPORT-3477 | C94: CameraControl and Analysis not launching from after RodLaverArena_D_RC1 for both Badminton and Volleyball (Win10 & Win11) | D94: P2 - High | E94: Open | F94: 45783.459 | G94: =HYPERLINK("https://hawk-eye.atlassian.net/browse/?atlOrigin=eyJpIjoiYzgwYTQ0ZjEyNzQzNGJhN2JmNjEyZTM0NmRhZWZhNjIiLCJwIjoic2hlZXRzLWppcmEifQ","") | H94: Hawk Report | I94: Badminton;Volleyball | K94: Analysis;CameraControl | M94: [no field found] | P94: 45783.459
A95: Bug | B95: =HYPERLINK("https://hawk-eye.atlassian.net/browse/HWKREPORT-3478?atlOrigin=eyJpIjoiYzgwYTQ0ZjEyNzQzNGJhN2JmNjEyZTM0NmRhZWZhNjIiLCJwIjoic2hlZXRzLWppcmEifQ","HWKREPORT-3478") -> HWKREPORT-3478 | C95: Show Image showing at the bottom of the UI, not the right | D95: P5 - Lowest | E95: Open | F95: 45783.47 | G95: =HYPERLINK("https://hawk-eye.atlassian.net/browse/?atlOrigin=eyJpIjoiYzgwYTQ0ZjEyNzQzNGJhN2JmNjEyZTM0NmRhZWZhNjIiLCJwIjoic2hlZXRzLWppcmEifQ","") | H95: Hawk Report | I95: Football | K95: OffsideLine | M95: [no field found] | P95: 45783.47
A96: Bug | B96: =HYPERLINK("https://hawk-eye.atlassian.net/browse/HWKREPORT-3479?atlOrigin=eyJpIjoiYzgwYTQ0ZjEyNzQzNGJhN2JmNjEyZTM0NmRhZWZhNjIiLCJwIjoic2hlZXRzLWppcmEifQ","HWKREPORT-3479") -> HWKREPORT-3479 | C96: Upgrades to various dependencies to support 50 series NVIDIA GPUs | D96: P2 - High | E96: Open | F96: 45783.634 | G96: =HYPERLINK("https://hawk-eye.atlassian.net/browse/?atlOrigin=eyJpIjoiYzgwYTQ0ZjEyNzQzNGJhN2JmNjEyZTM0NmRhZWZhNjIiLCJwIjoic2hlZXRzLWppcmEifQ","") | H96: Hawk Report | I96: Football | K96: MulticamAnalysis | M96: [no field found] | P96: 45783.634
A97: New Feature | B97: =HYPERLINK("https://hawk-eye.atlassian.net/browse/HWKREPORT-3480?atlOrigin=eyJpIjoiYzgwYTQ0ZjEyNzQzNGJhN2JmNjEyZTM0NmRhZWZhNjIiLCJwIjoic2hlZXRzLWppcmEifQ","HWKREPORT-3480") -> HWKREPORT-3480 | C97: Can we have the ability to set the save location of the .png files created by the Output_Grab function in SMARTViewer? | D97: P5 - Lowest | E97: Open | F97: 45783.711 | G97: =HYPERLINK("https://hawk-eye.atlassian.net/browse/?atlOrigin=eyJpIjoiYzgwYTQ0ZjEyNzQzNGJhN2JmNjEyZTM0NmRhZWZhNjIiLCJwIjoic2hlZXRzLWppcmEifQ","") | H97: Hawk Report | I97: Horse Racing;Motorsport | K97: SMARTViewer | M97: [no field found] | P97: 45783.711
A98: Bug | B98: =HYPERLINK("https://hawk-eye.atlassian.net/browse/HWKREPORT-3481?atlOrigin=eyJpIjoiYzgwYTQ0ZjEyNzQzNGJhN2JmNjEyZTM0NmRhZWZhNjIiLCJwIjoic2hlZXRzLWppcmEifQ","HWKREPORT-3481") -> HWKREPORT-3481 | C98: NHL Tracking | Zoom bug in TrackingControlUI - Timeline Detaches from UI in Full Screen | D98: P4 - Low | E98: Open | F98: 45783.743 | G98: =HYPERLINK("https://hawk-eye.atlassian.net/browse/CTF-1548?atlOrigin=eyJpIjoiYzgwYTQ0ZjEyNzQzNGJhN2JmNjEyZTM0NmRhZWZhNjIiLCJwIjoic2hlZXRzLWppcmEifQ","CTF-1548") -> CTF-1548 | H98: Hawk Report | I98: Ice Hockey | K98: TrackingControlUI | M98: [no field found] | P98: 45783.743
A99: New Feature | B99: =HYPERLINK("https://hawk-eye.atlassian.net/browse/HWKREPORT-3482?atlOrigin=eyJpIjoiYzgwYTQ0ZjEyNzQzNGJhN2JmNjEyZTM0NmRhZWZhNjIiLCJwIjoic2hlZXRzLWppcmEifQ","HWKREPORT-3482") -> HWKREPORT-3482 | C99: NHL Tracking | 2D Top Down View - Ability to Move the Model rather than Just Zoom In and Out | D99: P4 - Low | E99: Open | F99: 45783.797 | G99: =HYPERLINK("https://hawk-eye.atlassian.net/browse/CTF-1546?atlOrigin=eyJpIjoiYzgwYTQ0ZjEyNzQzNGJhN2JmNjEyZTM0NmRhZWZhNjIiLCJwIjoic2hlZXRzLWppcmEifQ","CTF-1546") -> CTF-1546 | H99: Hawk Report | I99: Ice Hockey | K99: NHL Tracking;TrackingControlUI | M99: [no field found] | P99: 45783.797
A100: Bug | B100: =HYPERLINK("https://hawk-eye.atlassian.net/browse/HWKREPORT-3483?atlOrigin=eyJpIjoiYzgwYTQ0ZjEyNzQzNGJhN2JmNjEyZTM0NmRhZWZhNjIiLCJwIjoic2hlZXRzLWppcmEifQ","HWKREPORT-3483") -> HWKREPORT-3483 | C100: NHL Tracking | 2D Read Usage Reaching Provisioning Limit | D100: P2 - High | E100: Open | F100: 45783.821 | G100: =HYPERLINK("https://hawk-eye.atlassian.net/browse/?atlOrigin=eyJpIjoiYzgwYTQ0ZjEyNzQzNGJhN2JmNjEyZTM0NmRhZWZhNjIiLCJwIjoic2hlZXRzLWppcmEifQ","") | H100: Hawk Report | I100: Ice Hockey | K100: NHL Tracking | M100: [no field found] | P100: 45783.821
...

Sheet buildReport
B1: testmo
B2: Case ID | C2: Priority | D2: complexity | E2: Impact of failure | F2: Likelihood of failure | G2: can be automated | H2: Automation status | I2: Status (latest) | J2: Release | K2: Issues
B3: ='testmo-export-repository'!A2 -> 1110 | C3: {=IFERROR(INDEX('testmo-export-repository'!$B$2:$X$1000,MATCH($B3,'testmo-export-repository'!$A$2:$A$1000,false),MATCH(C$2,'testmo-export-repository'!$B$1:$X$1,false)),"")} -> High | D3: {=IFERROR(INDEX('testmo-export-repository'!$B$2:$X$1000,MATCH($B3,'testmo-export-repository'!$A$2:$A$1000,false),MATCH(D$2,'testmo-export-repository'!$B$1:$X$1,false)),"")} -> Low | E3: =IFERROR(VLOOKUP($C3,instructions!$N$3:$O$5,2,false),"") -> 1 | F3: =IFERROR(VLOOKUP($D3,instructions!$N$3:$O$5,2,false),"") -> 3 | G3: {=IFERROR(INDEX('testmo-export-repository'!$B$2:$X$1000,MATCH($B3,'testmo-export-repository'!$A$2:$A$1000,false),MATCH(G$2,'testmo-export-repository'!$B$1:$Y$1,false)),"")} -> Yes | H3: {=IFERROR(INDEX('testmo-export-repository'!$B$2:$X$1000,MATCH($B3,'testmo-export-repository'!$A$2:$A$1000,false),MATCH(H$2,'testmo-export-repository'!$B$1:$Y$1,false)),"")} -> No | I3: {=IFERROR(INDEX('testmo-export-repository'!$B$2:$X$1000,MATCH($B3,'testmo-export-repository'!$A$2:$A$1000,false),MATCH(I$2,'testmo-export-repository'!$B$1:$Y$1,false)),"")} -> Passed | J3: {=IFERROR(INDEX('testmo-export-repository'!$B$2:$Y$1000,MATCH($B3,'testmo-export-repository'!$A$2:$A$1000,false),MATCH(J$2,'testmo-export-repository'!$B$1:$Y$1,false)),"")} | K3: {=IFERROR(INDEX('testmo-export-repository'!$B$2:$Y$1000,MATCH($B3,'testmo-export-repository'!$A$2:$A$1000,false),MATCH(K$2,'testmo-export-repository'!$B$1:$Y$1,false)),"")} -> BAS-474
B4: ='testmo-export-repository'!A3 -> 2033 | C4: {=IFERROR(INDEX('testmo-export-repository'!$B$2:$X$1000,MATCH($B4,'testmo-export-repository'!$A$2:$A$1000,false),MATCH(C$2,'testmo-export-repository'!$B$1:$X$1,false)),"")} -> High | D4: {=IFERROR(INDEX('testmo-export-repository'!$B$2:$X$1000,MATCH($B4,'testmo-export-repository'!$A$2:$A$1000,false),MATCH(D$2,'testmo-export-repository'!$B$1:$X$1,false)),"")} -> Normal | E4: =IFERROR(VLOOKUP($C4,instructions!$N$3:$O$5,2,false),"") -> 1 | F4: =IFERROR(VLOOKUP($D4,instructions!$N$3:$O$5,2,false),"") -> 2 | G4: {=IFERROR(INDEX('testmo-export-repository'!$B$2:$X$1000,MATCH($B4,'testmo-export-repository'!$A$2:$A$1000,false),MATCH(G$2,'testmo-export-repository'!$B$1:$X$1,false)),"")} -> Yes | H4: {=IFERROR(INDEX('testmo-export-repository'!$B$2:$X$1000,MATCH($B4,'testmo-export-repository'!$A$2:$A$1000,false),MATCH(H$2,'testmo-export-repository'!$B$1:$X$1,false)),"")} -> Yes | I4: {=IFERROR(INDEX('testmo-export-repository'!$B$2:$X$1000,MATCH($B4,'testmo-export-repository'!$A$2:$A$1000,false),MATCH(I$2,'testmo-export-repository'!$B$1:$X$1,false)),"")} | J4: {=IFERROR(INDEX('testmo-export-repository'!$B$2:$Y$1000,MATCH($B4,'testmo-export-repository'!$A$2:$A$1000,false),MATCH(J$2,'testmo-export-repository'!$B$1:$Y$1,false)),"")} | K4: {=IFERROR(INDEX('testmo-export-repository'!$B$2:$Y$1000,MATCH($B4,'testmo-export-repository'!$A$2:$A$1000,false),MATCH(K$2,'testmo-export-repository'!$B$1:$Y$1,false)),"")} -> BAS-121
B5: ='testmo-export-repository'!A4 -> 2034 | C5: {=IFERROR(INDEX('testmo-export-repository'!$B$2:$X$1000,MATCH($B5,'testmo-export-repository'!$A$2:$A$1000,false),MATCH(C$2,'testmo-export-repository'!$B$1:$X$1,false)),"")} -> Normal | D5: {=IFERROR(INDEX('testmo-export-repository'!$B$2:$X$1000,MATCH($B5,'testmo-export-repository'!$A$2:$A$1000,false),MATCH(D$2,'testmo-export-repository'!$B$1:$X$1,false)),"")} -> Normal | E5: =IFERROR(VLOOKUP($C5,instructions!$N$3:$O$5,2,false),"") -> 2 | F5: =IFERROR(VLOOKUP($D5,instructions!$N$3:$O$5,2,false),"") -> 2 | G5: {=IFERROR(INDEX('testmo-export-repository'!$B$2:$X$1000,MATCH($B5,'testmo-export-repository'!$A$2:$A$1000,false),MATCH(G$2,'testmo-export-repository'!$B$1:$X$1,false)),"")} -> No | H5: {=IFERROR(INDEX('testmo-export-repository'!$B$2:$X$1000,MATCH($B5,'testmo-export-repository'!$A$2:$A$1000,false),MATCH(H$2,'testmo-export-repository'!$B$1:$X$1,false)),"")} -> No | I5: {=IFERROR(INDEX('testmo-export-repository'!$B$2:$X$1000,MATCH($B5,'testmo-export-repository'!$A$2:$A$1000,false),MATCH(I$2,'testmo-export-repository'!$B$1:$X$1,false)),"")} | J5: {=IFERROR(INDEX('testmo-export-repository'!$B$2:$Y$1000,MATCH($B5,'testmo-export-repository'!$A$2:$A$1000,false),MATCH(J$2,'testmo-export-repository'!$B$1:$Y$1,false)),"")} | K5: {=IFERROR(INDEX('testmo-export-repository'!$B$2:$Y$1000,MATCH($B5,'testmo-export-repository'!$A$2:$A$1000,false),MATCH(K$2,'testmo-export-repository'!$B$1:$Y$1,false)),"")} -> BAS-121
B6: ='testmo-export-repository'!A5 -> 2044 | C6: {=IFERROR(INDEX('testmo-export-repository'!$B$2:$X$1000,MATCH($B6,'testmo-export-repository'!$A$2:$A$1000,false),MATCH(C$2,'testmo-export-repository'!$B$1:$X$1,false)),"")} -> High | D6: {=IFERROR(INDEX('testmo-export-repository'!$B$2:$X$1000,MATCH($B6,'testmo-export-repository'!$A$2:$A$1000,false),MATCH(D$2,'testmo-export-repository'!$B$1:$X$1,false)),"")} -> Normal | E6: =IFERROR(VLOOKUP($C6,instructions!$N$3:$O$5,2,false),"") -> 1 | F6: =IFERROR(VLOOKUP($D6,instructions!$N$3:$O$5,2,false),"") -> 2 | G6: {=IFERROR(INDEX('testmo-export-repository'!$B$2:$X$1000,MATCH($B6,'testmo-export-repository'!$A$2:$A$1000,false),MATCH(G$2,'testmo-export-repository'!$B$1:$X$1,false)),"")} -> Yes | H6: {=IFERROR(INDEX('testmo-export-repository'!$B$2:$X$1000,MATCH($B6,'testmo-export-repository'!$A$2:$A$1000,false),MATCH(H$2,'testmo-export-repository'!$B$1:$X$1,false)),"")} -> Yes | I6: {=IFERROR(INDEX('testmo-export-repository'!$B$2:$X$1000,MATCH($B6,'testmo-export-repository'!$A$2:$A$1000,false),MATCH(I$2,'testmo-export-repository'!$B$1:$X$1,false)),"")} | J6: {=IFERROR(INDEX('testmo-export-repository'!$B$2:$Y$1000,MATCH($B6,'testmo-export-repository'!$A$2:$A$1000,false),MATCH(J$2,'testmo-export-repository'!$B$1:$Y$1,false)),"")} | K6: {=IFERROR(INDEX('testmo-export-repository'!$B$2:$Y$1000,MATCH($B6,'testmo-export-repository'!$A$2:$A$1000,false),MATCH(K$2,'testmo-export-repository'!$B$1:$Y$1,false)),"")} -> BAS-121
B7: ='testmo-export-repository'!A6 -> 2247 | C7: {=IFERROR(INDEX('testmo-export-repository'!$B$2:$X$1000,MATCH($B7,'testmo-export-repository'!$A$2:$A$1000,false),MATCH(C$2,'testmo-export-repository'!$B$1:$X$1,false)),"")} -> High | D7: {=IFERROR(INDEX('testmo-export-repository'!$B$2:$X$1000,MATCH($B7,'testmo-export-repository'!$A$2:$A$1000,false),MATCH(D$2,'testmo-export-repository'!$B$1:$X$1,false)),"")} -> High | E7: =IFERROR(VLOOKUP($C7,instructions!$N$3:$O$5,2,false),"") -> 1 | F7: =IFERROR(VLOOKUP($D7,instructions!$N$3:$O$5,2,false),"") -> 1 | G7: {=IFERROR(INDEX('testmo-export-repository'!$B$2:$X$1000,MATCH($B7,'testmo-export-repository'!$A$2:$A$1000,false),MATCH(G$2,'testmo-export-repository'!$B$1:$X$1,false)),"")} -> Yes | H7: {=IFERROR(INDEX('testmo-export-repository'!$B$2:$X$1000,MATCH($B7,'testmo-export-repository'!$A$2:$A$1000,false),MATCH(H$2,'testmo-export-repository'!$B$1:$X$1,false)),"")} -> No | I7: {=IFERROR(INDEX('testmo-export-repository'!$B$2:$X$1000,MATCH($B7,'testmo-export-repository'!$A$2:$A$1000,false),MATCH(I$2,'testmo-export-repository'!$B$1:$X$1,false)),"")} | J7: {=IFERROR(INDEX('testmo-export-repository'!$B$2:$Y$1000,MATCH($B7,'testmo-export-repository'!$A$2:$A$1000,false),MATCH(J$2,'testmo-export-repository'!$B$1:$Y$1,false)),"")} | K7: {=IFERROR(INDEX('testmo-export-repository'!$B$2:$Y$1000,MATCH($B7,'testmo-export-repository'!$A$2:$A$1000,false),MATCH(K$2,'testmo-export-repository'!$B$1:$Y$1,false)),"")}
B8: ='testmo-export-repository'!A7 -> 2248 | C8: {=IFERROR(INDEX('testmo-export-repository'!$B$2:$X$1000,MATCH($B8,'testmo-export-repository'!$A$2:$A$1000,false),MATCH(C$2,'testmo-export-repository'!$B$1:$X$1,false)),"")} -> High | D8: {=IFERROR(INDEX('testmo-export-repository'!$B$2:$X$1000,MATCH($B8,'testmo-export-repository'!$A$2:$A$1000,false),MATCH(D$2,'testmo-export-repository'!$B$1:$X$1,false)),"")} -> High | E8: =IFERROR(VLOOKUP($C8,instructions!$N$3:$O$5,2,false),"") -> 1 | F8: =IFERROR(VLOOKUP($D8,instructions!$N$3:$O$5,2,false),"") -> 1 | G8: {=IFERROR(INDEX('testmo-export-repository'!$B$2:$X$1000,MATCH($B8,'testmo-export-repository'!$A$2:$A$1000,false),MATCH(G$2,'testmo-export-repository'!$B$1:$X$1,false)),"")} -> Yes | H8: {=IFERROR(INDEX('testmo-export-repository'!$B$2:$X$1000,MATCH($B8,'testmo-export-repository'!$A$2:$A$1000,false),MATCH(H$2,'testmo-export-repository'!$B$1:$X$1,false)),"")} -> No | I8: {=IFERROR(INDEX('testmo-export-repository'!$B$2:$X$1000,MATCH($B8,'testmo-export-repository'!$A$2:$A$1000,false),MATCH(I$2,'testmo-export-repository'!$B$1:$X$1,false)),"")} | J8: {=IFERROR(INDEX('testmo-export-repository'!$B$2:$Y$1000,MATCH($B8,'testmo-export-repository'!$A$2:$A$1000,false),MATCH(J$2,'testmo-export-repository'!$B$1:$Y$1,false)),"")} | K8: {=IFERROR(INDEX('testmo-export-repository'!$B$2:$Y$1000,MATCH($B8,'testmo-export-repository'!$A$2:$A$1000,false),MATCH(K$2,'testmo-export-repository'!$B$1:$Y$1,false)),"")}
